Workbook

Sheet Corpus B
A1: File | B1: Title | C1: Year | D1: Serie | E1: Volume | F1: Language | G1: City | H1: Country | I1: Matches
A2: AMP1834s1v26 | B2: Annales de la médecine physiologique | C2: 1834 | D2: 1 | E2: 26 | F2: French | G2: Paris | H2: France | I2: =_xlfn.LET(_xlpm.id,TRIM($A2),IF(_xlpm.id="","",SUM(COUNTIF('1. OP'!$M:$M,_xlpm.id),COUNTIF('2. JSEL'!$M:$M,_xlpm.id),COUNTIF('3. PSM'!$M:$M,_xlpm.id),COUNTIF('4. SSP'!$M:$M,_xlpm.id),COUNTIF('5. JSACI'!$M:$M,_xlpm.id),COUNTIF('6. AIN'!$M:$M,_xlpm.id),COUNTIF('7. MS'!$M:$M,_xlpm.id),COUNTIF('8. DS'!$M:$M,_xlpm.id),COUNTIF('9. RMF'!$M:$M,_xlpm.id),COUNTIF('10. PCU'!$M:$M,_xlpm.id)))) -> 1
A3: AMP1834s1v25 | B3: Annales de la médecine physiologique | C3: 1834 | D3: 1 | E3: 25 | F3: French | G3: Paris | H3: France | I3: =_xlfn.LET(_xlpm.id,TRIM($A3),IF(_xlpm.id="","",SUM(COUNTIF('1. OP'!$M:$M,_xlpm.id),COUNTIF('2. JSEL'!$M:$M,_xlpm.id),COUNTIF('3. PSM'!$M:$M,_xlpm.id),COUNTIF('4. SSP'!$M:$M,_xlpm.id),COUNTIF('5. JSACI'!$M:$M,_xlpm.id),COUNTIF('6. AIN'!$M:$M,_xlpm.id),COUNTIF('7. MS'!$M:$M,_xlpm.id),COUNTIF('8. DS'!$M:$M,_xlpm.id),COUNTIF('9. RMF'!$M:$M,_xlpm.id),COUNTIF('10. PCU'!$M:$M,_xlpm.id)))) -> 0
A4: AMP1833s1v23 | B4: Annales de la médecine physiologique | C4: 1833 | D4: 1 | E4: 24 | F4: French | G4: Paris | H4: France | I4: =_xlfn.LET(_xlpm.id,TRIM($A4),IF(_xlpm.id="","",SUM(COUNTIF('1. OP'!$M:$M,_xlpm.id),COUNTIF('2. JSEL'!$M:$M,_xlpm.id),COUNTIF('3. PSM'!$M:$M,_xlpm.id),COUNTIF('4. SSP'!$M:$M,_xlpm.id),COUNTIF('5. JSACI'!$M:$M,_xlpm.id),COUNTIF('6. AIN'!$M:$M,_xlpm.id),COUNTIF('7. MS'!$M:$M,_xlpm.id),COUNTIF('8. DS'!$M:$M,_xlpm.id),COUNTIF('9. RMF'!$M:$M,_xlpm.id),COUNTIF('10. PCU'!$M:$M,_xlpm.id)))) -> 0
A5: AMP1833s1v24 | B5: Annales de la médecine physiologique | C5: 1833 | D5: 1 | E5: 23 | F5: French | G5: Paris | H5: France | I5: =_xlfn.LET(_xlpm.id,TRIM($A5),IF(_xlpm.id="","",SUM(COUNTIF('1. OP'!$M:$M,_xlpm.id),COUNTIF('2. JSEL'!$M:$M,_xlpm.id),COUNTIF('3. PSM'!$M:$M,_xlpm.id),COUNTIF('4. SSP'!$M:$M,_xlpm.id),COUNTIF('5. JSACI'!$M:$M,_xlpm.id),COUNTIF('6. AIN'!$M:$M,_xlpm.id),COUNTIF('7. MS'!$M:$M,_xlpm.id),COUNTIF('8. DS'!$M:$M,_xlpm.id),COUNTIF('9. RMF'!$M:$M,_xlpm.id),COUNTIF('10. PCU'!$M:$M,_xlpm.id)))) -> 0
A6: AMP1832s1v22 | B6: Annales de la médecine physiologique | C6: 1832 | D6: 1 | E6: 22 | F6: French | G6: Paris | H6: France | I6: =_xlfn.LET(_xlpm.id,TRIM($A6),IF(_xlpm.id="","",SUM(COUNTIF('1. OP'!$M:$M,_xlpm.id),COUNTIF('2. JSEL'!$M:$M,_xlpm.id),COUNTIF('3. PSM'!$M:$M,_xlpm.id),COUNTIF('4. SSP'!$M:$M,_xlpm.id),COUNTIF('5. JSACI'!$M:$M,_xlpm.id),COUNTIF('6. AIN'!$M:$M,_xlpm.id),COUNTIF('7. MS'!$M:$M,_xlpm.id),COUNTIF('8. DS'!$M:$M,_xlpm.id),COUNTIF('9. RMF'!$M:$M,_xlpm.id),COUNTIF('10. PCU'!$M:$M,_xlpm.id)))) -> 0
A7: AMP1832s1v21 | B7: Annales de la médecine physiologique | C7: 1832 | D7: 1 | E7: 21 | F7: French | G7: Paris | H7: France | I7: =_xlfn.LET(_xlpm.id,TRIM($A7),IF(_xlpm.id="","",SUM(COUNTIF('1. OP'!$M:$M,_xlpm.id),COUNTIF('2. JSEL'!$M:$M,_xlpm.id),COUNTIF('3. PSM'!$M:$M,_xlpm.id),COUNTIF('4. SSP'!$M:$M,_xlpm.id),COUNTIF('5. JSACI'!$M:$M,_xlpm.id),COUNTIF('6. AIN'!$M:$M,_xlpm.id),COUNTIF('7. MS'!$M:$M,_xlpm.id),COUNTIF('8. DS'!$M:$M,_xlpm.id),COUNTIF('9. RMF'!$M:$M,_xlpm.id),COUNTIF('10. PCU'!$M:$M,_xlpm.id)))) -> 0
A8: AMP1831s1v20 | B8: Annales de la médecine physiologique | C8: 1831 | D8: 1 | E8: 20 | F8: French | G8: Paris | H8: France | I8: =_xlfn.LET(_xlpm.id,TRIM($A8),IF(_xlpm.id="","",SUM(COUNTIF('1. OP'!$M:$M,_xlpm.id),COUNTIF('2. JSEL'!$M:$M,_xlpm.id),COUNTIF('3. PSM'!$M:$M,_xlpm.id),COUNTIF('4. SSP'!$M:$M,_xlpm.id),COUNTIF('5. JSACI'!$M:$M,_xlpm.id),COUNTIF('6. AIN'!$M:$M,_xlpm.id),COUNTIF('7. MS'!$M:$M,_xlpm.id),COUNTIF('8. DS'!$M:$M,_xlpm.id),COUNTIF('9. RMF'!$M:$M,_xlpm.id),COUNTIF('10. PCU'!$M:$M,_xlpm.id)))) -> 1
A9: AMP1831s1v19 | B9: Annales de la médecine physiologique | C9: 1831 | D9: 1 | E9: 19 | F9: French | G9: Paris | H9: France | I9: =_xlfn.LET(_xlpm.id,TRIM($A9),IF(_xlpm.id="","",SUM(COUNTIF('1. OP'!$M:$M,_xlpm.id),COUNTIF('2. JSEL'!$M:$M,_xlpm.id),COUNTIF('3. PSM'!$M:$M,_xlpm.id),COUNTIF('4. SSP'!$M:$M,_xlpm.id),COUNTIF('5. JSACI'!$M:$M,_xlpm.id),COUNTIF('6. AIN'!$M:$M,_xlpm.id),COUNTIF('7. MS'!$M:$M,_xlpm.id),COUNTIF('8. DS'!$M:$M,_xlpm.id),COUNTIF('9. RMF'!$M:$M,_xlpm.id),COUNTIF('10. PCU'!$M:$M,_xlpm.id)))) -> 1
A10: AMP1830s1v18 | B10: Annales de la médecine physiologique | C10: 1830 | D10: 1 | E10: 18 | F10: French | G10: Paris | H10: France | I10: =_xlfn.LET(_xlpm.id,TRIM($A10),IF(_xlpm.id="","",SUM(COUNTIF('1. OP'!$M:$M,_xlpm.id),COUNTIF('2. JSEL'!$M:$M,_xlpm.id),COUNTIF('3. PSM'!$M:$M,_xlpm.id),COUNTIF('4. SSP'!$M:$M,_xlpm.id),COUNTIF('5. JSACI'!$M:$M,_xlpm.id),COUNTIF('6. AIN'!$M:$M,_xlpm.id),COUNTIF('7. MS'!$M:$M,_xlpm.id),COUNTIF('8. DS'!$M:$M,_xlpm.id),COUNTIF('9. RMF'!$M:$M,_xlpm.id),COUNTIF('10. PCU'!$M:$M,_xlpm.id)))) -> 0
A11: AMP1830s1v17 | B11: Annales de la médecine physiologique | C11: 1830 | D11: 1 | E11: 17 | F11: French | G11: Paris | H11: France | I11: =_xlfn.LET(_xlpm.id,TRIM($A11),IF(_xlpm.id="","",SUM(COUNTIF('1. OP'!$M:$M,_xlpm.id),COUNTIF('2. JSEL'!$M:$M,_xlpm.id),COUNTIF('3. PSM'!$M:$M,_xlpm.id),COUNTIF('4. SSP'!$M:$M,_xlpm.id),COUNTIF('5. JSACI'!$M:$M,_xlpm.id),COUNTIF('6. AIN'!$M:$M,_xlpm.id),COUNTIF('7. MS'!$M:$M,_xlpm.id),COUNTIF('8. DS'!$M:$M,_xlpm.id),COUNTIF('9. RMF'!$M:$M,_xlpm.id),COUNTIF('10. PCU'!$M:$M,_xlpm.id)))) -> 19
A12: AMP1829s1v16 | B12: Annales de la médecine physiologique | C12: 1829 | D12: 1 | E12: 16 | F12: French | G12: Paris | H12: France | I12: =_xlfn.LET(_xlpm.id,TRIM($A12),IF(_xlpm.id="","",SUM(COUNTIF('1. OP'!$M:$M,_xlpm.id),COUNTIF('2. JSEL'!$M:$M,_xlpm.id),COUNTIF('3. PSM'!$M:$M,_xlpm.id),COUNTIF('4. SSP'!$M:$M,_xlpm.id),COUNTIF('5. JSACI'!$M:$M,_xlpm.id),COUNTIF('6. AIN'!$M:$M,_xlpm.id),COUNTIF('7. MS'!$M:$M,_xlpm.id),COUNTIF('8. DS'!$M:$M,_xlpm.id),COUNTIF('9. RMF'!$M:$M,_xlpm.id),COUNTIF('10. PCU'!$M:$M,_xlpm.id)))) -> 6
A13: AMP1829s1v15 | B13: Annales de la médecine physiologique | C13: 1829 | D13: 1 | E13: 15 | F13: French | G13: Paris | H13: France | I13: =_xlfn.LET(_xlpm.id,TRIM($A13),IF(_xlpm.id="","",SUM(COUNTIF('1. OP'!$M:$M,_xlpm.id),COUNTIF('2. JSEL'!$M:$M,_xlpm.id),COUNTIF('3. PSM'!$M:$M,_xlpm.id),COUNTIF('4. SSP'!$M:$M,_xlpm.id),COUNTIF('5. JSACI'!$M:$M,_xlpm.id),COUNTIF('6. AIN'!$M:$M,_xlpm.id),COUNTIF('7. MS'!$M:$M,_xlpm.id),COUNTIF('8. DS'!$M:$M,_xlpm.id),COUNTIF('9. RMF'!$M:$M,_xlpm.id),COUNTIF('10. PCU'!$M:$M,_xlpm.id)))) -> 0
... A172: JCMP1840s2v6 | B172: Journal de chimie médicale, de pharmacie et de toxicologie | C172: 1840 | D172: 2 | E172: 6 | F172: French | G172: Paris | H172: France | I172: =_xlfn.LET(_xlpm.id,TRIM($A172),IF(_xlpm.id="","",SUM(COUNTIF('1. OP'!$M:$M,_xlpm.id),COUNTIF('2. JSEL'!$M:$M,_xlpm.id),COUNTIF('3. PSM'!$M:$M,_xlpm.id),COUNTIF('4. SSP'!$M:$M,_xlpm.id),COUNTIF('5. JSACI'!$M:$M,_xlpm.id),COUNTIF('6. AIN'!$M:$M,_xlpm.id),COUNTIF('7. MS'!$M:$M,_xlpm.id),COUNTIF('8. DS'!$M:$M,_xlpm.id),COUNTIF('9. RMF'!$M:$M,_xlpm.id),COUNTIF('10. PCU'!$M:$M,_xlpm.id)))) -> 0
A173: JCMC1833-4s1v1 | B173: Journal des Connaissances Medico Chirurgicales | C173: 1833-4 | D173: 1 | E173: 1 | F173: French | G173: Paris | H173: France | I173: =_xlfn.LET(_xlpm.id,TRIM($A173),IF(_xlpm.id="","",SUM(COUNTIF('1. OP'!$M:$M,_xlpm.id),COUNTIF('2. JSEL'!$M:$M,_xlpm.id),COUNTIF('3. PSM'!$M:$M,_xlpm.id),COUNTIF('4. SSP'!$M:$M,_xlpm.id),COUNTIF('5. JSACI'!$M:$M,_xlpm.id),COUNTIF('6. AIN'!$M:$M,_xlpm.id),COUNTIF('7. MS'!$M:$M,_xlpm.id),COUNTIF('8. DS'!$M:$M,_xlpm.id),COUNTIF('9. RMF'!$M:$M,_xlpm.id),COUNTIF('10. PCU'!$M:$M,_xlpm.id)))) -> 20
A174: JCMC1834-5s1v2 | B174: Journal des Connaissances Medico Chirurgicales | C174: 1834-5 | D174: 1 | E174: 2 | F174: French | G174: Paris | H174: France | I174: =_xlfn.LET(_xlpm.id,TRIM($A174),IF(_xlpm.id="","",SUM(COUNTIF('1. OP'!$M:$M,_xlpm.id),COUNTIF('2. JSEL'!$M:$M,_xlpm.id),COUNTIF('3. PSM'!$M:$M,_xlpm.id),COUNTIF('4. SSP'!$M:$M,_xlpm.id),COUNTIF('5. JSACI'!$M:$M,_xlpm.id),COUNTIF('6. AIN'!$M:$M,_xlpm.id),COUNTIF('7. MS'!$M:$M,_xlpm.id),COUNTIF('8. DS'!$M:$M,_xlpm.id),COUNTIF('9. RMF'!$M:$M,_xlpm.id),COUNTIF('10. PCU'!$M:$M,_xlpm.id)))) -> 12
A175: JCMC1835-6s1v3 | B175: Journal des Connaissances Medico Chirurgicales | C175: 1835-6 | D175: 1 | E175: 3 | F175: French | G175: Paris | H175: France | I175: =_xlfn.LET(_xlpm.id,TRIM($A175),IF(_xlpm.id="","",SUM(COUNTIF('1. OP'!$M:$M,_xlpm.id),COUNTIF('2. JSEL'!$M:$M,_xlpm.id),COUNTIF('3. PSM'!$M:$M,_xlpm.id),COUNTIF('4. SSP'!$M:$M,_xlpm.id),COUNTIF('5. JSACI'!$M:$M,_xlpm.id),COUNTIF('6. AIN'!$M:$M,_xlpm.id),COUNTIF('7. MS'!$M:$M,_xlpm.id),COUNTIF('8. DS'!$M:$M,_xlpm.id),COUNTIF('9. RMF'!$M:$M,_xlpm.id),COUNTIF('10. PCU'!$M:$M,_xlpm.id)))) -> 0
A176: JCMC1836-7s1v4 | B176: Journal des Connaissances Medico Chirurgicales | C176: 1836-7 | D176: 1 | E176: 4 | F176: French | G176: Paris | H176: France | I176: =_xlfn.LET(_xlpm.id,TRIM($A176),IF(_xlpm.id="","",SUM(COUNTIF('1. OP'!$M:$M,_xlpm.id),COUNTIF('2. JSEL'!$M:$M,_xlpm.id),COUNTIF('3. PSM'!$M:$M,_xlpm.id),COUNTIF('4. SSP'!$M:$M,_xlpm.id),COUNTIF('5. JSACI'!$M:$M,_xlpm.id),COUNTIF('6. AIN'!$M:$M,_xlpm.id),COUNTIF('7. MS'!$M:$M,_xlpm.id),COUNTIF('8. DS'!$M:$M,_xlpm.id),COUNTIF('9. RMF'!$M:$M,_xlpm.id),COUNTIF('10. PCU'!$M:$M,_xlpm.id)))) -> 5
A177: JCMC1837-8s1v5 | B177: Journal des Connaissances Medico Chirurgicales | C177: 1837-8 | D177: 1 | E177: 5 | F177: French | G177: Paris | H177: France | I177: =_xlfn.LET(_xlpm.id,TRIM($A177),IF(_xlpm.id="","",SUM(COUNTIF('1. OP'!$M:$M,_xlpm.id),COUNTIF('2. JSEL'!$M:$M,_xlpm.id),COUNTIF('3. PSM'!$M:$M,_xlpm.id),COUNTIF('4. SSP'!$M:$M,_xlpm.id),COUNTIF('5. JSACI'!$M:$M,_xlpm.id),COUNTIF('6. AIN'!$M:$M,_xlpm.id),COUNTIF('7. MS'!$M:$M,_xlpm.id),COUNTIF('8. DS'!$M:$M,_xlpm.id),COUNTIF('9. RMF'!$M:$M,_xlpm.id),COUNTIF('10. PCU'!$M:$M,_xlpm.id)))) -> 7
A178: JCMC1838-9s1v6 | B178: Journal des Connaissances Medico Chirurgicales | C178: 1838-9 | D178: 1 | E178: 6 | F178: French | G178: Paris | H178: France | I178: =_xlfn.LET(_xlpm.id,TRIM($A178),IF(_xlpm.id="","",SUM(COUNTIF('1. OP'!$M:$M,_xlpm.id),COUNTIF('2. JSEL'!$M:$M,_xlpm.id),COUNTIF('3. PSM'!$M:$M,_xlpm.id),COUNTIF('4. SSP'!$M:$M,_xlpm.id),COUNTIF('5. JSACI'!$M:$M,_xlpm.id),COUNTIF('6. AIN'!$M:$M,_xlpm.id),COUNTIF('7. MS'!$M:$M,_xlpm.id),COUNTIF('8. DS'!$M:$M,_xlpm.id),COUNTIF('9. RMF'!$M:$M,_xlpm.id),COUNTIF('10. PCU'!$M:$M,_xlpm.id)))) -> 17
A179: JCMC1839s1v7 | B179: Journal des Connaissances Medico Chirurgicales | C179: 1839 | D179: 1 | E179: 7 | F179: French | G179: Paris | H179: France | I179: =_xlfn.LET(_xlpm.id,TRIM($A179),IF(_xlpm.id="","",SUM(COUNTIF('1. OP'!$M:$M,_xlpm.id),COUNTIF('2. JSEL'!$M:$M,_xlpm.id),COUNTIF('3. PSM'!$M:$M,_xlpm.id),COUNTIF('4. SSP'!$M:$M,_xlpm.id),COUNTIF('5. JSACI'!$M:$M,_xlpm.id),COUNTIF('6. AIN'!$M:$M,_xlpm.id),COUNTIF('7. MS'!$M:$M,_xlpm.id),COUNTIF('8. DS'!$M:$M,_xlpm.id),COUNTIF('9. RMF'!$M:$M,_xlpm.id),COUNTIF('10. PCU'!$M:$M,_xlpm.id)))) -> 7
A180: JCMC1840s1v8 | B180: Journal des Connaissances Medico Chirurgicales | C180: 1840 | D180: 1 | E180: 8 | F180: French | G180: Paris | H180: France | I180: =_xlfn.LET(_xlpm.id,TRIM($A180),IF(_xlpm.id="","",SUM(COUNTIF('1. OP'!$M:$M,_xlpm.id),COUNTIF('2. JSEL'!$M:$M,_xlpm.id),COUNTIF('3. PSM'!$M:$M,_xlpm.id),COUNTIF('4. SSP'!$M:$M,_xlpm.id),COUNTIF('5. JSACI'!$M:$M,_xlpm.id),COUNTIF('6. AIN'!$M:$M,_xlpm.id),COUNTIF('7. MS'!$M:$M,_xlpm.id),COUNTIF('8. DS'!$M:$M,_xlpm.id),COUNTIF('9. RMF'!$M:$M,_xlpm.id),COUNTIF('10. PCU'!$M:$M,_xlpm.id)))) -> 0
A181: JPSA1815s1v1 | B181: Journal de pharmacie et des sciences accessoires | C181: 1815 | D181: 1 | E181: 1 | F181: French | G181: Paris | H181: France | I181: =_xlfn.LET(_xlpm.id,TRIM($A181),IF(_xlpm.id="","",SUM(COUNTIF('1. OP'!$M:$M,_xlpm.id),COUNTIF('2. JSEL'!$M:$M,_xlpm.id),COUNTIF('3. PSM'!$M:$M,_xlpm.id),COUNTIF('4. SSP'!$M:$M,_xlpm.id),COUNTIF('5. JSACI'!$M:$M,_xlpm.id),COUNTIF('6. AIN'!$M:$M,_xlpm.id),COUNTIF('7. MS'!$M:$M,_xlpm.id),COUNTIF('8. DS'!$M:$M,_xlpm.id),COUNTIF('9. RMF'!$M:$M,_xlpm.id),COUNTIF('10. PCU'!$M:$M,_xlpm.id)))) -> 0
A182: JPSA1816s1v2 | B182: Journal de pharmacie et des sciences accessoires | C182: 1816 | D182: 1 | E182: 2 | F182: French | G182: Paris | H182: France | I182: =_xlfn.LET(_xlpm.id,TRIM($A182),IF(_xlpm.id="","",SUM(COUNTIF('1. OP'!$M:$M,_xlpm.id),COUNTIF('2. JSEL'!$M:$M,_xlpm.id),COUNTIF('3. PSM'!$M:$M,_xlpm.id),COUNTIF('4. SSP'!$M:$M,_xlpm.id),COUNTIF('5. JSACI'!$M:$M,_xlpm.id),COUNTIF('6. AIN'!$M:$M,_xlpm.id),COUNTIF('7. MS'!$M:$M,_xlpm.id),COUNTIF('8. DS'!$M:$M,_xlpm.id),COUNTIF('9. RMF'!$M:$M,_xlpm.id),COUNTIF('10. PCU'!$M:$M,_xlpm.id)))) -> 0
A183: JPSA1817s1v3 | B183: Journal de pharmacie et des sciences accessoires | C183: 1817 | D183: 1 | E183: 3 | F183: French | G183: Paris | H183: France | I183: =_xlfn.LET(_xlpm.id,TRIM($A183),IF(_xlpm.id="","",SUM(COUNTIF('1. OP'!$M:$M,_xlpm.id),COUNTIF('2. JSEL'!$M:$M,_xlpm.id),COUNTIF('3. PSM'!$M:$M,_xlpm.id),COUNTIF('4. SSP'!$M:$M,_xlpm.id),COUNTIF('5. JSACI'!$M:$M,_xlpm.id),COUNTIF('6. AIN'!$M:$M,_xlpm.id),COUNTIF('7. MS'!$M:$M,_xlpm.id),COUNTIF('8. DS'!$M:$M,_xlpm.id),COUNTIF('9. RMF'!$M:$M,_xlpm.id),COUNTIF('10. PCU'!$M:$M,_xlpm.id)))) -> 0
A184: JPSA1818s1v4 | B184: Journal de pharmacie et des sciences accessoires | C184: 1818 | D184: 1 | E184: 4 | F184: French | G184: Paris | H184: France | I184: =_xlfn.LET(_xlpm.id,TRIM($A184),IF(_xlpm.id="","",SUM(COUNTIF('1. OP'!$M:$M,_xlpm.id),COUNTIF('2. JSEL'!$M:$M,_xlpm.id),COUNTIF('3. PSM'!$M:$M,_xlpm.id),COUNTIF('4. SSP'!$M:$M,_xlpm.id),COUNTIF('5. JSACI'!$M:$M,_xlpm.id),COUNTIF('6. AIN'!$M:$M,_xlpm.id),COUNTIF('7. MS'!$M:$M,_xlpm.id),COUNTIF('8. DS'!$M:$M,_xlpm.id),COUNTIF('9. RMF'!$M:$M,_xlpm.id),COUNTIF('10. PCU'!$M:$M,_xlpm.id)))) -> 0
A185: JPSA1819s1v5 | B185: Journal de pharmacie et des sciences accessoires | C185: 1819 | D185: 1 | E185: 5 | F185: French | G185: Paris | H185: France | I185: =_xlfn.LET(_xlpm.id,TRIM($A185),IF(_xlpm.id="","",SUM(COUNTIF('1. OP'!$M:$M,_xlpm.id),COUNTIF('2. JSEL'!$M:$M,_xlpm.id),COUNTIF('3. PSM'!$M:$M,_xlpm.id),COUNTIF('4. SSP'!$M:$M,_xlpm.id),COUNTIF('5. JSACI'!$M:$M,_xlpm.id),COUNTIF('6. AIN'!$M:$M,_xlpm.id),COUNTIF('7. MS'!$M:$M,_xlpm.id),COUNTIF('8. DS'!$M:$M,_xlpm.id),COUNTIF('9. RMF'!$M:$M,_xlpm.id),COUNTIF('10. PCU'!$M:$M,_xlpm.id)))) -> 0
A186: JPSA1820s1v6 | B186: Journal de pharmacie et des sciences accessoires | C186: 1820 | D186: 1 | E186: 6 | F186: French | G186: Paris | H186: France | I186: =_xlfn.LET(_xlpm.id,TRIM($A186),IF(_xlpm.id="","",SUM(COUNTIF('1. OP'!$M:$M,_xlpm.id),COUNTIF('2. JSEL'!$M:$M,_xlpm.id),COUNTIF('3. PSM'!$M:$M,_xlpm.id),COUNTIF('4. SSP'!$M:$M,_xlpm.id),COUNTIF('5. JSACI'!$M:$M,_xlpm.id),COUNTIF('6. AIN'!$M:$M,_xlpm.id),COUNTIF('7. MS'!$M:$M,_xlpm.id),COUNTIF('8. DS'!$M:$M,_xlpm.id),COUNTIF('9. RMF'!$M:$M,_xlpm.id),COUNTIF('10. PCU'!$M:$M,_xlpm.id)))) -> 0
A187: JPSA1821s1v7 | B187: Journal de pharmacie et des sciences accessoires | C187: 1821 | D187: 1 | E187: 7 | F187: French | G187: Paris | H187: France | I187: =_xlfn.LET(_xlpm.id,TRIM($A187),IF(_xlpm.id="","",SUM(COUNTIF('1. OP'!$M:$M,_xlpm.id),COUNTIF('2. JSEL'!$M:$M,_xlpm.id),COUNTIF('3. PSM'!$M:$M,_xlpm.id),COUNTIF('4. SSP'!$M:$M,_xlpm.id),COUNTIF('5. JSACI'!$M:$M,_xlpm.id),COUNTIF('6. AIN'!$M:$M,_xlpm.id),COUNTIF('7. MS'!$M:$M,_xlpm.id),COUNTIF('8. DS'!$M:$M,_xlpm.id),COUNTIF('9. RMF'!$M:$M,_xlpm.id),COUNTIF('10. PCU'!$M:$M,_xlpm.id)))) -> 0
A188: JPSA1822s1v8 | B188: Journal de pharmacie et des sciences accessoires | C188: 1822 | D188: 1 | E188: 8 | F188: French | G188: Paris | H188: France | I188: =_xlfn.LET(_xlpm.id,TRIM($A188),IF(_xlpm.id="","",SUM(COUNTIF('1. OP'!$M:$M,_xlpm.id),COUNTIF('2. JSEL'!$M:$M,_xlpm.id),COUNTIF('3. PSM'!$M:$M,_xlpm.id),COUNTIF('4. SSP'!$M:$M,_xlpm.id),COUNTIF('5. JSACI'!$M:$M,_xlpm.id),COUNTIF('6. AIN'!$M:$M,_xlpm.id),COUNTIF('7. MS'!$M:$M,_xlpm.id),COUNTIF('8. DS'!$M:$M,_xlpm.id),COUNTIF('9. RMF'!$M:$M,_xlpm.id),COUNTIF('10. PCU'!$M:$M,_xlpm.id)))) -> 0
A189: JPSA1823s1v9 | B189: Journal de pharmacie et des sciences accessoires | C189: 1823 | D189: 1 | E189: 9 | F189: French | G189: Paris | H189: France | I189: =_xlfn.LET(_xlpm.id,TRIM($A189),IF(_xlpm.id="","",SUM(COUNTIF('1. OP'!$M:$M,_xlpm.id),COUNTIF('2. JSEL'!$M:$M,_xlpm.id),COUNTIF('3. PSM'!$M:$M,_xlpm.id),COUNTIF('4. SSP'!$M:$M,_xlpm.id),COUNTIF('5. JSACI'!$M:$M,_xlpm.id),COUNTIF('6. AIN'!$M:$M,_xlpm.id),COUNTIF('7. MS'!$M:$M,_xlpm.id),COUNTIF('8. DS'!$M:$M,_xlpm.id),COUNTIF('9. RMF'!$M:$M,_xlpm.id),COUNTIF('10. PCU'!$M:$M,_xlpm.id)))) -> 2
A190: JPSA1824s1v10 | B190: Journal de pharmacie et des sciences accessoires | C190: 1824 | D190: 1 | E190: 10 | F190: French | G190: Paris | H190: France | I190: =_xlfn.LET(_xlpm.id,TRIM($A190),IF(_xlpm.id="","",SUM(COUNTIF('1. OP'!$M:$M,_xlpm.id),COUNTIF('2. JSEL'!$M:$M,_xlpm.id),COUNTIF('3. PSM'!$M:$M,_xlpm.id),COUNTIF('4. SSP'!$M:$M,_xlpm.id),COUNTIF('5. JSACI'!$M:$M,_xlpm.id),COUNTIF('6. AIN'!$M:$M,_xlpm.id),COUNTIF('7. MS'!$M:$M,_xlpm.id),COUNTIF('8. DS'!$M:$M,_xlpm.id),COUNTIF('9. RMF'!$M:$M,_xlpm.id),COUNTIF('10. PCU'!$M:$M,_xlpm.id)))) -> 5
... A209: MF1836s1v3 | B209: Musée des familles | C209: 1836 | D209: 1 | E209: 3 | F209: French | G209: Paris | H209: France | I209: =_xlfn.LET(_xlpm.id,TRIM($A209),IF(_xlpm.id="","",SUM(COUNTIF('1. OP'!$M:$M,_xlpm.id),COUNTIF('2. JSEL'!$M:$M,_xlpm.id),COUNTIF('3. PSM'!$M:$M,_xlpm.id),COUNTIF('4. SSP'!$M:$M,_xlpm.id),COUNTIF('5. JSACI'!$M:$M,_xlpm.id),COUNTIF('6. AIN'!$M:$M,_xlpm.id),COUNTIF('7. MS'!$M:$M,_xlpm.id),COUNTIF('8. DS'!$M:$M,_xlpm.id),COUNTIF('9. RMF'!$M:$M,_xlpm.id),COUNTIF('10. PCU'!$M:$M,_xlpm.id)))) -> 0
A210: MF1836-1837s1v4 | B210: Musée des familles | C210: 1836-1837 | D210: 1 | E210: 4 | F210: French | G210: Paris | H210: France | I210: =_xlfn.LET(_xlpm.id,TRIM($A210),IF(_xlpm.id="","",SUM(COUNTIF('1. OP'!$M:$M,_xlpm.id),COUNTIF('2. JSEL'!$M:$M,_xlpm.id),COUNTIF('3. PSM'!$M:$M,_xlpm.id),COUNTIF('4. SSP'!$M:$M,_xlpm.id),COUNTIF('5. JSACI'!$M:$M,_xlpm.id),COUNTIF('6. AIN'!$M:$M,_xlpm.id),COUNTIF('7. MS'!$M:$M,_xlpm.id),COUNTIF('8. DS'!$M:$M,_xlpm.id),COUNTIF('9. RMF'!$M:$M,_xlpm.id),COUNTIF('10. PCU'!$M:$M,_xlpm.id)))) -> 0
A211: MF1837-1838s1v5 | B211: Musée des familles | C211: 1837-1838 | D211: 1 | E211: 5 | F211: French | G211: Paris | H211: France | I211: =_xlfn.LET(_xlpm.id,TRIM($A211),IF(_xlpm.id="","",SUM(COUNTIF('1. OP'!$M:$M,_xlpm.id),COUNTIF('2. JSEL'!$M:$M,_xlpm.id),COUNTIF('3. PSM'!$M:$M,_xlpm.id),COUNTIF('4. SSP'!$M:$M,_xlpm.id),COUNTIF('5. JSACI'!$M:$M,_xlpm.id),COUNTIF('6. AIN'!$M:$M,_xlpm.id),COUNTIF('7. MS'!$M:$M,_xlpm.id),COUNTIF('8. DS'!$M:$M,_xlpm.id),COUNTIF('9. RMF'!$M:$M,_xlpm.id),COUNTIF('10. PCU'!$M:$M,_xlpm.id)))) -> 0
A212: LMU1833-1834s1v1 | B212: Le Magasin Universel | C212: 1833-1834 | D212: 1 | E212: 1 | F212: French | G212: Paris | H212: France | I212: =_xlfn.LET(_xlpm.id,TRIM($A212),IF(_xlpm.id="","",SUM(COUNTIF('1. OP'!$M:$M,_xlpm.id),COUNTIF('2. JSEL'!$M:$M,_xlpm.id),COUNTIF('3. PSM'!$M:$M,_xlpm.id),COUNTIF('4. SSP'!$M:$M,_xlpm.id),COUNTIF('5. JSACI'!$M:$M,_xlpm.id),COUNTIF('6. AIN'!$M:$M,_xlpm.id),COUNTIF('7. MS'!$M:$M,_xlpm.id),COUNTIF('8. DS'!$M:$M,_xlpm.id),COUNTIF('9. RMF'!$M:$M,_xlpm.id),COUNTIF('10. PCU'!$M:$M,_xlpm.id)))) -> 2
A213: LMU1834-1835s1v2 | B213: Le Magasin Universel | C213: 1834-1835 | D213: 1 | E213: 2 | F213: French | G213: Paris | H213: France | I213: =_xlfn.LET(_xlpm.id,TRIM($A213),IF(_xlpm.id="","",SUM(COUNTIF('1. OP'!$M:$M,_xlpm.id),COUNTIF('2. JSEL'!$M:$M,_xlpm.id),COUNTIF('3. PSM'!$M:$M,_xlpm.id),COUNTIF('4. SSP'!$M:$M,_xlpm.id),COUNTIF('5. JSACI'!$M:$M,_xlpm.id),COUNTIF('6. AIN'!$M:$M,_xlpm.id),COUNTIF('7. MS'!$M:$M,_xlpm.id),COUNTIF('8. DS'!$M:$M,_xlpm.id),COUNTIF('9. RMF'!$M:$M,_xlpm.id),COUNTIF('10. PCU'!$M:$M,_xlpm.id)))) -> 0
A214: LMU1835-1836s1v3 | B214: Le Magasin Universel | C214: 1835-1836 | D214: 1 | E214: 3 | F214: French | G214: Paris | H214: France | I214: =_xlfn.LET(_xlpm.id,TRIM($A214),IF(_xlpm.id="","",SUM(COUNTIF('1. OP'!$M:$M,_xlpm.id),COUNTIF('2. JSEL'!$M:$M,_xlpm.id),COUNTIF('3. PSM'!$M:$M,_xlpm.id),COUNTIF('4. SSP'!$M:$M,_xlpm.id),COUNTIF('5. JSACI'!$M:$M,_xlpm.id),COUNTIF('6. AIN'!$M:$M,_xlpm.id),COUNTIF('7. MS'!$M:$M,_xlpm.id),COUNTIF('8. DS'!$M:$M,_xlpm.id),COUNTIF('9. RMF'!$M:$M,_xlpm.id),COUNTIF('10. PCU'!$M:$M,_xlpm.id)))) -> 1
A215: LMU1836-1837s1v4 | B215: Le Magasin Universel | C215: 1836-1837 | D215: 1 | E215: 4 | F215: French | G215: Paris | H215: France | I215: =_xlfn.LET(_xlpm.id,TRIM($A215),IF(_xlpm.id="","",SUM(COUNTIF('1. OP'!$M:$M,_xlpm.id),COUNTIF('2. JSEL'!$M:$M,_xlpm.id),COUNTIF('3. PSM'!$M:$M,_xlpm.id),COUNTIF('4. SSP'!$M:$M,_xlpm.id),COUNTIF('5. JSACI'!$M:$M,_xlpm.id),COUNTIF('6. AIN'!$M:$M,_xlpm.id),COUNTIF('7. MS'!$M:$M,_xlpm.id),COUNTIF('8. DS'!$M:$M,_xlpm.id),COUNTIF('9. RMF'!$M:$M,_xlpm.id),COUNTIF('10. PCU'!$M:$M,_xlpm.id)))) -> 0
A216: LMU1837-1838s1v5 | B216: Le Magasin Universel | C216: 1837-1838 | D216: 1 | E216: 5 | F216: French | G216: Paris | H216: France | I216: =_xlfn.LET(_xlpm.id,TRIM($A216),IF(_xlpm.id="","",SUM(COUNTIF('1. OP'!$M:$M,_xlpm.id),COUNTIF('2. JSEL'!$M:$M,_xlpm.id),COUNTIF('3. PSM'!$M:$M,_xlpm.id),COUNTIF('4. SSP'!$M:$M,_xlpm.id),COUNTIF('5. JSACI'!$M:$M,_xlpm.id),COUNTIF('6. AIN'!$M:$M,_xlpm.id),COUNTIF('7. MS'!$M:$M,_xlpm.id),COUNTIF('8. DS'!$M:$M,_xlpm.id),COUNTIF('9. RMF'!$M:$M,_xlpm.id),COUNTIF('10. PCU'!$M:$M,_xlpm.id)))) -> 0
A217: LMU1838-1839s1v6 | B217: Le Magasin Universel | C217: 1838-1839 | D217: 1 | E217: 6 | F217: French | G217: Paris | H217: France | I217: =_xlfn.LET(_xlpm.id,TRIM($A217),IF(_xlpm.id="","",SUM(COUNTIF('1. OP'!$M:$M,_xlpm.id),COUNTIF('2. JSEL'!$M:$M,_xlpm.id),COUNTIF('3. PSM'!$M:$M,_xlpm.id),COUNTIF('4. SSP'!$M:$M,_xlpm.id),COUNTIF('5. JSACI'!$M:$M,_xlpm.id),COUNTIF('6. AIN'!$M:$M,_xlpm.id),COUNTIF('7. MS'!$M:$M,_xlpm.id),COUNTIF('8. DS'!$M:$M,_xlpm.id),COUNTIF('9. RMF'!$M:$M,_xlpm.id),COUNTIF('10. PCU'!$M:$M,_xlpm.id)))) -> 0
A218: LMU1839-1840s1v7 | B218: Le Magasin Universel | C218: 1839-1840 | D218: 1 | E218: 7 | F218: French | G218: Paris | H218: France | I218: =_xlfn.LET(_xlpm.id,TRIM($A218),IF(_xlpm.id="","",SUM(COUNTIF('1. OP'!$M:$M,_xlpm.id),COUNTIF('2. JSEL'!$M:$M,_xlpm.id),COUNTIF('3. PSM'!$M:$M,_xlpm.id),COUNTIF('4. SSP'!$M:$M,_xlpm.id),COUNTIF('5. JSACI'!$M:$M,_xlpm.id),COUNTIF('6. AIN'!$M:$M,_xlpm.id),COUNTIF('7. MS'!$M:$M,_xlpm.id),COUNTIF('8. DS'!$M:$M,_xlpm.id),COUNTIF('9. RMF'!$M:$M,_xlpm.id),COUNTIF('10. PCU'!$M:$M,_xlpm.id)))) -> 0
A219: TSM1832s1v1 | B219: The Saturday Magazine | C219: 1832 | D219: 1 | E219: 1 | F219: English | G219: London | H219: United Kingdom | I219: =_xlfn.LET(_xlpm.id,TRIM($A219),IF(_xlpm.id="","",SUM(COUNTIF('1. OP'!$M:$M,_xlpm.id),COUNTIF('2. JSEL'!$M:$M,_xlpm.id),COUNTIF('3. PSM'!$M:$M,_xlpm.id),COUNTIF('4. SSP'!$M:$M,_xlpm.id),COUNTIF('5. JSACI'!$M:$M,_xlpm.id),COUNTIF('6. AIN'!$M:$M,_xlpm.id),COUNTIF('7. MS'!$M:$M,_xlpm.id),COUNTIF('8. DS'!$M:$M,_xlpm.id),COUNTIF('9. RMF'!$M:$M,_xlpm.id),COUNTIF('10. PCU'!$M:$M,_xlpm.id)))) -> 2
A220: TSM1833s1v2 | B220: The Saturday Magazine | C220: 1833 | D220: 1 | E220: 2 | F220: English | G220: London | H220: United Kingdom | I220: =_xlfn.LET(_xlpm.id,TRIM($A220),IF(_xlpm.id="","",SUM(COUNTIF('1. OP'!$M:$M,_xlpm.id),COUNTIF('2. JSEL'!$M:$M,_xlpm.id),COUNTIF('3. PSM'!$M:$M,_xlpm.id),COUNTIF('4. SSP'!$M:$M,_xlpm.id),COUNTIF('5. JSACI'!$M:$M,_xlpm.id),COUNTIF('6. AIN'!$M:$M,_xlpm.id),COUNTIF('7. MS'!$M:$M,_xlpm.id),COUNTIF('8. DS'!$M:$M,_xlpm.id),COUNTIF('9. RMF'!$M:$M,_xlpm.id),COUNTIF('10. PCU'!$M:$M,_xlpm.id)))) -> 5
A221: TSM1833s1v3 | B221: The Saturday Magazine | C221: 1833 | D221: 1 | E221: 3 | F221: English | G221: London | H221: United Kingdom | I221: =_xlfn.LET(_xlpm.id,TRIM($A221),IF(_xlpm.id="","",SUM(COUNTIF('1. OP'!$M:$M,_xlpm.id),COUNTIF('2. JSEL'!$M:$M,_xlpm.id),COUNTIF('3. PSM'!$M:$M,_xlpm.id),COUNTIF('4. SSP'!$M:$M,_xlpm.id),COUNTIF('5. JSACI'!$M:$M,_xlpm.id),COUNTIF('6. AIN'!$M:$M,_xlpm.id),COUNTIF('7. MS'!$M:$M,_xlpm.id),COUNTIF('8. DS'!$M:$M,_xlpm.id),COUNTIF('9. RMF'!$M:$M,_xlpm.id),COUNTIF('10. PCU'!$M:$M,_xlpm.id)))) -> 0
A222: TSM1834s1v4 | B222: The Saturday Magazine | C222: 1834 | D222: 1 | E222: 4 | F222: English | G222: London | H222: United Kingdom | I222: =_xlfn.LET(_xlpm.id,TRIM($A222),IF(_xlpm.id="","",SUM(COUNTIF('1. OP'!$M:$M,_xlpm.id),COUNTIF('2. JSEL'!$M:$M,_xlpm.id),COUNTIF('3. PSM'!$M:$M,_xlpm.id),COUNTIF('4. SSP'!$M:$M,_xlpm.id),COUNTIF('5. JSACI'!$M:$M,_xlpm.id),COUNTIF('6. AIN'!$M:$M,_xlpm.id),COUNTIF('7. MS'!$M:$M,_xlpm.id),COUNTIF('8. DS'!$M:$M,_xlpm.id),COUNTIF('9. RMF'!$M:$M,_xlpm.id),COUNTIF('10. PCU'!$M:$M,_xlpm.id)))) -> 0
A223: TSM1834s1v5 | B223: The Saturday Magazine | C223: 1834 | D223: 1 | E223: 5 | F223: English | G223: London | H223: United Kingdom | I223: =_xlfn.LET(_xlpm.id,TRIM($A223),IF(_xlpm.id="","",SUM(COUNTIF('1. OP'!$M:$M,_xlpm.id),COUNTIF('2. JSEL'!$M:$M,_xlpm.id),COUNTIF('3. PSM'!$M:$M,_xlpm.id),COUNTIF('4. SSP'!$M:$M,_xlpm.id),COUNTIF('5. JSACI'!$M:$M,_xlpm.id),COUNTIF('6. AIN'!$M:$M,_xlpm.id),COUNTIF('7. MS'!$M:$M,_xlpm.id),COUNTIF('8. DS'!$M:$M,_xlpm.id),COUNTIF('9. RMF'!$M:$M,_xlpm.id),COUNTIF('10. PCU'!$M:$M,_xlpm.id)))) -> 0
A224: TSM1835s1v6 | B224: The Saturday Magazine | C224: 1834 | D224: 1 | E224: 6 | F224: English | G224: London | H224: United Kingdom | I224: =_xlfn.LET(_xlpm.id,TRIM($A224),IF(_xlpm.id="","",SUM(COUNTIF('1. OP'!$M:$M,_xlpm.id),COUNTIF('2. JSEL'!$M:$M,_xlpm.id),COUNTIF('3. PSM'!$M:$M,_xlpm.id),COUNTIF('4. SSP'!$M:$M,_xlpm.id),COUNTIF('5. JSACI'!$M:$M,_xlpm.id),COUNTIF('6. AIN'!$M:$M,_xlpm.id),COUNTIF('7. MS'!$M:$M,_xlpm.id),COUNTIF('8. DS'!$M:$M,_xlpm.id),COUNTIF('9. RMF'!$M:$M,_xlpm.id),COUNTIF('10. PCU'!$M:$M,_xlpm.id)))) -> 1
A225: TSM1835s1v7 | B225: The Saturday Magazine | C225: 1835 | D225: 1 | E225: 7 | F225: English | G225: London | H225: United Kingdom | I225: =_xlfn.LET(_xlpm.id,TRIM($A225),IF(_xlpm.id="","",SUM(COUNTIF('1. OP'!$M:$M,_xlpm.id),COUNTIF('2. JSEL'!$M:$M,_xlpm.id),COUNTIF('3. PSM'!$M:$M,_xlpm.id),COUNTIF('4. SSP'!$M:$M,_xlpm.id),COUNTIF('5. JSACI'!$M:$M,_xlpm.id),COUNTIF('6. AIN'!$M:$M,_xlpm.id),COUNTIF('7. MS'!$M:$M,_xlpm.id),COUNTIF('8. DS'!$M:$M,_xlpm.id),COUNTIF('9. RMF'!$M:$M,_xlpm.id),COUNTIF('10. PCU'!$M:$M,_xlpm.id)))) -> 0
A226: TSM1836s1v8 | B226: The Saturday Magazine | C226: 1836 | D226: 1 | E226: 8 | F226: English | G226: London | H226: United Kingdom | I226: =_xlfn.LET(_xlpm.id,TRIM($A226),IF(_xlpm.id="","",SUM(COUNTIF('1. OP'!$M:$M,_xlpm.id),COUNTIF('2. JSEL'!$M:$M,_xlpm.id),COUNTIF('3. PSM'!$M:$M,_xlpm.id),COUNTIF('4. SSP'!$M:$M,_xlpm.id),COUNTIF('5. JSACI'!$M:$M,_xlpm.id),COUNTIF('6. AIN'!$M:$M,_xlpm.id),COUNTIF('7. MS'!$M:$M,_xlpm.id),COUNTIF('8. DS'!$M:$M,_xlpm.id),COUNTIF('9. RMF'!$M:$M,_xlpm.id),COUNTIF('10. PCU'!$M:$M,_xlpm.id)))) -> 0
A227: TSM1836s1v9 | B227: The Saturday Magazine | C227: 1836 | D227: 1 | E227: 9 | F227: English | G227: London | H227: United Kingdom | I227: =_xlfn.LET(_xlpm.id,TRIM($A227),IF(_xlpm.id="","",SUM(COUNTIF('1. OP'!$M:$M,_xlpm.id),COUNTIF('2. JSEL'!$M:$M,_xlpm.id),COUNTIF('3. PSM'!$M:$M,_xlpm.id),COUNTIF('4. SSP'!$M:$M,_xlpm.id),COUNTIF('5. JSACI'!$M:$M,_xlpm.id),COUNTIF('6. AIN'!$M:$M,_xlpm.id),COUNTIF('7. MS'!$M:$M,_xlpm.id),COUNTIF('8. DS'!$M:$M,_xlpm.id),COUNTIF('9. RMF'!$M:$M,_xlpm.id),COUNTIF('10. PCU'!$M:$M,_xlpm.id)))) -> 0
A228: TSM1837s1v10 | B228: The Saturday Magazine | C228: 1837 | D228: 1 | E228: 10 | F228: English | G228: London | H228: United Kingdom | I228: =_xlfn.LET(_xlpm.id,TRIM($A228),IF(_xlpm.id="","",SUM(COUNTIF('1. OP'!$M:$M,_xlpm.id),COUNTIF('2. JSEL'!$M:$M,_xlpm.id),COUNTIF('3. PSM'!$M:$M,_xlpm.id),COUNTIF('4. SSP'!$M:$M,_xlpm.id),COUNTIF('5. JSACI'!$M:$M,_xlpm.id),COUNTIF('6. AIN'!$M:$M,_xlpm.id),COUNTIF('7. MS'!$M:$M,_xlpm.id),COUNTIF('8. DS'!$M:$M,_xlpm.id),COUNTIF('9. RMF'!$M:$M,_xlpm.id),COUNTIF('10. PCU'!$M:$M,_xlpm.id)))) -> 0
A229: TSM1837s1v11 | B229: The Saturday Magazine | C229: 1837 | D229: 1 | E229: 11 | F229: English | G229: London | H229: United Kingdom | I229: =_xlfn.LET(_xlpm.id,TRIM($A229),IF(_xlpm.id="","",SUM(COUNTIF('1. OP'!$M:$M,_xlpm.id),COUNTIF('2. JSEL'!$M:$M,_xlpm.id),COUNTIF('3. PSM'!$M:$M,_xlpm.id),COUNTIF('4. SSP'!$M:$M,_xlpm.id),COUNTIF('5. JSACI'!$M:$M,_xlpm.id),COUNTIF('6. AIN'!$M:$M,_xlpm.id),COUNTIF('7. MS'!$M:$M,_xlpm.id),COUNTIF('8. DS'!$M:$M,_xlpm.id),COUNTIF('9. RMF'!$M:$M,_xlpm.id),COUNTIF('10. PCU'!$M:$M,_xlpm.id)))) -> 0
A230: PM1832s1v1 | B230: The Penny Magazine | C230: 1832 | D230: 1 | E230: 1 | F230: English | G230: London | H230: United Kingdom | I230: =_xlfn.LET(_xlpm.id,TRIM($A230),IF(_xlpm.id="","",SUM(COUNTIF('1. OP'!$M:$M,_xlpm.id),COUNTIF('2. JSEL'!$M:$M,_xlpm.id),COUNTIF('3. PSM'!$M:$M,_xlpm.id),COUNTIF('4. SSP'!$M:$M,_xlpm.id),COUNTIF('5. JSACI'!$M:$M,_xlpm.id),COUNTIF('6. AIN'!$M:$M,_xlpm.id),COUNTIF('7. MS'!$M:$M,_xlpm.id),COUNTIF('8. DS'!$M:$M,_xlpm.id),COUNTIF('9. RMF'!$M:$M,_xlpm.id),COUNTIF('10. PCU'!$M:$M,_xlpm.id)))) -> 3
... A404: RPI1840s2v14 | B404: The Report of Patent Inventions | C404: 1840 | D404: 2 | E404: 14 | F404: English | G404: London | H404: United Kingdom | I404: =_xlfn.LET(_xlpm.id,TRIM($A404),IF(_xlpm.id="","",SUM(COUNTIF('1. OP'!$M:$M,_xlpm.id),COUNTIF('2. JSEL'!$M:$M,_xlpm.id),COUNTIF('3. PSM'!$M:$M,_xlpm.id),COUNTIF('4. SSP'!$M:$M,_xlpm.id),COUNTIF('5. JSACI'!$M:$M,_xlpm.id),COUNTIF('6. AIN'!$M:$M,_xlpm.id),COUNTIF('7. MS'!$M:$M,_xlpm.id),COUNTIF('8. DS'!$M:$M,_xlpm.id),COUNTIF('9. RMF'!$M:$M,_xlpm.id),COUNTIF('10. PCU'!$M:$M,_xlpm.id)))) -> 0
A405: TGK1832-1833s1v1 | B405: The Guide to Knowledge | C405: 1832-1833 | D405: 1 | E405: 1-2 | F405: English | G405: London | H405: United Kingdom | I405: =_xlfn.LET(_xlpm.id,TRIM($A405),IF(_xlpm.id="","",SUM(COUNTIF('1. OP'!$M:$M,_xlpm.id),COUNTIF('2. JSEL'!$M:$M,_xlpm.id),COUNTIF('3. PSM'!$M:$M,_xlpm.id),COUNTIF('4. SSP'!$M:$M,_xlpm.id),COUNTIF('5. JSACI'!$M:$M,_xlpm.id),COUNTIF('6. AIN'!$M:$M,_xlpm.id),COUNTIF('7. MS'!$M:$M,_xlpm.id),COUNTIF('8. DS'!$M:$M,_xlpm.id),COUNTIF('9. RMF'!$M:$M,_xlpm.id),COUNTIF('10. PCU'!$M:$M,_xlpm.id)))) -> 0
A406: TGK1835s1v3 | B406: The Guide to Knowledge | C406: 1835 | D406: 1 | E406: 3 | F406: English | G406: London | H406: United Kingdom | I406: =_xlfn.LET(_xlpm.id,TRIM($A406),IF(_xlpm.id="","",SUM(COUNTIF('1. OP'!$M:$M,_xlpm.id),COUNTIF('2. JSEL'!$M:$M,_xlpm.id),COUNTIF('3. PSM'!$M:$M,_xlpm.id),COUNTIF('4. SSP'!$M:$M,_xlpm.id),COUNTIF('5. JSACI'!$M:$M,_xlpm.id),COUNTIF('6. AIN'!$M:$M,_xlpm.id),COUNTIF('7. MS'!$M:$M,_xlpm.id),COUNTIF('8. DS'!$M:$M,_xlpm.id),COUNTIF('9. RMF'!$M:$M,_xlpm.id),COUNTIF('10. PCU'!$M:$M,_xlpm.id)))) -> 0
A407: TGK1836s1v4 | B407: The Guide to Knowledge | C407: 1836 | D407: 1 | E407: 4 | F407: English | G407: London | H407: United Kingdom | I407: =_xlfn.LET(_xlpm.id,TRIM($A407),IF(_xlpm.id="","",SUM(COUNTIF('1. OP'!$M:$M,_xlpm.id),COUNTIF('2. JSEL'!$M:$M,_xlpm.id),COUNTIF('3. PSM'!$M:$M,_xlpm.id),COUNTIF('4. SSP'!$M:$M,_xlpm.id),COUNTIF('5. JSACI'!$M:$M,_xlpm.id),COUNTIF('6. AIN'!$M:$M,_xlpm.id),COUNTIF('7. MS'!$M:$M,_xlpm.id),COUNTIF('8. DS'!$M:$M,_xlpm.id),COUNTIF('9. RMF'!$M:$M,_xlpm.id),COUNTIF('10. PCU'!$M:$M,_xlpm.id)))) -> 0
A408: TGK1837s2v1 | B408: The Guide to Knowledge | C408: 1837 | D408: 2 | E408: 1 | F408: English | G408: London | H408: United Kingdom | I408: =_xlfn.LET(_xlpm.id,TRIM($A408),IF(_xlpm.id="","",SUM(COUNTIF('1. OP'!$M:$M,_xlpm.id),COUNTIF('2. JSEL'!$M:$M,_xlpm.id),COUNTIF('3. PSM'!$M:$M,_xlpm.id),COUNTIF('4. SSP'!$M:$M,_xlpm.id),COUNTIF('5. JSACI'!$M:$M,_xlpm.id),COUNTIF('6. AIN'!$M:$M,_xlpm.id),COUNTIF('7. MS'!$M:$M,_xlpm.id),COUNTIF('8. DS'!$M:$M,_xlpm.id),COUNTIF('9. RMF'!$M:$M,_xlpm.id),COUNTIF('10. PCU'!$M:$M,_xlpm.id)))) -> 0
A409: TAF1821s1v1 | B409: The American Farmer | C409: 1821 | D409: 1 | E409: 1 | F409: English | G409: Baltimore | H409: United States of America | I409: =_xlfn.LET(_xlpm.id,TRIM($A409),IF(_xlpm.id="","",SUM(COUNTIF('1. OP'!$M:$M,_xlpm.id),COUNTIF('2. JSEL'!$M:$M,_xlpm.id),COUNTIF('3. PSM'!$M:$M,_xlpm.id),COUNTIF('4. SSP'!$M:$M,_xlpm.id),COUNTIF('5. JSACI'!$M:$M,_xlpm.id),COUNTIF('6. AIN'!$M:$M,_xlpm.id),COUNTIF('7. MS'!$M:$M,_xlpm.id),COUNTIF('8. DS'!$M:$M,_xlpm.id),COUNTIF('9. RMF'!$M:$M,_xlpm.id),COUNTIF('10. PCU'!$M:$M,_xlpm.id)))) -> 0
A410: TAF1821s1v2 | B410: The American Farmer | C410: 1821 | D410: 1 | E410: 2 | F410: English | G410: Baltimore | H410: United States of America | I410: =_xlfn.LET(_xlpm.id,TRIM($A410),IF(_xlpm.id="","",SUM(COUNTIF('1. OP'!$M:$M,_xlpm.id),COUNTIF('2. JSEL'!$M:$M,_xlpm.id),COUNTIF('3. PSM'!$M:$M,_xlpm.id),COUNTIF('4. SSP'!$M:$M,_xlpm.id),COUNTIF('5. JSACI'!$M:$M,_xlpm.id),COUNTIF('6. AIN'!$M:$M,_xlpm.id),COUNTIF('7. MS'!$M:$M,_xlpm.id),COUNTIF('8. DS'!$M:$M,_xlpm.id),COUNTIF('9. RMF'!$M:$M,_xlpm.id),COUNTIF('10. PCU'!$M:$M,_xlpm.id)))) -> 0
A411: TAF1822s1v3 | B411: The American Farmer | C411: 1822 | D411: 1 | E411: 3 | F411: English | G411: Baltimore | H411: United States of America | I411: =_xlfn.LET(_xlpm.id,TRIM($A411),IF(_xlpm.id="","",SUM(COUNTIF('1. OP'!$M:$M,_xlpm.id),COUNTIF('2. JSEL'!$M:$M,_xlpm.id),COUNTIF('3. PSM'!$M:$M,_xlpm.id),COUNTIF('4. SSP'!$M:$M,_xlpm.id),COUNTIF('5. JSACI'!$M:$M,_xlpm.id),COUNTIF('6. AIN'!$M:$M,_xlpm.id),COUNTIF('7. MS'!$M:$M,_xlpm.id),COUNTIF('8. DS'!$M:$M,_xlpm.id),COUNTIF('9. RMF'!$M:$M,_xlpm.id),COUNTIF('10. PCU'!$M:$M,_xlpm.id)))) -> 0
A412: TAF1823s1v4 | B412: The American Farmer | C412: 1823 | D412: 1 | E412: 4 | F412: English | G412: Baltimore | H412: United States of America | I412: =_xlfn.LET(_xlpm.id,TRIM($A412),IF(_xlpm.id="","",SUM(COUNTIF('1. OP'!$M:$M,_xlpm.id),COUNTIF('2. JSEL'!$M:$M,_xlpm.id),COUNTIF('3. PSM'!$M:$M,_xlpm.id),COUNTIF('4. SSP'!$M:$M,_xlpm.id),COUNTIF('5. JSACI'!$M:$M,_xlpm.id),COUNTIF('6. AIN'!$M:$M,_xlpm.id),COUNTIF('7. MS'!$M:$M,_xlpm.id),COUNTIF('8. DS'!$M:$M,_xlpm.id),COUNTIF('9. RMF'!$M:$M,_xlpm.id),COUNTIF('10. PCU'!$M:$M,_xlpm.id)))) -> 0
A413: TAF1823s1v5 | B413: The American Farmer | C413: 1823 | D413: 1 | E413: 5 | F413: English | G413: Baltimore | H413: United States of America | I413: =_xlfn.LET(_xlpm.id,TRIM($A413),IF(_xlpm.id="","",SUM(COUNTIF('1. OP'!$M:$M,_xlpm.id),COUNTIF('2. JSEL'!$M:$M,_xlpm.id),COUNTIF('3. PSM'!$M:$M,_xlpm.id),COUNTIF('4. SSP'!$M:$M,_xlpm.id),COUNTIF('5. JSACI'!$M:$M,_xlpm.id),COUNTIF('6. AIN'!$M:$M,_xlpm.id),COUNTIF('7. MS'!$M:$M,_xlpm.id),COUNTIF('8. DS'!$M:$M,_xlpm.id),COUNTIF('9. RMF'!$M:$M,_xlpm.id),COUNTIF('10. PCU'!$M:$M,_xlpm.id)))) -> 0
A414: TAF1824s1v6 | B414: The American Farmer | C414: 1824 | D414: 1 | E414: 6 | F414: English | G414: Baltimore | H414: United States of America | I414: =_xlfn.LET(_xlpm.id,TRIM($A414),IF(_xlpm.id="","",SUM(COUNTIF('1. OP'!$M:$M,_xlpm.id),COUNTIF('2. JSEL'!$M:$M,_xlpm.id),COUNTIF('3. PSM'!$M:$M,_xlpm.id),COUNTIF('4. SSP'!$M:$M,_xlpm.id),COUNTIF('5. JSACI'!$M:$M,_xlpm.id),COUNTIF('6. AIN'!$M:$M,_xlpm.id),COUNTIF('7. MS'!$M:$M,_xlpm.id),COUNTIF('8. DS'!$M:$M,_xlpm.id),COUNTIF('9. RMF'!$M:$M,_xlpm.id),COUNTIF('10. PCU'!$M:$M,_xlpm.id)))) -> 0
A415: TAF1825s1v7 | B415: The American Farmer | C415: 1825 | D415: 1 | E415: 7 | F415: English | G415: Baltimore | H415: United States of America | I415: =_xlfn.LET(_xlpm.id,TRIM($A415),IF(_xlpm.id="","",SUM(COUNTIF('1. OP'!$M:$M,_xlpm.id),COUNTIF('2. JSEL'!$M:$M,_xlpm.id),COUNTIF('3. PSM'!$M:$M,_xlpm.id),COUNTIF('4. SSP'!$M:$M,_xlpm.id),COUNTIF('5. JSACI'!$M:$M,_xlpm.id),COUNTIF('6. AIN'!$M:$M,_xlpm.id),COUNTIF('7. MS'!$M:$M,_xlpm.id),COUNTIF('8. DS'!$M:$M,_xlpm.id),COUNTIF('9. RMF'!$M:$M,_xlpm.id),COUNTIF('10. PCU'!$M:$M,_xlpm.id)))) -> 0
A416: TAF1826s1v8 | B416: The American Farmer | C416: 1826 | D416: 1 | E416: 8 | F416: English | G416: Baltimore | H416: United States of America | I416: =_xlfn.LET(_xlpm.id,TRIM($A416),IF(_xlpm.id="","",SUM(COUNTIF('1. OP'!$M:$M,_xlpm.id),COUNTIF('2. JSEL'!$M:$M,_xlpm.id),COUNTIF('3. PSM'!$M:$M,_xlpm.id),COUNTIF('4. SSP'!$M:$M,_xlpm.id),COUNTIF('5. JSACI'!$M:$M,_xlpm.id),COUNTIF('6. AIN'!$M:$M,_xlpm.id),COUNTIF('7. MS'!$M:$M,_xlpm.id),COUNTIF('8. DS'!$M:$M,_xlpm.id),COUNTIF('9. RMF'!$M:$M,_xlpm.id),COUNTIF('10. PCU'!$M:$M,_xlpm.id)))) -> 0
A417: TAF1827s1v9 | B417: The American Farmer | C417: 1827 | D417: 1 | E417: 9 | F417: English | G417: Baltimore | H417: United States of America | I417: =_xlfn.LET(_xlpm.id,TRIM($A417),IF(_xlpm.id="","",SUM(COUNTIF('1. OP'!$M:$M,_xlpm.id),COUNTIF('2. JSEL'!$M:$M,_xlpm.id),COUNTIF('3. PSM'!$M:$M,_xlpm.id),COUNTIF('4. SSP'!$M:$M,_xlpm.id),COUNTIF('5. JSACI'!$M:$M,_xlpm.id),COUNTIF('6. AIN'!$M:$M,_xlpm.id),COUNTIF('7. MS'!$M:$M,_xlpm.id),COUNTIF('8. DS'!$M:$M,_xlpm.id),COUNTIF('9. RMF'!$M:$M,_xlpm.id),COUNTIF('10. PCU'!$M:$M,_xlpm.id)))) -> 0
... A461: OR1840s1v6 | B461: O Recreio | C461: 1840 | D461: 1 | E461: 6 | F461: Portuguese | G461: Lisbon | H461: Portugal | I461: =_xlfn.LET(_xlpm.id,TRIM($A461),IF(_xlpm.id="","",SUM(COUNTIF('1. OP'!$M:$M,_xlpm.id),COUNTIF('2. JSEL'!$M:$M,_xlpm.id),COUNTIF('3. PSM'!$M:$M,_xlpm.id),COUNTIF('4. SSP'!$M:$M,_xlpm.id),COUNTIF('5. JSACI'!$M:$M,_xlpm.id),COUNTIF('6. AIN'!$M:$M,_xlpm.id),COUNTIF('7. MS'!$M:$M,_xlpm.id),COUNTIF('8. DS'!$M:$M,_xlpm.id),COUNTIF('9. RMF'!$M:$M,_xlpm.id),COUNTIF('10. PCU'!$M:$M,_xlpm.id)))) -> 0
A462: OMP1838-1839s1v1 | B462: O Museu Portuense | C462: 1838-1839 | D462: 1 | E462: 1 | F462: Portuguese | G462: Porto | H462: Portugal | I462: =_xlfn.LET(_xlpm.id,TRIM($A462),IF(_xlpm.id="","",SUM(COUNTIF('1. OP'!$M:$M,_xlpm.id),COUNTIF('2. JSEL'!$M:$M,_xlpm.id),COUNTIF('3. PSM'!$M:$M,_xlpm.id),COUNTIF('4. SSP'!$M:$M,_xlpm.id),COUNTIF('5. JSACI'!$M:$M,_xlpm.id),COUNTIF('6. AIN'!$M:$M,_xlpm.id),COUNTIF('7. MS'!$M:$M,_xlpm.id),COUNTIF('8. DS'!$M:$M,_xlpm.id),COUNTIF('9. RMF'!$M:$M,_xlpm.id),COUNTIF('10. PCU'!$M:$M,_xlpm.id)))) -> 1
A463: BFR1835s1v2 | B463: Bibliotheca Familiar e Recreativa | C463: 1835 | D463: 1 | E463: 2 | F463: Portuguese | G463: Lisbon | H463: Portugal | I463: =_xlfn.LET(_xlpm.id,TRIM($A463),IF(_xlpm.id="","",SUM(COUNTIF('1. OP'!$M:$M,_xlpm.id),COUNTIF('2. JSEL'!$M:$M,_xlpm.id),COUNTIF('3. PSM'!$M:$M,_xlpm.id),COUNTIF('4. SSP'!$M:$M,_xlpm.id),COUNTIF('5. JSACI'!$M:$M,_xlpm.id),COUNTIF('6. AIN'!$M:$M,_xlpm.id),COUNTIF('7. MS'!$M:$M,_xlpm.id),COUNTIF('8. DS'!$M:$M,_xlpm.id),COUNTIF('9. RMF'!$M:$M,_xlpm.id),COUNTIF('10. PCU'!$M:$M,_xlpm.id)))) -> 0
A464: BFR1836s1v3 | B464: Bibliotheca Familiar e Recreativa | C464: 1836 | D464: 1 | E464: 3 | F464: Portuguese | G464: Lisbon | H464: Portugal | I464: =_xlfn.LET(_xlpm.id,TRIM($A464),IF(_xlpm.id="","",SUM(COUNTIF('1. OP'!$M:$M,_xlpm.id),COUNTIF('2. JSEL'!$M:$M,_xlpm.id),COUNTIF('3. PSM'!$M:$M,_xlpm.id),COUNTIF('4. SSP'!$M:$M,_xlpm.id),COUNTIF('5. JSACI'!$M:$M,_xlpm.id),COUNTIF('6. AIN'!$M:$M,_xlpm.id),COUNTIF('7. MS'!$M:$M,_xlpm.id),COUNTIF('8. DS'!$M:$M,_xlpm.id),COUNTIF('9. RMF'!$M:$M,_xlpm.id),COUNTIF('10. PCU'!$M:$M,_xlpm.id)))) -> 0
A465: BFR1836s1v4 | B465: Bibliotheca Familiar e Recreativa | C465: 1836 | D465: 1 | E465: 4 | F465: Portuguese | G465: Lisbon | H465: Portugal | I465: =_xlfn.LET(_xlpm.id,TRIM($A465),IF(_xlpm.id="","",SUM(COUNTIF('1. OP'!$M:$M,_xlpm.id),COUNTIF('2. JSEL'!$M:$M,_xlpm.id),COUNTIF('3. PSM'!$M:$M,_xlpm.id),COUNTIF('4. SSP'!$M:$M,_xlpm.id),COUNTIF('5. JSACI'!$M:$M,_xlpm.id),COUNTIF('6. AIN'!$M:$M,_xlpm.id),COUNTIF('7. MS'!$M:$M,_xlpm.id),COUNTIF('8. DS'!$M:$M,_xlpm.id),COUNTIF('9. RMF'!$M:$M,_xlpm.id),COUNTIF('10. PCU'!$M:$M,_xlpm.id)))) -> 0
A466: MEARSL1788s1v1 | B466: Memorias Economicas da Academia Real das Sciencias de Lisboa Academia Real das Sciencias | C466: 1788 | D466: 1 | E466: 1 | F466: Portuguese | G466: Lisbon | H466: Portugal | I466: =_xlfn.LET(_xlpm.id,TRIM($A466),IF(_xlpm.id="","",SUM(COUNTIF('1. OP'!$M:$M,_xlpm.id),COUNTIF('2. JSEL'!$M:$M,_xlpm.id),COUNTIF('3. PSM'!$M:$M,_xlpm.id),COUNTIF('4. SSP'!$M:$M,_xlpm.id),COUNTIF('5. JSACI'!$M:$M,_xlpm.id),COUNTIF('6. AIN'!$M:$M,_xlpm.id),COUNTIF('7. MS'!$M:$M,_xlpm.id),COUNTIF('8. DS'!$M:$M,_xlpm.id),COUNTIF('9. RMF'!$M:$M,_xlpm.id),COUNTIF('10. PCU'!$M:$M,_xlpm.id)))) -> 3
A467: MEARSL1789s1v1 | B467: Memorias Economicas da Academia Real das Sciencias de Lisboa Academia Real das Sciencias | C467: 1789 | D467: 1 | E467: 1 | F467: Portuguese | G467: Lisbon | H467: Portugal | I467: =_xlfn.LET(_xlpm.id,TRIM($A467),IF(_xlpm.id="","",SUM(COUNTIF('1. OP'!$M:$M,_xlpm.id),COUNTIF('2. JSEL'!$M:$M,_xlpm.id),COUNTIF('3. PSM'!$M:$M,_xlpm.id),COUNTIF('4. SSP'!$M:$M,_xlpm.id),COUNTIF('5. JSACI'!$M:$M,_xlpm.id),COUNTIF('6. AIN'!$M:$M,_xlpm.id),COUNTIF('7. MS'!$M:$M,_xlpm.id),COUNTIF('8. DS'!$M:$M,_xlpm.id),COUNTIF('9. RMF'!$M:$M,_xlpm.id),COUNTIF('10. PCU'!$M:$M,_xlpm.id)))) -> 2
A468: MEARSL1790s1v2 | B468: Memorias Economicas da Academia Real das Sciencias de Lisboa Academia Real das Sciencias | C468: 1790 | D468: 1 | E468: 2 | F468: Portuguese | G468: Lisbon | H468: Portugal | I468: =_xlfn.LET(_xlpm.id,TRIM($A468),IF(_xlpm.id="","",SUM(COUNTIF('1. OP'!$M:$M,_xlpm.id),COUNTIF('2. JSEL'!$M:$M,_xlpm.id),COUNTIF('3. PSM'!$M:$M,_xlpm.id),COUNTIF('4. SSP'!$M:$M,_xlpm.id),COUNTIF('5. JSACI'!$M:$M,_xlpm.id),COUNTIF('6. AIN'!$M:$M,_xlpm.id),COUNTIF('7. MS'!$M:$M,_xlpm.id),COUNTIF('8. DS'!$M:$M,_xlpm.id),COUNTIF('9. RMF'!$M:$M,_xlpm.id),COUNTIF('10. PCU'!$M:$M,_xlpm.id)))) -> 2
A469: MEARSL1791s1v3 | B469: Memorias Economicas da Academia Real das Sciencias de Lisboa Academia Real das Sciencias | C469: 1791 | D469: 1 | E469: 3 | F469: Portuguese | G469: Lisbon | H469: Portugal | I469: =_xlfn.LET(_xlpm.id,TRIM($A469),IF(_xlpm.id="","",SUM(COUNTIF('1. OP'!$M:$M,_xlpm.id),COUNTIF('2. JSEL'!$M:$M,_xlpm.id),COUNTIF('3. PSM'!$M:$M,_xlpm.id),COUNTIF('4. SSP'!$M:$M,_xlpm.id),COUNTIF('5. JSACI'!$M:$M,_xlpm.id),COUNTIF('6. AIN'!$M:$M,_xlpm.id),COUNTIF('7. MS'!$M:$M,_xlpm.id),COUNTIF('8. DS'!$M:$M,_xlpm.id),COUNTIF('9. RMF'!$M:$M,_xlpm.id),COUNTIF('10. PCU'!$M:$M,_xlpm.id)))) -> 0
A470: MEARSL1799s1v2 | B470: Memorias Economicas da Academia Real das Sciencias de Lisboa Academia Real das Sciencias | C470: 1799 | D470: 1 | E470: 2 | F470: Portuguese | G470: Lisbon | H470: Portugal | I470: =_xlfn.LET(_xlpm.id,TRIM($A470),IF(_xlpm.id="","",SUM(COUNTIF('1. OP'!$M:$M,_xlpm.id),COUNTIF('2. JSEL'!$M:$M,_xlpm.id),COUNTIF('3. PSM'!$M:$M,_xlpm.id),COUNTIF('4. SSP'!$M:$M,_xlpm.id),COUNTIF('5. JSACI'!$M:$M,_xlpm.id),COUNTIF('6. AIN'!$M:$M,_xlpm.id),COUNTIF('7. MS'!$M:$M,_xlpm.id),COUNTIF('8. DS'!$M:$M,_xlpm.id),COUNTIF('9. RMF'!$M:$M,_xlpm.id),COUNTIF('10. PCU'!$M:$M,_xlpm.id)))) -> 1
A471: MEARSL1812s1v4 | B471: Memorias Economicas da Academia Real das Sciencias de Lisboa Academia Real das Sciencias | C471: 1812 | D471: 1 | E471: 4 | F471: Portuguese | G471: Lisbon | H471: Portugal | I471: =_xlfn.LET(_xlpm.id,TRIM($A471),IF(_xlpm.id="","",SUM(COUNTIF('1. OP'!$M:$M,_xlpm.id),COUNTIF('2. JSEL'!$M:$M,_xlpm.id),COUNTIF('3. PSM'!$M:$M,_xlpm.id),COUNTIF('4. SSP'!$M:$M,_xlpm.id),COUNTIF('5. JSACI'!$M:$M,_xlpm.id),COUNTIF('6. AIN'!$M:$M,_xlpm.id),COUNTIF('7. MS'!$M:$M,_xlpm.id),COUNTIF('8. DS'!$M:$M,_xlpm.id),COUNTIF('9. RMF'!$M:$M,_xlpm.id),COUNTIF('10. PCU'!$M:$M,_xlpm.id)))) -> 2
A472: MEARSL1815s1v5 | B472: Memorias Economicas da Academia Real das Sciencias de Lisboa Academia Real das Sciencias | C472: 1815 | D472: 1 | E472: 5 | F472: Portuguese | G472: Lisbon | H472: Portugal | I472: =_xlfn.LET(_xlpm.id,TRIM($A472),IF(_xlpm.id="","",SUM(COUNTIF('1. OP'!$M:$M,_xlpm.id),COUNTIF('2. JSEL'!$M:$M,_xlpm.id),COUNTIF('3. PSM'!$M:$M,_xlpm.id),COUNTIF('4. SSP'!$M:$M,_xlpm.id),COUNTIF('5. JSACI'!$M:$M,_xlpm.id),COUNTIF('6. AIN'!$M:$M,_xlpm.id),COUNTIF('7. MS'!$M:$M,_xlpm.id),COUNTIF('8. DS'!$M:$M,_xlpm.id),COUNTIF('9. RMF'!$M:$M,_xlpm.id),COUNTIF('10. PCU'!$M:$M,_xlpm.id)))) -> 0
A473: ASPIN1822s1v1 | B473: Annaes da Sociedade Promotora da Indústria Nacional | C473: 1822 | D473: 1 | E473: 1 | F473: Portuguese | G473: Lisbon | H473: Portugal | I473: =_xlfn.LET(_xlpm.id,TRIM($A473),IF(_xlpm.id="","",SUM(COUNTIF('1. OP'!$M:$M,_xlpm.id),COUNTIF('2. JSEL'!$M:$M,_xlpm.id),COUNTIF('3. PSM'!$M:$M,_xlpm.id),COUNTIF('4. SSP'!$M:$M,_xlpm.id),COUNTIF('5. JSACI'!$M:$M,_xlpm.id),COUNTIF('6. AIN'!$M:$M,_xlpm.id),COUNTIF('7. MS'!$M:$M,_xlpm.id),COUNTIF('8. DS'!$M:$M,_xlpm.id),COUNTIF('9. RMF'!$M:$M,_xlpm.id),COUNTIF('10. PCU'!$M:$M,_xlpm.id)))) -> 1
A474: ASPIN1826s1v2 | B474: Annaes da Sociedade Promotora da Indústria Nacional | C474: 1826 | D474: 1 | E474: 2 | F474: Portuguese | G474: Lisbon | H474: Portugal | I474: =_xlfn.LET(_xlpm.id,TRIM($A474),IF(_xlpm.id="","",SUM(COUNTIF('1. OP'!$M:$M,_xlpm.id),COUNTIF('2. JSEL'!$M:$M,_xlpm.id),COUNTIF('3. PSM'!$M:$M,_xlpm.id),COUNTIF('4. SSP'!$M:$M,_xlpm.id),COUNTIF('5. JSACI'!$M:$M,_xlpm.id),COUNTIF('6. AIN'!$M:$M,_xlpm.id),COUNTIF('7. MS'!$M:$M,_xlpm.id),COUNTIF('8. DS'!$M:$M,_xlpm.id),COUNTIF('9. RMF'!$M:$M,_xlpm.id),COUNTIF('10. PCU'!$M:$M,_xlpm.id)))) -> 0
... A496: BGTM1840s1v19 | B496: Bulletin général de thérapeutique médicale, chirurgicale, obstétricale et pharmaceutique | C496: 1840 | D496: 1 | E496: 19 | F496: French | G496: Paris | H496: France | I496: =_xlfn.LET(_xlpm.id,TRIM($A496),IF(_xlpm.id="","",SUM(COUNTIF('1. OP'!$M:$M,_xlpm.id),COUNTIF('2. JSEL'!$M:$M,_xlpm.id),COUNTIF('3. PSM'!$M:$M,_xlpm.id),COUNTIF('4. SSP'!$M:$M,_xlpm.id),COUNTIF('5. JSACI'!$M:$M,_xlpm.id),COUNTIF('6. AIN'!$M:$M,_xlpm.id),COUNTIF('7. MS'!$M:$M,_xlpm.id),COUNTIF('8. DS'!$M:$M,_xlpm.id),COUNTIF('9. RMF'!$M:$M,_xlpm.id),COUNTIF('10. PCU'!$M:$M,_xlpm.id)))) -> 0
A497: LM1833-1834s1v1 | B497: La Mosaïque | C497: 1833-1834 | D497: 1 | E497: 1 | F497: French | G497: Paris | H497: France | I497: =_xlfn.LET(_xlpm.id,TRIM($A497),IF(_xlpm.id="","",SUM(COUNTIF('1. OP'!$M:$M,_xlpm.id),COUNTIF('2. JSEL'!$M:$M,_xlpm.id),COUNTIF('3. PSM'!$M:$M,_xlpm.id),COUNTIF('4. SSP'!$M:$M,_xlpm.id),COUNTIF('5. JSACI'!$M:$M,_xlpm.id),COUNTIF('6. AIN'!$M:$M,_xlpm.id),COUNTIF('7. MS'!$M:$M,_xlpm.id),COUNTIF('8. DS'!$M:$M,_xlpm.id),COUNTIF('9. RMF'!$M:$M,_xlpm.id),COUNTIF('10. PCU'!$M:$M,_xlpm.id)))) -> 3
A498: LM1834s1v2 | B498: La Mosaïque | C498: 1834 | D498: 1 | E498: 2 | F498: French | G498: Paris | H498: France | I498: =_xlfn.LET(_xlpm.id,TRIM($A498),IF(_xlpm.id="","",SUM(COUNTIF('1. OP'!$M:$M,_xlpm.id),COUNTIF('2. JSEL'!$M:$M,_xlpm.id),COUNTIF('3. PSM'!$M:$M,_xlpm.id),COUNTIF('4. SSP'!$M:$M,_xlpm.id),COUNTIF('5. JSACI'!$M:$M,_xlpm.id),COUNTIF('6. AIN'!$M:$M,_xlpm.id),COUNTIF('7. MS'!$M:$M,_xlpm.id),COUNTIF('8. DS'!$M:$M,_xlpm.id),COUNTIF('9. RMF'!$M:$M,_xlpm.id),COUNTIF('10. PCU'!$M:$M,_xlpm.id)))) -> 0
A499: LM1835-1836s1v3 | B499: La Mosaïque | C499: 1835-1836 | D499: 1 | E499: 3 | F499: French | G499: Paris | H499: France | I499: =_xlfn.LET(_xlpm.id,TRIM($A499),IF(_xlpm.id="","",SUM(COUNTIF('1. OP'!$M:$M,_xlpm.id),COUNTIF('2. JSEL'!$M:$M,_xlpm.id),COUNTIF('3. PSM'!$M:$M,_xlpm.id),COUNTIF('4. SSP'!$M:$M,_xlpm.id),COUNTIF('5. JSACI'!$M:$M,_xlpm.id),COUNTIF('6. AIN'!$M:$M,_xlpm.id),COUNTIF('7. MS'!$M:$M,_xlpm.id),COUNTIF('8. DS'!$M:$M,_xlpm.id),COUNTIF('9. RMF'!$M:$M,_xlpm.id),COUNTIF('10. PCU'!$M:$M,_xlpm.id)))) -> 0
A500: LM1839s2v1 | B500: La Mosaïque | C500: 1839 | D500: 2 | E500: 1 | F500: French | G500: Paris | H500: France | I500: =_xlfn.LET(_xlpm.id,TRIM($A500),IF(_xlpm.id="","",SUM(COUNTIF('1. OP'!$M:$M,_xlpm.id),COUNTIF('2. JSEL'!$M:$M,_xlpm.id),COUNTIF('3. PSM'!$M:$M,_xlpm.id),COUNTIF('4. SSP'!$M:$M,_xlpm.id),COUNTIF('5. JSACI'!$M:$M,_xlpm.id),COUNTIF('6. AIN'!$M:$M,_xlpm.id),COUNTIF('7. MS'!$M:$M,_xlpm.id),COUNTIF('8. DS'!$M:$M,_xlpm.id),COUNTIF('9. RMF'!$M:$M,_xlpm.id),COUNTIF('10. PCU'!$M:$M,_xlpm.id)))) -> 0
A501: JCUP1827s1v5 | B501: Journal des connaissances usuelles et pratiques | C501: 1827 | D501: 1 | E501: 5 | F501: French | G501: Paris | H501: France | I501: =_xlfn.LET(_xlpm.id,TRIM($A501),IF(_xlpm.id="","",SUM(COUNTIF('1. OP'!$M:$M,_xlpm.id),COUNTIF('2. JSEL'!$M:$M,_xlpm.id),COUNTIF('3. PSM'!$M:$M,_xlpm.id),COUNTIF('4. SSP'!$M:$M,_xlpm.id),COUNTIF('5. JSACI'!$M:$M,_xlpm.id),COUNTIF('6. AIN'!$M:$M,_xlpm.id),COUNTIF('7. MS'!$M:$M,_xlpm.id),COUNTIF('8. DS'!$M:$M,_xlpm.id),COUNTIF('9. RMF'!$M:$M,_xlpm.id),COUNTIF('10. PCU'!$M:$M,_xlpm.id)))) -> 3
A502: JCUP1827s1v6 | B502: Journal des connaissances usuelles et pratiques | C502: 1827 | D502: 1 | E502: 6 | F502: French | G502: Paris | H502: France | I502: =_xlfn.LET(_xlpm.id,TRIM($A502),IF(_xlpm.id="","",SUM(COUNTIF('1. OP'!$M:$M,_xlpm.id),COUNTIF('2. JSEL'!$M:$M,_xlpm.id),COUNTIF('3. PSM'!$M:$M,_xlpm.id),COUNTIF('4. SSP'!$M:$M,_xlpm.id),COUNTIF('5. JSACI'!$M:$M,_xlpm.id),COUNTIF('6. AIN'!$M:$M,_xlpm.id),COUNTIF('7. MS'!$M:$M,_xlpm.id),COUNTIF('8. DS'!$M:$M,_xlpm.id),COUNTIF('9. RMF'!$M:$M,_xlpm.id),COUNTIF('10. PCU'!$M:$M,_xlpm.id)))) -> 0
A503: JCUP1830s1v1 | B503: Journal des connaissances usuelles et pratiques | C503: 1830 | D503: 1 | E503: 1 | F503: French | G503: Paris | H503: France | I503: =_xlfn.LET(_xlpm.id,TRIM($A503),IF(_xlpm.id="","",SUM(COUNTIF('1. OP'!$M:$M,_xlpm.id),COUNTIF('2. JSEL'!$M:$M,_xlpm.id),COUNTIF('3. PSM'!$M:$M,_xlpm.id),COUNTIF('4. SSP'!$M:$M,_xlpm.id),COUNTIF('5. JSACI'!$M:$M,_xlpm.id),COUNTIF('6. AIN'!$M:$M,_xlpm.id),COUNTIF('7. MS'!$M:$M,_xlpm.id),COUNTIF('8. DS'!$M:$M,_xlpm.id),COUNTIF('9. RMF'!$M:$M,_xlpm.id),COUNTIF('10. PCU'!$M:$M,_xlpm.id)))) -> 0
A504: JCUP1830s1v2 | B504: Journal des connaissances usuelles et pratiques | C504: 1830 | D504: 1 | E504: 2 | F504: French | G504: Paris | H504: France | I504: =_xlfn.LET(_xlpm.id,TRIM($A504),IF(_xlpm.id="","",SUM(COUNTIF('1. OP'!$M:$M,_xlpm.id),COUNTIF('2. JSEL'!$M:$M,_xlpm.id),COUNTIF('3. PSM'!$M:$M,_xlpm.id),COUNTIF('4. SSP'!$M:$M,_xlpm.id),COUNTIF('5. JSACI'!$M:$M,_xlpm.id),COUNTIF('6. AIN'!$M:$M,_xlpm.id),COUNTIF('7. MS'!$M:$M,_xlpm.id),COUNTIF('8. DS'!$M:$M,_xlpm.id),COUNTIF('9. RMF'!$M:$M,_xlpm.id),COUNTIF('10. PCU'!$M:$M,_xlpm.id)))) -> 0
A505: JCUP1830s1v3 | B505: Journal des connaissances usuelles et pratiques | C505: 1830 | D505: 1 | E505: 3 | F505: French | G505: Paris | H505: France | I505: =_xlfn.LET(_xlpm.id,TRIM($A505),IF(_xlpm.id="","",SUM(COUNTIF('1. OP'!$M:$M,_xlpm.id),COUNTIF('2. JSEL'!$M:$M,_xlpm.id),COUNTIF('3. PSM'!$M:$M,_xlpm.id),COUNTIF('4. SSP'!$M:$M,_xlpm.id),COUNTIF('5. JSACI'!$M:$M,_xlpm.id),COUNTIF('6. AIN'!$M:$M,_xlpm.id),COUNTIF('7. MS'!$M:$M,_xlpm.id),COUNTIF('8. DS'!$M:$M,_xlpm.id),COUNTIF('9. RMF'!$M:$M,_xlpm.id),COUNTIF('10. PCU'!$M:$M,_xlpm.id)))) -> 0
A506: JCUP1830s1v4 | B506: Journal des connaissances usuelles et pratiques | C506: 1830 | D506: 1 | E506: 4 | F506: French | G506: Paris | H506: France | I506: =_xlfn.LET(_xlpm.id,TRIM($A506),IF(_xlpm.id="","",SUM(COUNTIF('1. OP'!$M:$M,_xlpm.id),COUNTIF('2. JSEL'!$M:$M,_xlpm.id),COUNTIF('3. PSM'!$M:$M,_xlpm.id),COUNTIF('4. SSP'!$M:$M,_xlpm.id),COUNTIF('5. JSACI'!$M:$M,_xlpm.id),COUNTIF('6. AIN'!$M:$M,_xlpm.id),COUNTIF('7. MS'!$M:$M,_xlpm.id),COUNTIF('8. DS'!$M:$M,_xlpm.id),COUNTIF('9. RMF'!$M:$M,_xlpm.id),COUNTIF('10. PCU'!$M:$M,_xlpm.id)))) -> 1
A507: JCUP1830s1v5 | B507: Journal des connaissances usuelles et pratiques | C507: 1830 | D507: 1 | E507: 5 | F507: French | G507: Paris | H507: France | I507: =_xlfn.LET(_xlpm.id,TRIM($A507),IF(_xlpm.id="","",SUM(COUNTIF('1. OP'!$M:$M,_xlpm.id),COUNTIF('2. JSEL'!$M:$M,_xlpm.id),COUNTIF('3. PSM'!$M:$M,_xlpm.id),COUNTIF('4. SSP'!$M:$M,_xlpm.id),COUNTIF('5. JSACI'!$M:$M,_xlpm.id),COUNTIF('6. AIN'!$M:$M,_xlpm.id),COUNTIF('7. MS'!$M:$M,_xlpm.id),COUNTIF('8. DS'!$M:$M,_xlpm.id),COUNTIF('9. RMF'!$M:$M,_xlpm.id),COUNTIF('10. PCU'!$M:$M,_xlpm.id)))) -> 0
A508: JCUP1830s1v6 | B508: Journal des connaissances usuelles et pratiques | C508: 1830 | D508: 1 | E508: 6 | F508: French | G508: Paris | H508: France | I508: =_xlfn.LET(_xlpm.id,TRIM($A508),IF(_xlpm.id="","",SUM(COUNTIF('1. OP'!$M:$M,_xlpm.id),COUNTIF('2. JSEL'!$M:$M,_xlpm.id),COUNTIF('3. PSM'!$M:$M,_xlpm.id),COUNTIF('4. SSP'!$M:$M,_xlpm.id),COUNTIF('5. JSACI'!$M:$M,_xlpm.id),COUNTIF('6. AIN'!$M:$M,_xlpm.id),COUNTIF('7. MS'!$M:$M,_xlpm.id),COUNTIF('8. DS'!$M:$M,_xlpm.id),COUNTIF('9. RMF'!$M:$M,_xlpm.id),COUNTIF('10. PCU'!$M:$M,_xlpm.id)))) -> 6
A509: JCUP1830s1v11 | B509: Journal des connaissances usuelles et pratiques | C509: 1830 | D509: 1 | E509: 11 | F509: French | G509: Paris | H509: France | I509: =_xlfn.LET(_xlpm.id,TRIM($A509),IF(_xlpm.id="","",SUM(COUNTIF('1. OP'!$M:$M,_xlpm.id),COUNTIF('2. JSEL'!$M:$M,_xlpm.id),COUNTIF('3. PSM'!$M:$M,_xlpm.id),COUNTIF('4. SSP'!$M:$M,_xlpm.id),COUNTIF('5. JSACI'!$M:$M,_xlpm.id),COUNTIF('6. AIN'!$M:$M,_xlpm.id),COUNTIF('7. MS'!$M:$M,_xlpm.id),COUNTIF('8. DS'!$M:$M,_xlpm.id),COUNTIF('9. RMF'!$M:$M,_xlpm.id),COUNTIF('10. PCU'!$M:$M,_xlpm.id)))) -> 3
A510: JCUP1830s1v12 | B510: Journal des connaissances usuelles et pratiques | C510: 1830 | D510: 1 | E510: 12 | F510: French | G510: Paris | H510: France | I510: =_xlfn.LET(_xlpm.id,TRIM($A510),IF(_xlpm.id="","",SUM(COUNTIF('1. OP'!$M:$M,_xlpm.id),COUNTIF('2. JSEL'!$M:$M,_xlpm.id),COUNTIF('3. PSM'!$M:$M,_xlpm.id),COUNTIF('4. SSP'!$M:$M,_xlpm.id),COUNTIF('5. JSACI'!$M:$M,_xlpm.id),COUNTIF('6. AIN'!$M:$M,_xlpm.id),COUNTIF('7. MS'!$M:$M,_xlpm.id),COUNTIF('8. DS'!$M:$M,_xlpm.id),COUNTIF('9. RMF'!$M:$M,_xlpm.id),COUNTIF('10. PCU'!$M:$M,_xlpm.id)))) -> 4
A511: JCUP1831s1v7 | B511: Journal des connaissances usuelles et pratiques | C511: 1831 | D511: 1 | E511: 7 | F511: French | G511: Paris | H511: France | I511: =_xlfn.LET(_xlpm.id,TRIM($A511),IF(_xlpm.id="","",SUM(COUNTIF('1. OP'!$M:$M,_xlpm.id),COUNTIF('2. JSEL'!$M:$M,_xlpm.id),COUNTIF('3. PSM'!$M:$M,_xlpm.id),COUNTIF('4. SSP'!$M:$M,_xlpm.id),COUNTIF('5. JSACI'!$M:$M,_xlpm.id),COUNTIF('6. AIN'!$M:$M,_xlpm.id),COUNTIF('7. MS'!$M:$M,_xlpm.id),COUNTIF('8. DS'!$M:$M,_xlpm.id),COUNTIF('9. RMF'!$M:$M,_xlpm.id),COUNTIF('10. PCU'!$M:$M,_xlpm.id)))) -> 0
... A545: JCU1838s2v8 | B545: Journal des connaissances utiles | C545: 1838 | D545: 2 | E545: 8 | F545: French | G545: Paris | H545: France | I545: =_xlfn.LET(_xlpm.id,TRIM($A545),IF(_xlpm.id="","",SUM(COUNTIF('1. OP'!$M:$M,_xlpm.id),COUNTIF('2. JSEL'!$M:$M,_xlpm.id),COUNTIF('3. PSM'!$M:$M,_xlpm.id),COUNTIF('4. SSP'!$M:$M,_xlpm.id),COUNTIF('5. JSACI'!$M:$M,_xlpm.id),COUNTIF('6. AIN'!$M:$M,_xlpm.id),COUNTIF('7. MS'!$M:$M,_xlpm.id),COUNTIF('8. DS'!$M:$M,_xlpm.id),COUNTIF('9. RMF'!$M:$M,_xlpm.id),COUNTIF('10. PCU'!$M:$M,_xlpm.id)))) -> 0
A546: JBCU1831-1832s1v1 | B546: Journal Belge des connaissances utiles | C546: 1831-1832 | D546: 1 | E546: 1 | F546: French | G546: Brussels | H546: Belgium | I546: =_xlfn.LET(_xlpm.id,TRIM($A546),IF(_xlpm.id="","",SUM(COUNTIF('1. OP'!$M:$M,_xlpm.id),COUNTIF('2. JSEL'!$M:$M,_xlpm.id),COUNTIF('3. PSM'!$M:$M,_xlpm.id),COUNTIF('4. SSP'!$M:$M,_xlpm.id),COUNTIF('5. JSACI'!$M:$M,_xlpm.id),COUNTIF('6. AIN'!$M:$M,_xlpm.id),COUNTIF('7. MS'!$M:$M,_xlpm.id),COUNTIF('8. DS'!$M:$M,_xlpm.id),COUNTIF('9. RMF'!$M:$M,_xlpm.id),COUNTIF('10. PCU'!$M:$M,_xlpm.id)))) -> 21
...

Sheet Corpus A
A1: File | B1: Full title | C1: Short title | D1: Initialism | E1: Start | F1: End | G1: Serie | H1: Volume | I1: Language
A2: OP1813s1v1 | B2: O Patriota: jornal litterario, politico, mercantil, do Rio de Janeiro | C2: O Patriota | D2: OP | E2: 1813 | F2: 1813 | G2: 1 | H2: 1 | I2: Portuguese
A3: OP1813s1v2 | B3: O Patriota: jornal litterario, politico, mercantil, do Rio de Janeiro | C3: O Patriota | D3: OP | E3: 1813 | F3: 1813 | G3: 1 | H3: 2 | I3: Portuguese
A4: OP1814s1v3 | B4: O Patriota: jornal litterario, politico, mercantil, do Rio de Janeiro | C4: O Patriota | D4: OP | E4: 1814 | F4: 1814 | G4: 1 | H4: 3 | I4: Portuguese
A5: JSEL1826s1v1n1 | B5: Jornal Scientifico, Economico e Litterario, ou Collecao de varias pecas, memorias, relacoens, viagens, poesias e anedoctas. Mixto de instruccao e de recreio, accommodado a todo o genero de leitores. | C5: Jornal Scientifico, Economico e Litterario | D5: JSEL | E5: 1826 | F5: 1826 | G5: 1 | H5: 1 | I5: Portuguese
A6: JSEL1826s1v1n2 | B6: Jornal Scientifico, Economico e Litterario, ou Collecao de varias pecas, memorias, relacoens, viagens, poesias e anedoctas. Mixto de instruccao e de recreio, accommodado a todo o genero de leitores. | C6: Jornal Scientifico, Economico e Litterario | D6: JSEL | E6: 1826 | F6: 1826 | G6: 1 | H6: 1 | I6: Portuguese
A7: JSEL1826s1v1n3 | B7: Jornal Scientifico, Economico e Litterario, ou Collecao de varias pecas, memorias, relacoens, viagens, poesias e anedoctas. Mixto de instruccao e de recreio, accommodado a todo o genero de leitores. | C7: Jornal Scientifico, Economico e Litterario | D7: JSEL | E7: 1826 | F7: 1826 | G7: 1 | H7: 1 | I7: Portuguese
A8: PSM1827s1v1 | B8: O Propagador das Sciencias Medicas, ou Annaes de Medicina, Cirurgia, e Pharmacia; para o Imperio do Brasil e naçoes estrangeiras, seguidos de hum boletim especialmente consagrado as sciencias naturaes, zoologia, botanica. | C8: O Propagador das Sciencias Medicas | D8: PSM | E8: 1827 | F8: 1827 | G8: 1 | H8: 1 | I8: Portuguese
A9: PSM1827s1v2 | B9: O Propagador das Sciencias Medicas, ou Annaes de Medicina, Cirurgia, e Pharmacia; para o Imperio do Brasil e naçoes estrangeiras, seguidos de hum boletim especialmente consagrado as sciencias naturaes, zoologia, botanica. | C9: O Propagador das Sciencias Medicas | D9: PSM | E9: 1827 | F9: 1827 | G9: 1 | H9: 2 | I9: Portuguese
A10: PSM1827s1v3 | B10: O Propagador das Sciencias Medicas, ou Annaes de Medicina, Cirurgia, e Pharmacia; para o Imperio do Brasil e naçoes estrangeiras, seguidos de hum boletim especialmente consagrado as sciencias naturaes, zoologia, botanica. | C10: O Propagador das Sciencias Medicas | D10: PSM | E10: 1827 | F10: 1827 | G10: 1 | H10: 3 | I10: Portuguese
A11: PSM1827-8s1v4 | B11: O Propagador das Sciencias Medicas, ou Annaes de Medicina, Cirurgia, e Pharmacia; para o Imperio do Brasil e naçoes estrangeiras, seguidos de hum boletim especialmente consagrado as sciencias naturaes, zoologia, botanica. | C11: O Propagador das Sciencias Medicas | D11: PSM | E11: 1827 | F11: 1828 | G11: 1 | H11: 4 | I11: Portuguese
A12: SSP1831s1v1n1-53 | B12: Semanario de Saude Publica: pela Sociedade de Medicina do Rio de Janeiro. | C12: Semanario de Saude Publica | D12: SSP | E12: 1831 | F12: 1831 | G12: 1 | H12: 1 | I12: Portuguese
A13: SSP1832s1v1n54-132 | B13: Semanario de Saude Publica: pela Sociedade de Medicina do Rio de Janeiro. | C13: Semanario de Saude Publica | D13: SSP | E13: 1832 | F13: 1832 | G13: 1 | H13: 1 | I13: Portuguese
... A35: PCU1836s1v1n8 | B35: O Propagador de Conhecimentos Uteis | C35: O Propagador de Conhecimentos Uteis | D35: PCU | E35: 1836 | F35: 1836 | G35: 1 | H35: 1 | I35: Portuguese

Sheet Overview
C1: 1. OP | D1: 2. JSEL | E1: 3. PSM | F1: 4. SSP | G1: 5. JSACI | H1: 6. AIN | I1: 7. MS | J1: 8. DS | K1: 9. RMF | L1: 10. PCU
A2: Size | B2: Total, Articles | C2: =COUNTA('1. OP'!J2:J1048576) -> 289 | D2: =COUNTA('2. JSEL'!J2:J1048576) -> 47 | E2: =COUNTA('3. PSM'!J2:J1048576) -> 205 | F2: =COUNTA('4. SSP'!J2:J1048576) -> 494 | G2: =COUNTA('5. JSACI'!J2:J1048576) -> 45 | H2: =COUNTA('6. AIN'!J2:J1048576) -> 857 | I2: =COUNTA('7. MS'!J2:J1048576) -> 16 | J2: =COUNTA('8. DS'!J2:J1048576) -> 384 | K2: =COUNTA('9. RMF'!J2:J1048576) -> 703 | L2: =COUNTA('10. PCU'!J2:J1048576) -> 8
B3: Total, Pages | C3: =SUM('1. OP'!H2:H5536) -> 1849 | D3: =SUM('2. JSEL'!H2:H1048576) -> 279 | E3: =SUM('3. PSM'!H2:H1048576) -> 1063 | F3: =SUM('4. SSP'!H2:H1048576) -> 563 | G3: =SUM('5. JSACI'!H2:H1048576) -> 235 | H3: =SUM('6. AIN'!H2:H1048576) -> 3323 | I3: =SUM('7. MS'!H2:H1048573) -> 14 | J3: =SUM('8. DS'!H2:H1048576) -> 427 | K3: =SUM('9. RMF'!H2:H1048576) -> 2886 | L3: =SUM('10. PCU'!H2:H1048576) -> 16
A4: Scientific | B4: Yes (Articles) | C4: {=SUM(_xlfn.BYROW('1. OP'!R2:R10002, _xlfn.LAMBDA(_xlpm.x, --ISNUMBER(MATCH("TRUE", _xlfn.TEXTSPLIT(LOWER(_xlpm.x)," "), 0)))))} -> 67 | D4: {=SUM(_xlfn.BYROW('2. JSEL'!R2:R48, _xlfn.LAMBDA(_xlpm.x, --ISNUMBER(MATCH("TRUE", _xlfn.TEXTSPLIT(LOWER(_xlpm.x)," "), 0)))))} -> 15 | E4: {=SUM(_xlfn.BYROW('3. PSM'!R2:R206, _xlfn.LAMBDA(_xlpm.x, --ISNUMBER(MATCH("TRUE", _xlfn.TEXTSPLIT(LOWER(_xlpm.x)," "), 0)))))} -> 205 | F4: {=SUM(_xlfn.BYROW('4. SSP'!R2:R495, _xlfn.LAMBDA(_xlpm.x, --ISNUMBER(MATCH("TRUE", _xlfn.TEXTSPLIT(LOWER(_xlpm.x)," "), 0)))))} -> 418 | G4: {=SUM(_xlfn.BYROW('5. JSACI'!R2:R46, _xlfn.LAMBDA(_xlpm.x, --ISNUMBER(MATCH("TRUE", _xlfn.TEXTSPLIT(LOWER(_xlpm.x)," "), 0)))))} -> 28 | H4: {=SUM(_xlfn.BYROW('6. AIN'!R2:R858, _xlfn.LAMBDA(_xlpm.x, --ISNUMBER(MATCH("TRUE", _xlfn.TEXTSPLIT(LOWER(_xlpm.x)," "), 0)))))} -> 722 | I4: {=SUM(_xlfn.BYROW('7. MS'!R2:R9999, _xlfn.LAMBDA(_xlpm.x, --ISNUMBER(MATCH("TRUE", _xlfn.TEXTSPLIT(LOWER(_xlpm.x)," "), 0)))))} -> 13 | J4: {=SUM(_xlfn.BYROW('8. DS'!R2:R10006, _xlfn.LAMBDA(_xlpm.x, --ISNUMBER(MATCH("TRUE", _xlfn.TEXTSPLIT(LOWER(_xlpm.x)," "), 0)))))} -> 382 | K4: {=SUM(_xlfn.BYROW('9. RMF'!R2:R10124, _xlfn.LAMBDA(_xlpm.x, --ISNUMBER(MATCH("TRUE", _xlfn.TEXTSPLIT(LOWER(_xlpm.x)," "), 0)))))} -> 557 | L4: {=SUM(_xlfn.BYROW('10. PCU'!R2:R10001, _xlfn.LAMBDA(_xlpm.x, --ISNUMBER(MATCH("TRUE", _xlfn.TEXTSPLIT(LOWER(_xlpm.x)," "), 0)))))} -> 4
B5: Yes (Pages) | C5: =SUMIF('1. OP'!$R:$R,"TRUE",'1. OP'!$H:$H) -> 741.5 | D5: =SUMIF('2. JSEL'!$R:$R,"TRUE",'2. JSEL'!$H:$H) -> 132.5 | E5: =SUMIF('3. PSM'!$R:$R,"TRUE",'3. PSM'!$H:$H) -> 1063 | F5: =SUMIF('4. SSP'!$R:$R,"TRUE",'4. SSP'!$H:$H) -> 477.88333 | G5: =SUMIF('5. JSACI'!$R:$R,"TRUE",'5. JSACI'!$H:$H) -> 162.33333 | H5: =SUMIF('6. AIN'!$R:$R,"TRUE",'6. AIN'!$H:$H) -> 3005.8333 | I5: =SUMIF('7. MS'!$R:$R,"TRUE",'7. MS'!$H:$H) -> 12 | J5: =SUMIF('8. DS'!$R:$R,"TRUE",'8. DS'!$H:$H) -> 426.05 | K5: =SUMIF('9. RMF'!$R:$R,"TRUE",'9. RMF'!$H:$H) -> 2492.1667 | L5: =SUMIF('10. PCU'!$R:$R,"TRUE",'10. PCU'!$H:$H) -> 6.25
B6: Science-Ratio (Articles) | C6: =IFERROR(C4/C2,"") -> 0.23183391 | D6: =IFERROR(D4/D2,"") -> 0.31914894 | E6: =IFERROR(E4/E2,"") -> 1 | F6: =IFERROR(F4/F2,"") -> 0.84615385 | G6: =IFERROR(G4/G2,"") -> 0.62222222 | H6: =IFERROR(H4/H2,"") -> 0.84247375 | I6: =IFERROR(I4/I2,"") -> 0.8125 | J6: =IFERROR(J4/J2,"") -> 0.99479167 | ... L6: =IFERROR(L4/L2,"") -> 0.5
B7: Science-Ratio (Pages) | C7: =IFERROR(C5/C3,"") -> 0.40102758 | D7: =IFERROR(D5/D3,"") -> 0.47491039 | E7: =IFERROR(E5/E3,"") -> 1 | F7: =IFERROR(F5/F3,"") -> 0.84881587 | G7: =IFERROR(G5/G3,"") -> 0.69078014 | H7: =IFERROR(H5/H3,"") -> 0.90455412 | I7: =IFERROR(I5/I3,"") -> 0.85714286 | J7: =IFERROR(J5/J3,"") -> 0.99777518 | ... L7: =IFERROR(L5/L3,"") -> 0.390625
A8: Provenance,Articles (All) | B8: Local | C8: =COUNTIF('1. OP'!O2:O10002, "*Local*") -> 180 | D8: =COUNTIF('2. JSEL'!O2:O48, "*Local*") -> 28 | E8: =COUNTIF('3. PSM'!O2:O206, "*Local*") -> 28 | F8: =COUNTIF('4. SSP'!O2:O495, "*Local*") -> 262 | G8: =COUNTIF('5. JSACI'!O2:O46, "*Local*") -> 31 | H8: =COUNTIF('6. AIN'!O2:O858, "*Local*") -> 303 | I8: =COUNTIF('7. MS'!O2:O9999, "*Local*") -> 4 | J8: =COUNTIF('8. DS'!O2:O10006, "*Local*") -> 132 | K8: =COUNTIF('9. RMF'!O2:O10124, "*Local*") -> 452 | L8: =COUNTIF('10. PCU'!O2:O10001, "*Local*") -> 2
B9: Reuse (Translation) | C9: =COUNTIF('1. OP'!O2:O10002, "*Reuse (Translation)*") -> 59 | D9: =COUNTIF('2. JSEL'!O2:O48, "*Reuse (Translation)*") -> 13 | E9: =COUNTIF('3. PSM'!O2:O206, "*Reuse (Translation)*") -> 128 | F9: =COUNTIF('4. SSP'!O2:O495, "*Reuse (Translation)*") -> 173 | G9: =COUNTIF('5. JSACI'!O2:O46, "*Reuse (Translation)*") -> 6 | H9: =COUNTIF('6. AIN'!O2:O858, "*Reuse (Translation)*") -> 449 | I9: =COUNTIF('7. MS'!O2:O9999, "*Reuse (Translation)*") -> 10 | J9: =COUNTIF('8. DS'!O2:O10006, "*Reuse (Translation)*") -> 134 | K9: =COUNTIF('9. RMF'!O2:O10124, "*Reuse (Translation)*") -> 132 | L9: =COUNTIF('10. PCU'!O2:O10001, "*Reuse (Translation)*") -> 4
B10: Reuse (Reprint) | C10: =COUNTIF('1. OP'!O2:O10002, "*Reuse (Reprint)*") -> 34 | D10: =COUNTIF('2. JSEL'!O2:O48, "*Reuse (Reprint)*") -> 1 | E10: =COUNTIF('3. PSM'!O2:O206, "*Reuse (Reprint)*") -> 0 | F10: =COUNTIF('4. SSP'!O2:O495, "*Reuse (Reprint)*") -> 1 | G10: =COUNTIF('5. JSACI'!O2:O46, "*Reuse (Reprint)*") -> 1 | H10: =COUNTIF('6. AIN'!O2:O858, "*Reuse (Reprint)*") -> 50 | I10: =COUNTIF('7. MS'!O2:O9999, "*Reuse (Reprint)*") -> 0 | J10: =COUNTIF('8. DS'!O2:O10006, "*Reuse (Reprint)*") -> 18 | K10: =COUNTIF('9. RMF'!O2:O10124, "*Reuse (Reprint)*") -> 39 | L10: =COUNTIF('10. PCU'!O2:O10001, "*Reuse (Reprint)*") -> 1
B11: Adaptation | C11: =COUNTIF('1. OP'!O2:O10002, "*Adaptation*") -> 5 | D11: =COUNTIF('2. JSEL'!O2:O48, "*Adaptation*") -> 5 | E11: =COUNTIF('3. PSM'!O2:O206, "*Adaptation*") -> 49 | F11: =COUNTIF('4. SSP'!O2:O495, "*Adaptation*") -> 56 | G11: =COUNTIF('5. JSACI'!O2:O46, "*Adaptation*") -> 6 | H11: =COUNTIF('6. AIN'!O2:O858, "*Adaptation*") -> 53 | I11: =COUNTIF('7. MS'!O2:O9999, "*Adaptation*") -> 2 | J11: =COUNTIF('8. DS'!O2:O10006, "*Adaptation*") -> 98 | K11: =COUNTIF('9. RMF'!O2:O10124, "*Adaptation*") -> 76 | L11: =COUNTIF('10. PCU'!O2:O10001, "*Adaptation*") -> 1
B12: ESA (Total) | C12: =SUM(C9:C11) -> 98 | D12: =SUM(D9:D11) -> 19 | E12: =SUM(E9:E11) -> 177 | F12: =SUM(F9:F11) -> 230 | G12: =SUM(G9:G11) -> 13 | H12: =SUM(H9:H11) -> 552 | I12: =SUM(I9:I11) -> 12 | J12: =SUM(J9:J11) -> 250 | ... L12: =SUM(L9:L11) -> 6
B13: Trans.-Ratio | C13: =IFERROR(C9/C2,"") -> 0.20415225 | D13: =IFERROR(D9/D2,"") -> 0.27659574 | E13: =IFERROR(E9/E2,"") -> 0.62439024 | F13: =IFERROR(F9/F2,"") -> 0.35020243 | G13: =IFERROR(G9/G2,"") -> 0.13333333 | H13: =IFERROR(H9/H2,"") -> 0.52392065 | I13: =IFERROR(I9/I2,"") -> 0.625 | J13: =IFERROR(J9/J2,"") -> 0.34895833 | ... L13: =IFERROR(L9/L2,"") -> 0.5
B14: Reprint-Ratio | C14: =IFERROR(C10/C2,"") -> 0.11764706 | D14: =IFERROR(D10/D2,"") -> 0.021276596 | E14: =IFERROR(E10/E2,"") -> 0 | F14: =IFERROR(F10/F2,"") -> 0.0020242915 | G14: =IFERROR(G10/G2,"") -> 0.022222222 | H14: =IFERROR(H10/H2,"") -> 0.058343057 | I14: =IFERROR(I10/I2,"") -> 0 | J14: =IFERROR(J10/J2,"") -> 0.046875 | ... L14: =IFERROR(L10/L2,"") -> 0.125
B15: ESA-Ratio | C15: =IFERROR(C12/C2,"") -> 0.33910035 | D15: =IFERROR(D12/D2,"") -> 0.40425532 | E15: =IFERROR(E12/E2,"") -> 0.86341463 | F15: =IFERROR(F12/F2,"") -> 0.46558704 | G15: =IFERROR(G12/G2,"") -> 0.28888889 | H15: =IFERROR(H12/H2,"") -> 0.64410735 | I15: =IFERROR(I12/I2,"") -> 0.75 | J15: =IFERROR(J12/J2,"") -> 0.65104167 | ... L15: =IFERROR(L12/L2,"") -> 0.75
A16: Provenance, Articles (Scientific) | B16: Local | C16: =COUNTIFS('1. OP'!O2:O10002,"*Local*",'1. OP'!R2:R10002,"TRUE") -> 47 | D16: =COUNTIFS('2. JSEL'!O2:O48,"*Local*",'2. JSEL'!R2:R48,"TRUE") -> 4 | E16: =COUNTIFS('3. PSM'!O2:O206,"*Local*",'3. PSM'!R2:R206,"TRUE") -> 28 | F16: =COUNTIFS('4. SSP'!O2:O495,"*Local*",'4. SSP'!R2:R495,"TRUE") -> 186 | G16: =COUNTIFS('5. JSACI'!O2:O46,"*Local*",'5. JSACI'!R2:R46,"TRUE") -> 15 | H16: =COUNTIFS('6. AIN'!O2:O858,"*Local*",'6. AIN'!R2:R858,"TRUE") -> 169 | I16: =COUNTIFS('7. MS'!O2:O9999,"*Local*",'7. MS'!R2:R9999,"TRUE") -> 1 | J16: =COUNTIFS('8. DS'!O2:O10006,"*Local*",'8. DS'!R2:R10006,"TRUE") -> 130 | K16: =COUNTIFS('9. RMF'!O2:O10124,"*Local*",'9. RMF'!R2:R10124,"TRUE") -> 306 | L16: =COUNTIFS('10. PCU'!O2:O10001,"*Local*",'10. PCU'!R2:R10001,"TRUE") -> 0
B17: Reuse (Translation) | C17: =COUNTIFS('1. OP'!O2:O10002,"*Reuse (Translation)*",'1. OP'!R2:R10002,"TRUE") -> 3 | D17: =COUNTIFS('2. JSEL'!O2:O48,"*Reuse (Translation)*",'2. JSEL'!R2:R48,"TRUE") -> 7 | E17: =COUNTIFS('3. PSM'!O2:O206,"*Reuse (Translation)*",'3. PSM'!R2:R206,"TRUE") -> 128 | F17: =COUNTIFS('4. SSP'!O2:O495,"*Reuse (Translation)*",'4. SSP'!R2:R495,"TRUE") -> 173 | G17: =COUNTIFS('5. JSACI'!O2:O46,"*Reuse (Translation)*",'5. JSACI'!R2:R46,"TRUE") -> 5 | H17: =COUNTIFS('6. AIN'!O2:O858,"*Reuse (Translation)*",'6. AIN'!R2:R858,"TRUE") -> 448 | I17: =COUNTIFS('7. MS'!O2:O9999,"*Reuse (Translation)*",'7. MS'!R2:R9999,"TRUE") -> 10 | J17: =COUNTIFS('8. DS'!O2:O10006,"*Reuse (Translation)*",'8. DS'!R2:R10006,"TRUE") -> 134 | K17: =COUNTIFS('9. RMF'!O2:O10124,"*Reuse (Translation)*",'9. RMF'!R2:R10124,"TRUE") -> 132 | L17: =COUNTIFS('10. PCU'!O2:O10001,"*Reuse (Translation)*",'10. PCU'!R2:R10001,"TRUE") -> 3
B18: Reuse (Reprint) | C18: =COUNTIFS('1. OP'!O2:O10002,"*Reuse (Reprint)*",'1. OP'!R2:R10002,"TRUE") -> 7 | D18: =COUNTIFS('2. JSEL'!O2:O48,"*Reuse (Reprint)*",'2. JSEL'!R2:R48,"TRUE") -> 0 | E18: =COUNTIFS('3. PSM'!O2:O206,"*Reuse (Reprint)*",'3. PSM'!R2:R206,"TRUE") -> 0 | F18: =COUNTIFS('4. SSP'!O2:O495,"*Reuse (Reprint)*",'4. SSP'!R2:R495,"TRUE") -> 1 | G18: =COUNTIFS('5. JSACI'!O2:O46,"*Reuse (Reprint)*",'5. JSACI'!R2:R46,"TRUE") -> 1 | H18: =COUNTIFS('6. AIN'!O2:O858,"*Reuse (Reprint)*",'6. AIN'!R2:R858,"TRUE") -> 50 | I18: =COUNTIFS('7. MS'!O2:O9999,"*Reuse (Reprint)*",'7. MS'!R2:R9999,"TRUE") -> 0 | J18: =COUNTIFS('8. DS'!O2:O10006,"*Reuse (Reprint)*",'8. DS'!R2:R10006,"TRUE") -> 18 | K18: =COUNTIFS('9. RMF'!O2:O10124,"*Reuse (Reprint)*",'9. RMF'!R2:R10124,"TRUE") -> 39 | L18: =COUNTIFS('10. PCU'!O2:O10001,"*Reuse (Reprint)*",'10. PCU'!R2:R10001,"TRUE") -> 0
B19: Adaptation | C19: =COUNTIFS('1. OP'!O2:O10002,"*Adaptation*",'1. OP'!R2:R10002,"TRUE") -> 4 | D19: =COUNTIFS('2. JSEL'!O2:O48,"*Adaptation*",'2. JSEL'!R2:R48,"TRUE") -> 4 | E19: =COUNTIFS('3. PSM'!O2:O206,"*Adaptation*",'3. PSM'!R2:R206,"TRUE") -> 49 | F19: =COUNTIFS('4. SSP'!O2:O495,"*Adaptation*",'4. SSP'!R2:R495,"TRUE") -> 56 | G19: =COUNTIFS('5. JSACI'!O2:O46,"*Adaptation*",'5. JSACI'!R2:R46,"TRUE") -> 6 | H19: =COUNTIFS('6. AIN'!O2:O858,"*Adaptation*",'6. AIN'!R2:R858,"TRUE") -> 53 | I19: =COUNTIFS('7. MS'!O2:O9999,"*Adaptation*",'7. MS'!R2:R9999,"TRUE") -> 2 | J19: =COUNTIFS('8. DS'!O2:O10006,"*Adaptation*",'8. DS'!R2:R10006,"TRUE") -> 98 | K19: =COUNTIFS('9. RMF'!O2:O10124,"*Adaptation*",'9. RMF'!R2:R10124,"TRUE") -> 76 | L19: =COUNTIFS('10. PCU'!O2:O10001,"*Adaptation*",'10. PCU'!R2:R10001,"TRUE") -> 1
B20: ESA (Total) | C20: =SUM(C17:C19) -> 14 | D20: =SUM(D17:D19) -> 11 | E20: =SUM(E17:E19) -> 177 | F20: =SUM(F17:F19) -> 230 | G20: =SUM(G17:G19) -> 12 | H20: =SUM(H17:H19) -> 551 | I20: =SUM(I17:I19) -> 12 | J20: =SUM(J17:J19) -> 250 | ... L20: =SUM(L17:L19) -> 4
B21: Trans.-Ratio | C21: =IFERROR(C17/C4,"") -> 0.044776119 | D21: =IFERROR(D17/D4,"") -> 0.46666667 | E21: =IFERROR(E17/E4,"") -> 0.62439024 | F21: =IFERROR(F17/F4,"") -> 0.4138756 | G21: =IFERROR(G17/G4,"") -> 0.17857143 | H21: =IFERROR(H17/H4,"") -> 0.62049861 | I21: =IFERROR(I17/I4,"") -> 0.76923077 | J21: =IFERROR(J17/J4,"") -> 0.35078534 | ... L21: =IFERROR(L17/L4,"") -> 0.75
B22: Reprint-Ratio | C22: =IFERROR(C18/C4,"") -> 0.10447761 | D22: =IFERROR(D18/D4,"") -> 0 | E22: =IFERROR(E18/E4,"") -> 0 | F22: =IFERROR(F18/F4,"") -> 0.0023923445 | G22: =IFERROR(G18/G4,"") -> 0.035714286 | H22: =IFERROR(H18/H4,"") -> 0.069252078 | I22: =IFERROR(I18/I4,"") -> 0 | J22: =IFERROR(J18/J4,"") -> 0.047120419 | ... L22: =IFERROR(L18/L4,"") -> 0
B23: ESA-Ratio | C23: =IFERROR(C20/C4,"") -> 0.20895522 | D23: =IFERROR(D20/D4,"") -> 0.73333333 | E23: =IFERROR(E20/E4,"") -> 0.86341463 | F23: =IFERROR(F20/F4,"") -> 0.55023923 | G23: =IFERROR(G20/G4,"") -> 0.42857143 | H23: =IFERROR(H20/H4,"") -> 0.76315789 | I23: =IFERROR(I20/I4,"") -> 0.92307692 | J23: =IFERROR(J20/J4,"") -> 0.65445026 | ... L23: =IFERROR(L20/L4,"") -> 1
A24: Provenance, Pages (Scientific) | B24: Local | C24: =SUMIFS('1. OP'!$H:$H,'1. OP'!$R:$R,"TRUE",'1. OP'!$O:$O,"Local") -> 514 | D24: =SUMIFS('2. JSEL'!$H:$H,'2. JSEL'!$R:$R,"TRUE",'2. JSEL'!$O:$O,"Local") -> 39 | E24: =SUMIFS('3. PSM'!$H:$H,'3. PSM'!$R:$R,"TRUE",'3. PSM'!$O:$O,"Local") -> 161.33333 | F24: =SUMIFS('4. SSP'!$H:$H,'4. SSP'!$R:$R,"TRUE",'4. SSP'!$O:$O,"Local") -> 298.98333 | G24: =SUMIFS('5. JSACI'!$H:$H,'5. JSACI'!$R:$R,"TRUE",'5. JSACI'!$O:$O,"Local") -> 105.5 | H24: =SUMIFS('6. AIN'!$H:$H,'6. AIN'!$R:$R,"TRUE",'6. AIN'!$O:$O,"Local") -> 945 | I24: =SUMIFS('7. MS'!$H:$H,'7. MS'!$R:$R,"TRUE",'7. MS'!$O:$O,"Local") -> 0.5 | J24: =SUMIFS('8. DS'!$H:$H,'8. DS'!$R:$R,"TRUE",'8. DS'!$O:$O,"Local") -> 160.0619 | K24: =SUMIFS('9. RMF'!$H:$H,'9. RMF'!$R:$R,"TRUE",'9. RMF'!$O:$O,"Local") -> 1744.4167 | L24: =SUMIFS('10. PCU'!$H:$H,'10. PCU'!$R:$R,"TRUE",'10. PCU'!$O:$O,"Local") -> 0
B25: Reuse (Translation) | C25: =SUMIFS('1. OP'!$H:$H,'1. OP'!$R:$R,"TRUE",'1. OP'!$O:$O,"Reuse (Translation)") -> 24.5 | D25: =SUMIFS('2. JSEL'!$H:$H,'2. JSEL'!$R:$R,"TRUE",'2. JSEL'!$O:$O,"Reuse (Translation)") -> 50 | E25: =SUMIFS('3. PSM'!$H:$H,'3. PSM'!$R:$R,"TRUE",'3. PSM'!$O:$O,"Reuse (Translation)") -> 775.33333 | F25: =SUMIFS('4. SSP'!$H:$H,'4. SSP'!$R:$R,"TRUE",'4. SSP'!$O:$O,"Reuse (Translation)") -> 137.82381 | G25: =SUMIFS('5. JSACI'!$H:$H,'5. JSACI'!$R:$R,"TRUE",'5. JSACI'!$O:$O,"Reuse (Translation)") -> 25.833333 | H25: =SUMIFS('6. AIN'!$H:$H,'6. AIN'!$R:$R,"TRUE",'6. AIN'!$O:$O,"Reuse (Translation)") -> 1714.0833 | I25: =SUMIFS('7. MS'!$H:$H,'7. MS'!$R:$R,"TRUE",'7. MS'!$O:$O,"Reuse (Translation)") -> 9.6666667 | J25: =SUMIFS('8. DS'!$H:$H,'8. DS'!$R:$R,"TRUE",'8. DS'!$O:$O,"Reuse (Translation)") -> 153.16429 | K25: =SUMIFS('9. RMF'!$H:$H,'9. RMF'!$R:$R,"TRUE",'9. RMF'!$O:$O,"Reuse (Translation)") -> 500.03333 | L25: =SUMIFS('10. PCU'!$H:$H,'10. PCU'!$R:$R,"TRUE",'10. PCU'!$O:$O,"Reuse (Translation)") -> 1.25
B26: Reuse (Reprint) | C26: =SUMIFS('1. OP'!$H:$H,'1. OP'!$R:$R,"TRUE",'1. OP'!$O:$O,"Reuse (Reprint)") -> 76 | D26: =SUMIFS('2. JSEL'!$H:$H,'2. JSEL'!$R:$R,"TRUE",'2. JSEL'!$O:$O,"Reuse (Reprint)") -> 0 | E26: =SUMIFS('3. PSM'!$H:$H,'3. PSM'!$R:$R,"TRUE",'3. PSM'!$O:$O,"Reuse (Reprint)") -> 0 | F26: =SUMIFS('4. SSP'!$H:$H,'4. SSP'!$R:$R,"TRUE",'4. SSP'!$O:$O,"Reuse (Reprint)") -> 3.5 | G26: =SUMIFS('5. JSACI'!$H:$H,'5. JSACI'!$R:$R,"TRUE",'5. JSACI'!$O:$O,"Reuse (Reprint)") -> 6 | H26: =SUMIFS('6. AIN'!$H:$H,'6. AIN'!$R:$R,"TRUE",'6. AIN'!$O:$O,"Reuse (Reprint)") -> 216.75 | I26: =SUMIFS('7. MS'!$H:$H,'7. MS'!$R:$R,"TRUE",'7. MS'!$O:$O,"Reuse (Reprint)") -> 0 | J26: =SUMIFS('8. DS'!$H:$H,'8. DS'!$R:$R,"TRUE",'8. DS'!$O:$O,"Reuse (Reprint)") -> 50.166667 | K26: =SUMIFS('9. RMF'!$H:$H,'9. RMF'!$R:$R,"TRUE",'9. RMF'!$O:$O,"Reuse (Reprint)") -> 119.61667 | L26: =SUMIFS('10. PCU'!$H:$H,'10. PCU'!$R:$R,"TRUE",'10. PCU'!$O:$O,"Reuse (Reprint)") -> 0
B27: Adaptation | C27: =SUMIFS('1. OP'!$H:$H,'1. OP'!$R:$R,"TRUE",'1. OP'!$O:$O,"Adaptation") -> 42 | D27: =SUMIFS('2. JSEL'!$H:$H,'2. JSEL'!$R:$R,"TRUE",'2. JSEL'!$O:$O,"Adaptation") -> 43.5 | E27: =SUMIFS('3. PSM'!$H:$H,'3. PSM'!$R:$R,"TRUE",'3. PSM'!$O:$O,"Adaptation") -> 126.33333 | F27: =SUMIFS('4. SSP'!$H:$H,'4. SSP'!$R:$R,"TRUE",'4. SSP'!$O:$O,"Adaptation") -> 36.909524 | G27: =SUMIFS('5. JSACI'!$H:$H,'5. JSACI'!$R:$R,"TRUE",'5. JSACI'!$O:$O,"Adaptation") -> 23.5 | H27: =SUMIFS('6. AIN'!$H:$H,'6. AIN'!$R:$R,"TRUE",'6. AIN'!$O:$O,"Adaptation") -> 121.5 | I27: =SUMIFS('7. MS'!$H:$H,'7. MS'!$R:$R,"TRUE",'7. MS'!$O:$O,"Adaptation") -> 1.8333333 | J27: =SUMIFS('8. DS'!$H:$H,'8. DS'!$R:$R,"TRUE",'8. DS'!$O:$O,"Adaptation") -> 59.907143 | K27: =SUMIFS('9. RMF'!$H:$H,'9. RMF'!$R:$R,"TRUE",'9. RMF'!$O:$O,"Adaptation") -> 96.1 | L27: =SUMIFS('10. PCU'!$H:$H,'10. PCU'!$R:$R,"TRUE",'10. PCU'!$O:$O,"Adaptation") -> 5
B28: ESA (Total) | C28: =SUM(C25:C27) -> 142.5 | D28: =SUM(D25:D27) -> 93.5 | E28: =SUM(E25:E27) -> 901.66667 | F28: =SUM(F25:F27) -> 178.23333 | G28: =SUM(G25:G27) -> 55.333333 | H28: =SUM(H25:H27) -> 2052.3333 | I28: =SUM(I25:I27) -> 11.5 | J28: =SUM(J25:J27) -> 263.2381 | ... L28: =SUM(L25:L27) -> 6.25
B29: Trans.-Ratio | C29: =IFERROR(C25/C5,"") -> 0.033041133 | D29: =IFERROR(D25/D5,"") -> 0.37735849 | E29: =IFERROR(E25/E5,"") -> 0.72938225 | F29: =IFERROR(F25/F5,"") -> 0.28840472 | G29: =IFERROR(G25/G5,"") -> 0.15913758 | H29: =IFERROR(H25/H5,"") -> 0.57025229 | I29: =IFERROR(I25/I5,"") -> 0.80555556 | J29: =IFERROR(J25/J5,"") -> 0.35949838 | ... L29: =IFERROR(L25/L5,"") -> 0.2
B30: Reprint-Ratio | C30: =IFERROR(C26/C5,"") -> 0.10249494 | D30: =IFERROR(D26/D5,"") -> 0 | E30: =IFERROR(E26/E5,"") -> 0 | F30: =IFERROR(F26/F5,"") -> 0.0073239633 | G30: =IFERROR(G26/G5,"") -> 0.036960986 | H30: =IFERROR(H26/H5,"") -> 0.072109787 | I30: =IFERROR(I26/I5,"") -> 0 | J30: =IFERROR(J26/J5,"") -> 0.11774831 | ... L30: =IFERROR(L26/L5,"") -> 0
B31: ESA-Ratio | C31: =IFERROR(C28/C5,"") -> 0.19217802 | D31: =IFERROR(D28/D5,"") -> 0.70566038 | E31: =IFERROR(E28/E5,"") -> 0.84822828 | F31: =IFERROR(F28/F5,"") -> 0.37296411 | G31: =IFERROR(G28/G5,"") -> 0.34086242 | H31: =IFERROR(H28/H5,"") -> 0.68278348 | I31: =IFERROR(I28/I5,"") -> 0.95833333 | J31: =IFERROR(J28/J5,"") -> 0.61785728 | ... L31: =IFERROR(L28/L5,"") -> 1

Sheet 1. OP
A1: File | B1: ID | C1: Date | D1: Vol. | E1: Issue | F1: Start | G1: End | H1: Size | I1: Section | J1: Title | K1: AuthorhipAttribution | L1: SourceAttribution | M1: ProximateSourceIdentification | N1: Reference | O1: TextualProvenanceClassification | P1: ProximateSourceLocation | Q1: Notes | R1: Science
A2: OP1813s1v1 | B2: OP1813.1.1.1-1 | C2: 01/1813 | D2: 1 | E2: 1 | F2: 3 | G2: 8 | H2: {=_xlfn.LET(_xlpm.s,IFERROR(--F2,""),_xlpm.e,IFERROR(--G2,""),IF(OR(_xlpm.s="",_xlpm.e="",_xlpm.e<_xlpm.s),"",_xlfn.LET(_xlpm.p,_xlfn.SEQUENCE(_xlpm.e-_xlpm.s+1,1,_xlpm.s,1),SUM(1/COUNTIFS($D:$D,D2,$E:$E,E2,$F:$F,"<>N/A",$G:$G,"<>N/A",$F:$F,"<="&_xlpm.p,$G:$G,">="&_xlpm.p)))))} -> 6 | I2: N/A | J2: Introducção. | K2: N/A | L2: N/A | M2: N/A | N2: N/A | O2: Local | P2: Brazil | R2: FALSE
A3: OP1813s1v1 | B3: OP1813.1.1.1-2 | C3: 01/1813 | D3: 1 | E3: 1 | F3: 9 | G3: 10 | H3: {=_xlfn.LET(_xlpm.s,IFERROR(--F3,""),_xlpm.e,IFERROR(--G3,""),IF(OR(_xlpm.s="",_xlpm.e="",_xlpm.e<_xlpm.s),"",_xlfn.LET(_xlpm.p,_xlfn.SEQUENCE(_xlpm.e-_xlpm.s+1,1,_xlpm.s,1),SUM(1/COUNTIFS($D:$D,D3,$E:$E,E3,$F:$F,"<>N/A",$G:$G,"<>N/A",$F:$F,"<="&_xlpm.p,$G:$G,">="&_xlpm.p)))))} -> 1.5 | I3: Artes | J3: Memoria sobre o emprego do assucar combinado com a polvora, extrahida do Repertoio das Artes, Manufacturas, e Agricultura | K3: N/A | L3: Repertory of Arts, &cc. n.º 125 | M3: RAMA1812s2v21 | N3: “Specification of the Patent granted to Frederick Albert Winsor...” The Repertory of Arts, Manufactures, and Agriculture (London) 2nd ser., 21, no. 125 (1812): 261–262. | O3: Adaptation | P3: United Kingdom | R3: TRUE
A4: OP1813s1v1 | B4: OP1813.1.1.1-3 | C4: 01/1813 | D4: 1 | E4: 1 | F4: 10 | G4: 21 | H4: {=_xlfn.LET(_xlpm.s,IFERROR(--F4,""),_xlpm.e,IFERROR(--G4,""),IF(OR(_xlpm.s="",_xlpm.e="",_xlpm.e<_xlpm.s),"",_xlfn.LET(_xlpm.p,_xlfn.SEQUENCE(_xlpm.e-_xlpm.s+1,1,_xlpm.s,1),SUM(1/COUNTIFS($D:$D,D4,$E:$E,E4,$F:$F,"<>N/A",$G:$G,"<>N/A",$F:$F,"<="&_xlpm.p,$G:$G,">="&_xlpm.p)))))} -> 11.5 | I4: Artes | J4: Novo methodo para refinar assucar por Luiz Honoré Henry German Constant, premiado a 27 de fevereiro de 1812 | K4: N/A | L4: N/A | M4: RAMA1812s2v21 | N4: "Specification of the Patent granted to Louis Honoré Henry Germain Constant, of Blandford-street, Portman-square, in the Parish of Saint Mary-le-bone, and County of Middlesex; for a Method of refining Sugars. Dated February 27, 1812." The Repertory of Arts, Manufactures, and Agriculture (London) 2nd ser., 21, no. 124 (1812): 207–216. | O4: Reuse (Translation) | P4: United Kingdom | R4: TRUE
A5: OP1813s1v1 | B5: OP1813.1.1.1-4 | C5: 01/1813 | D5: 1 | E5: 1 | F5: 22 | G5: 34 | H5: {=_xlfn.LET(_xlpm.s,IFERROR(--F5,""),_xlpm.e,IFERROR(--G5,""),IF(OR(_xlpm.s="",_xlpm.e="",_xlpm.e<_xlpm.s),"",_xlfn.LET(_xlpm.p,_xlfn.SEQUENCE(_xlpm.e-_xlpm.s+1,1,_xlpm.s,1),SUM(1/COUNTIFS($D:$D,D5,$E:$E,E5,$F:$F,"<>N/A",$G:$G,"<>N/A",$F:$F,"<="&_xlpm.p,$G:$G,">="&_xlpm.p)))))} -> 12.5 | I5: Agricultura | J5: Memoria sobre a cultura dos algodoeiros, por Manoel Arruda da Câmara, Doutor em Medicina pela Universidade de Montpellier, da Academia das Sciencias da mesma Cidade, Correspondente da Sociedade de Agricultura de Pariz, e da Academia Real das Sciencias de Lisboa, e Naturalista empregado no Serviço de S. M. Fidelissima na Capitania de Pernambuco. Anno de 1797. Capítulo I. Da antiguidade do uso do algodão, e da vantagem, que tem resultado a Portugal, e a Pernambuco, da sua cultura. | K5: Manuel Arruda da Câmara | L5: Memoria sobre a cultura dos algodoeiros | M5: N/A | N5: Câmara, Manuel Arruda da. Memoria sobre a cultura dos algodoeiros, e sobre o methodo de o escolher, e ensacar, etc.: em que se propoem alguns planos novos, para o seu melhoramento. Lisbon: Na Officina da Casa Litteraria do Arco do Cego, 1799. [4], 80, [3] p., [6] fold. plates. | O5: Reuse (Reprint) | P5: Portugal | R5: TRUE
A6: OP1813s1v1 | B6: OP1813.1.1.1-5 | C6: 01/1813 | D6: 1 | E6: 1 | F6: 34 | G6: 49 | H6: {=_xlfn.LET(_xlpm.s,IFERROR(--F6,""),_xlpm.e,IFERROR(--G6,""),IF(OR(_xlpm.s="",_xlpm.e="",_xlpm.e<_xlpm.s),"",_xlfn.LET(_xlpm.p,_xlfn.SEQUENCE(_xlpm.e-_xlpm.s+1,1,_xlpm.s,1),SUM(1/COUNTIFS($D:$D,D6,$E:$E,E6,$F:$F,"<>N/A",$G:$G,"<>N/A",$F:$F,"<="&_xlpm.p,$G:$G,">="&_xlpm.p)))))} -> 15 | I6: Agricultura | J6: Memoria sobre a plantação e fabrico do Urucú, por B* | K6: Domingos Borges de Barros | L6: N/A | M6: N/A | N6: Leblond, Jean-Baptiste. “Mémoire sur la préparation du rocou et sur la culture du rocouyer.” In Mémoires de la Société d’agriculture de Paris, tome 6, 65–133. Paris, 1804. | O6: Adaptation | P6: France | Q6: The article is a adaption of Jean-Baptiste Leblond’s Mémoire sur la culture du roucouyer à la Guyane française (Mémoires de la Société d’agriculture du département de la Seine, 1804) with additional material from contemporary French chemical literature (particularly Vauquelin and Chaptal). | R6: TRUE
A7: OP1813s1v1 | B7: OP1813.1.1.1-6 | C7: 01/1813 | D7: 1 | E7: 1 | F7: 49 | G7: 57 | H7: {=_xlfn.LET(_xlpm.s,IFERROR(--F7,""),_xlpm.e,IFERROR(--G7,""),IF(OR(_xlpm.s="",_xlpm.e="",_xlpm.e<_xlpm.s),"",_xlfn.LET(_xlpm.p,_xlfn.SEQUENCE(_xlpm.e-_xlpm.s+1,1,_xlpm.s,1),SUM(1/COUNTIFS($D:$D,D7,$E:$E,E7,$F:$F,"<>N/A",$G:$G,"<>N/A",$F:$F,"<="&_xlpm.p,$G:$G,">="&_xlpm.p)))))} -> 8.5 | I7: Hidrografia | J7: Methodo, que se seguiu no trabalho Hydrographico da Planta do Porto do Rio de Janeiro, levantada por Ordem do Serenissimo Senhor Infante Almirante General, em o anno de 1810. | K7: D.J.B. | L7: N/A | M7: N/A | N7: N/A | O7: Local | P7: Brazil | R7: TRUE
A8: OP1813s1v1 | B8: OP1813.1.1.1-7 | C8: 01/1813 | D8: 1 | E8: 1 | F8: 58 | G8: 59 | H8: {=_xlfn.LET(_xlpm.s,IFERROR(--F8,""),_xlpm.e,IFERROR(--G8,""),IF(OR(_xlpm.s="",_xlpm.e="",_xlpm.e<_xlpm.s),"",_xlfn.LET(_xlpm.p,_xlfn.SEQUENCE(_xlpm.e-_xlpm.s+1,1,_xlpm.s,1),SUM(1/COUNTIFS($D:$D,D8,$E:$E,E8,$F:$F,"<>N/A",$G:$G,"<>N/A",$F:$F,"<="&_xlpm.p,$G:$G,">="&_xlpm.p)))))} -> 2 | I8: Medicina | J8: No anno de 1798 se propoz por Acordo da Camara desta Cidade a varios Medicos, hum Programma que tinha por objecto os quesitos seguintes. | K8: N/A | L8: N/A | M8: N/A | N8: N/A | O8: Local | P8: Brazil | R8: TRUE
A9: OP1813s1v1 | B9: OP1813.1.1.1-8 | C9: 01/1813 | D9: 1 | E9: 1 | F9: 60 | G9: 67 | H9: {=_xlfn.LET(_xlpm.s,IFERROR(--F9,""),_xlpm.e,IFERROR(--G9,""),IF(OR(_xlpm.s="",_xlpm.e="",_xlpm.e<_xlpm.s),"",_xlfn.LET(_xlpm.p,_xlfn.SEQUENCE(_xlpm.e-_xlpm.s+1,1,_xlpm.s,1),SUM(1/COUNTIFS($D:$D,D9,$E:$E,E9,$F:$F,"<>N/A",$G:$G,"<>N/A",$F:$F,"<="&_xlpm.p,$G:$G,">="&_xlpm.p)))))} -> 8 | I9: Medicina | J9: Resposta, que deu o Doutor Manoel Joaquim Marreiros, aos quesitos precedentes. | K9: Manoel Joaquim Marreiros | L9: N/A | M9: N/A | N9: N/A | O9: Local | P9: Brazil | R9: TRUE
A10: OP1813s1v1 | B10: OP1813.1.1.1-9 | C10: 01/1813 | D10: 1 | E10: 1 | F10: 68 | G10: 73 | H10: {=_xlfn.LET(_xlpm.s,IFERROR(--F10,""),_xlpm.e,IFERROR(--G10,""),IF(OR(_xlpm.s="",_xlpm.e="",_xlpm.e<_xlpm.s),"",_xlfn.LET(_xlpm.p,_xlfn.SEQUENCE(_xlpm.e-_xlpm.s+1,1,_xlpm.s,1),SUM(1/COUNTIFS($D:$D,D10,$E:$E,E10,$F:$F,"<>N/A",$G:$G,"<>N/A",$F:$F,"<="&_xlpm.p,$G:$G,">="&_xlpm.p)))))} -> 6 | I10: Litteratura | J10: Ode. A’ partida de S. A. R. o Principe Regente Nosso Senhor, de Portugal para o Brazil, feita em Paris aos 5 (a) de Janeiro de 1808 ; e recitada em prezença dos Bons Portuguezes alli existentes. | K10: Domingos Borges de Barros | L10: N/A | M10: N/A | N10: N/A | O10: Local | P10: Brazil | R10: FALSE
A11: OP1813s1v1 | B11: OP1813.1.1.1-10 | C11: 01/1813 | D11: 1 | E11: 1 | F11: 74 | G11: 75 | H11: {=_xlfn.LET(_xlpm.s,IFERROR(--F11,""),_xlpm.e,IFERROR(--G11,""),IF(OR(_xlpm.s="",_xlpm.e="",_xlpm.e<_xlpm.s),"",_xlfn.LET(_xlpm.p,_xlfn.SEQUENCE(_xlpm.e-_xlpm.s+1,1,_xlpm.s,1),SUM(1/COUNTIFS($D:$D,D11,$E:$E,E11,$F:$F,"<>N/A",$G:$G,"<>N/A",$F:$F,"<="&_xlpm.p,$G:$G,">="&_xlpm.p)))))} -> 2 | I11: Litteratura | J11: Do Dezembargador Antonio Ribeiro dos Santos a Francisco de Borja Garção Stockler. Ode. | K11: Antonio Ribeiro dos Santos | L11: N/A | M11: N/A | N11: N/A | O11: Local | P11: Brazil | R11: FALSE
A12: OP1813s1v1 | B12: OP1813.1.1.1-11 | C12: 01/1813 | D12: 1 | E12: 1 | F12: 76 | G12: 78 | H12: {=_xlfn.LET(_xlpm.s,IFERROR(--F12,""),_xlpm.e,IFERROR(--G12,""),IF(OR(_xlpm.s="",_xlpm.e="",_xlpm.e<_xlpm.s),"",_xlfn.LET(_xlpm.p,_xlfn.SEQUENCE(_xlpm.e-_xlpm.s+1,1,_xlpm.s,1),SUM(1/COUNTIFS($D:$D,D12,$E:$E,E12,$F:$F,"<>N/A",$G:$G,"<>N/A",$F:$F,"<="&_xlpm.p,$G:$G,">="&_xlpm.p)))))} -> 3 | I12: Litteratura | J12: Ode. Ao Illustrissimo Antonio Ribeiro dos Santos, em resposta á antecêdente, por Francisco de Borja Garção Stockler. | K12: Francisco de Borja Garção Stockler | L12: N/A | M12: N/A | N12: N/A | O12: Local | P12: Brazil | R12: FALSE
A13: OP1813s1v1 | B13: OP1813.1.1.1-12 | C13: 01/1813 | D13: 1 | E13: 1 | F13: 79 | G13: 87 | H13: {=_xlfn.LET(_xlpm.s,IFERROR(--F13,""),_xlpm.e,IFERROR(--G13,""),IF(OR(_xlpm.s="",_xlpm.e="",_xlpm.e<_xlpm.s),"",_xlfn.LET(_xlpm.p,_xlfn.SEQUENCE(_xlpm.e-_xlpm.s+1,1,_xlpm.s,1),SUM(1/COUNTIFS($D:$D,D13,$E:$E,E13,$F:$F,"<>N/A",$G:$G,"<>N/A",$F:$F,"<="&_xlpm.p,$G:$G,">="&_xlpm.p)))))} -> 9 | I13: Litteratura | J13: Ode Pindarica. Ao grande Affonso de Albuquerque, Governador da India. Por Antonio Diniz da Cruz. | K13: Antonio Diniz da Cruz | L13: N/A | M13: N/A | N13: Cruz e Silva, António Diniz da. Poesias de Antonio Diniz da Cruz e Silva na Arcadia de Lisboa Elpino Nonacriense. Tom. III: Que contém as Poesias Líricas. Lisbon: Typografia Lacerdina, 1812. | O13: Reuse (Reprint) | P13: Portugal | R13: FALSE
A14: OP1813s1v1 | B14: OP1813.1.1.1-13 | C14: 01/1813 | D14: 1 | E14: 1 | F14: 88 | G14: 90 | H14: {=_xlfn.LET(_xlpm.s,IFERROR(--F14,""),_xlpm.e,IFERROR(--G14,""),IF(OR(_xlpm.s="",_xlpm.e="",_xlpm.e<_xlpm.s),"",_xlfn.LET(_xlpm.p,_xlfn.SEQUENCE(_xlpm.e-_xlpm.s+1,1,_xlpm.s,1),SUM(1/COUNTIFS($D:$D,D14,$E:$E,E14,$F:$F,"<>N/A",$G:$G,"<>N/A",$F:$F,"<="&_xlpm.p,$G:$G,">="&_xlpm.p)))))} -> 3 | I14: Litteratura | J14: Lira Inedita de T. A. Gonzaga, Author da celebre Marilia de Dirceo. | K14: T. A. Gonzaga | L14: N/A | M14: N/A | N14: N/A | O14: Local | P14: Brazil | R14: FALSE
A15: OP1813s1v1 | B15: OP1813.1.1.1-14 | C15: 01/1813 | D15: 1 | E15: 1 | F15: 91 | G15: 93 | H15: {=_xlfn.LET(_xlpm.s,IFERROR(--F15,""),_xlpm.e,IFERROR(--G15,""),IF(OR(_xlpm.s="",_xlpm.e="",_xlpm.e<_xlpm.s),"",_xlfn.LET(_xlpm.p,_xlfn.SEQUENCE(_xlpm.e-_xlpm.s+1,1,_xlpm.s,1),SUM(1/COUNTIFS($D:$D,D15,$E:$E,E15,$F:$F,"<>N/A",$G:$G,"<>N/A",$F:$F,"<="&_xlpm.p,$G:$G,">="&_xlpm.p)))))} -> 2.5 | I15: Litteratura | J15: Maximas, Pensamentos, e Reflexoẽs Moraes por hum Brazileiro. | K15: Mariano Pereira da Fonseca | L15: N/A | M15: N/A | N15: N/A | O15: Local | P15: Brazil | R15: FALSE
A16: OP1813s1v1 | B16: OP1813.1.1.1-15 | C16: 01/1813 | D16: 1 | E16: 1 | F16: 93 | G16: 95 | H16: {=_xlfn.LET(_xlpm.s,IFERROR(--F16,""),_xlpm.e,IFERROR(--G16,""),IF(OR(_xlpm.s="",_xlpm.e="",_xlpm.e<_xlpm.s),"",_xlfn.LET(_xlpm.p,_xlfn.SEQUENCE(_xlpm.e-_xlpm.s+1,1,_xlpm.s,1),SUM(1/COUNTIFS($D:$D,D16,$E:$E,E16,$F:$F,"<>N/A",$G:$G,"<>N/A",$F:$F,"<="&_xlpm.p,$G:$G,">="&_xlpm.p)))))} -> 2 | I16: Litteratura | J16: ["Em huma questão..."] Questão grammatical sobre as Syllabas por S.P.F. | K16: S.P.F. | L16: N/A | M16: N/A | N16: N/A | O16: Local | P16: Brazil | R16: FALSE
A17: OP1813s1v1 | B17: OP1813.1.1.1-16 | C17: 01/1813 | D17: 1 | E17: 1 | F17: 95 | G17: 96 | H17: {=_xlfn.LET(_xlpm.s,IFERROR(--F17,""),_xlpm.e,IFERROR(--G17,""),IF(OR(_xlpm.s="",_xlpm.e="",_xlpm.e<_xlpm.s),"",_xlfn.LET(_xlpm.p,_xlfn.SEQUENCE(_xlpm.e-_xlpm.s+1,1,_xlpm.s,1),SUM(1/COUNTIFS($D:$D,D17,$E:$E,E17,$F:$F,"<>N/A",$G:$G,"<>N/A",$F:$F,"<="&_xlpm.p,$G:$G,">="&_xlpm.p)))))} -> 1.5 | I17: Litteratura | J17: Correspondencia. | K17: S.r…; D.B.B. | L17: N/A | M17: N/A | N17: N/A | O17: Local | P17: Brazil | R17: FALSE
A18: OP1813s1v1 | B18: OP1813.1.1.1-17 | C18: 01/1813 | D18: 1 | E18: 1 | F18: 97 | G18: 100 | H18: {=_xlfn.LET(_xlpm.s,IFERROR(--F18,""),_xlpm.e,IFERROR(--G18,""),IF(OR(_xlpm.s="",_xlpm.e="",_xlpm.e<_xlpm.s),"",_xlfn.LET(_xlpm.p,_xlfn.SEQUENCE(_xlpm.e-_xlpm.s+1,1,_xlpm.s,1),SUM(1/COUNTIFS($D:$D,D18,$E:$E,E18,$F:$F,"<>N/A",$G:$G,"<>N/A",$F:$F,"<="&_xlpm.p,$G:$G,">="&_xlpm.p)))))} -> 4 | I18: História | J18: Extracto da viagem, que fez ao sertão de Benguella no anno de 1785 por ordem do Governador e Capitão General do Reino de Angola, o Bacharel Joaquim José da Silva, enviado à aquelle Reino como Naturalista, e depois Secretario do Governo de Loanda para Benguella. | K18: Joaquim José da Silva | L18: N/A | M18: N/A | N18: Silva, Joaquim José da. Letter to Júlio Mattiazzi. Benguela, 24 May 1787. Manuscript, CN/S-22. Arquivo Histórico do Museu Bocage, Museu Nacional de História Natural e da Ciência (MUHNAC/ULisboa), Lisbon; Silva, Joaquim José da. Letter to Júlio Mattiazzi. Luanda, 9 July 1787. Manuscript, CN/S-23. Arquivo Histórico do Museu Bocage, Museu Nacional de História Natural e da Ciência (MUHNAC/ULisboa), Lisbon. | O18: N/A | P18: Portugal | R18: FALSE
A19: OP1813s1v1 | B19: OP1813.1.1.1-18 | C19: 01/1813 | D19: 1 | E19: 1 | F19: 101 | G19: 107 | H19: {=_xlfn.LET(_xlpm.s,IFERROR(--F19,""),_xlpm.e,IFERROR(--G19,""),IF(OR(_xlpm.s="",_xlpm.e="",_xlpm.e<_xlpm.s),"",_xlfn.LET(_xlpm.p,_xlfn.SEQUENCE(_xlpm.e-_xlpm.s+1,1,_xlpm.s,1),SUM(1/COUNTIFS($D:$D,D19,$E:$E,E19,$F:$F,"<>N/A",$G:$G,"<>N/A",$F:$F,"<="&_xlpm.p,$G:$G,">="&_xlpm.p)))))} -> 7 | I19: Política | J19: Calculo sobre a perda de dinheiro do Reino, offerecido ao Senhor Rei D. JOAM QUINTO, de eterna gloria, por Alexandre de Gusmão, Seu Secretario do Estado, Fielmente copiado do seu original authographo. | K19: Alexandre de Gusmão | L19: N/A | M19: N/A | N19: N/A | O19: Reuse (Reprint) | P19: Portugal | Q19: Seventeenth-century Portuguese state paper reproduced for Rio readers. | R19: FALSE
A20: OP1813s1v1 | B20: OP1813.1.1.1-19 | C20: 01/1813 | D20: 1 | E20: 1 | F20: 108 | G20: 109 | H20: {=_xlfn.LET(_xlpm.s,IFERROR(--F20,""),_xlpm.e,IFERROR(--G20,""),IF(OR(_xlpm.s="",_xlpm.e="",_xlpm.e<_xlpm.s),"",_xlfn.LET(_xlpm.p,_xlfn.SEQUENCE(_xlpm.e-_xlpm.s+1,1,_xlpm.s,1),SUM(1/COUNTIFS($D:$D,D20,$E:$E,E20,$F:$F,"<>N/A",$G:$G,"<>N/A",$F:$F,"<="&_xlpm.p,$G:$G,">="&_xlpm.p)))))} -> 2 | I20: Política | J20: Tratado de paz entre S. M. o Rei da Suecia, e S. M. o Rei do Reino Unido da Gran Bretanha e Irlãnda. | K20: Barão de Engerstrom, Barão de Wotlersdet, Edward Thornton | L20: N/A | M20: N/A | N20: N/A | O20: Reuse (Translation) | P20: Portugal | Q20: Diplomatic text carried via Portuguese official prints. | R20: FALSE
A21: OP1813s1v1 | B21: OP1813.1.1.1-20 | C21: 01/1813 | D21: 1 | E21: 1 | F21: 110 | G21: 111 | H21: {=_xlfn.LET(_xlpm.s,IFERROR(--F21,""),_xlpm.e,IFERROR(--G21,""),IF(OR(_xlpm.s="",_xlpm.e="",_xlpm.e<_xlpm.s),"",_xlfn.LET(_xlpm.p,_xlfn.SEQUENCE(_xlpm.e-_xlpm.s+1,1,_xlpm.s,1),SUM(1/COUNTIFS($D:$D,D21,$E:$E,E21,$F:$F,"<>N/A",$G:$G,"<>N/A",$F:$F,"<="&_xlpm.p,$G:$G,">="&_xlpm.p)))))} -> 2 | I21: Política | J21: Tratado de Amizade, União e Alliança entre a Hespanha e a Russia. | K21: Francisco de Zea Bermudes, Conde Nicolao de Romanzoff | L21: N/A | M21: N/A | N21: N/A | O21: Reuse (Translation) | P21: Russia | Q21: Same treaty-reprint pattern as above. | R21: FALSE
A22: OP1813s1v1 | B22: OP1813.1.1.1-21 | C22: 01/1813 | D22: 1 | E22: 1 | F22: 112 | G22: 121 | H22: {=_xlfn.LET(_xlpm.s,IFERROR(--F22,""),_xlpm.e,IFERROR(--G22,""),IF(OR(_xlpm.s="",_xlpm.e="",_xlpm.e<_xlpm.s),"",_xlfn.LET(_xlpm.p,_xlfn.SEQUENCE(_xlpm.e-_xlpm.s+1,1,_xlpm.s,1),SUM(1/COUNTIFS($D:$D,D22,$E:$E,E22,$F:$F,"<>N/A",$G:$G,"<>N/A",$F:$F,"<="&_xlpm.p,$G:$G,">="&_xlpm.p)))))} -> 9.5 | I22: Política | J22: Estado politico da Europa. | K22: N/A | L22: N/A | M22: N/A | N22: N/A | O22: Local | P22: Brazil | R22: FALSE
A23: OP1813s1v1 | B23: OP1813.1.1.1-22 | C23: 01/1813 | D23: 1 | E23: 1 | F23: 121 | G23: 122 | H23: {=_xlfn.LET(_xlpm.s,IFERROR(--F23,""),_xlpm.e,IFERROR(--G23,""),IF(OR(_xlpm.s="",_xlpm.e="",_xlpm.e<_xlpm.s),"",_xlfn.LET(_xlpm.p,_xlfn.SEQUENCE(_xlpm.e-_xlpm.s+1,1,_xlpm.s,1),SUM(1/COUNTIFS($D:$D,D23,$E:$E,E23,$F:$F,"<>N/A",$G:$G,"<>N/A",$F:$F,"<="&_xlpm.p,$G:$G,">="&_xlpm.p)))))} -> 1 | I23: Política | J23: Obras publicadas no Rio de Janeiro no presente mez de Janeiro. | K23: N/A | L23: N/A | M23: N/A | N23: N/A | O23: Local | P23: Brazil | R23: FALSE
A24: OP1813s1v1 | B24: OP1813.1.1.1-23 | C24: 01/1813 | D24: 1 | E24: 1 | F24: 122 | G24: 125 | H24: {=_xlfn.LET(_xlpm.s,IFERROR(--F24,""),_xlpm.e,IFERROR(--G24,""),IF(OR(_xlpm.s="",_xlpm.e="",_xlpm.e<_xlpm.s),"",_xlfn.LET(_xlpm.p,_xlfn.SEQUENCE(_xlpm.e-_xlpm.s+1,1,_xlpm.s,1),SUM(1/COUNTIFS($D:$D,D24,$E:$E,E24,$F:$F,"<>N/A",$G:$G,"<>N/A",$F:$F,"<="&_xlpm.p,$G:$G,">="&_xlpm.p)))))} -> 3.5 | I24: Comércio | J24: Mappa das Embarcações Portuguezas que entrarão em Gibraltar no anno de 1811, e suas importações, e exportações, extrahido de Documentos Officiaes. | K24: N/A | L24: N/A | M24: N/A | N24: N/A | O24: Reuse (Reprint) | P24: Portugal | Q24: Consular/official Portuguese data reproduced for the journal. | R24: FALSE
A25: OP1813s1v1 | B25: OP1813.1.1.2-24 | C25: 02/1813 | D25: 1 | E25: 2 | F25: 3 | G25: 7 | H25: {=_xlfn.LET(_xlpm.s,IFERROR(--F25,""),_xlpm.e,IFERROR(--G25,""),IF(OR(_xlpm.s="",_xlpm.e="",_xlpm.e<_xlpm.s),"",_xlfn.LET(_xlpm.p,_xlfn.SEQUENCE(_xlpm.e-_xlpm.s+1,1,_xlpm.s,1),SUM(1/COUNTIFS($D:$D,D25,$E:$E,E25,$F:$F,"<>N/A",$G:$G,"<>N/A",$F:$F,"<="&_xlpm.p,$G:$G,">="&_xlpm.p)))))} -> 5 | I25: Mathematica | J25: Problema. Entre todos os Solidos de igual superficie, achar o que tem o maximo volume. | K25: José Saturnino da Costa Pereira | L25: N/A | M25: N/A | N25: N/A | O25: Local | P25: Brazil | R25: TRUE
A26: OP1813s1v1 | B26: OP1813.1.1.2-25 | C26: 02/1813 | D26: 1 | E26: 2 | F26: 8 | G26: 12 | H26: {=_xlfn.LET(_xlpm.s,IFERROR(--F26,""),_xlpm.e,IFERROR(--G26,""),IF(OR(_xlpm.s="",_xlpm.e="",_xlpm.e<_xlpm.s),"",_xlfn.LET(_xlpm.p,_xlfn.SEQUENCE(_xlpm.e-_xlpm.s+1,1,_xlpm.s,1),SUM(1/COUNTIFS($D:$D,D26,$E:$E,E26,$F:$F,"<>N/A",$G:$G,"<>N/A",$F:$F,"<="&_xlpm.p,$G:$G,">="&_xlpm.p)))))} -> 4.5 | I26: Química | J26: Extracto de duas Cartas de M. Scheweiger a F.C. Delamethrie, sobre o Galvanismo. | K26: Johann Salomo Christoph Schweigger; Jean-Claude Delamétherie | L26: Jornal de Physica | M26: JPCHNA1811s1v72 | N26: Schweigger, Johann Salomo Christoph, “Extrait d’une lettre de M. Schweigger à J.-C. Delamétherie, sur un procédé pour produire le galvanisme par la chaleur,” Journal de physique, de chimie, d’histoire naturelle et des arts 73 (November 1811): 405–6; Johann Salomo Christoph Schweigger, “Seconde lettre de M. Schweigger à J.-C. Delamétherie, sur son procédé pour produire le galvanisme par le moyen du feu,” Journal de physique, de chimie, d’histoire naturelle et des arts (Paris) 73 (December 1811): 462–63. | O26: Reuse (Translation) | P26: France | R26: TRUE
A27: OP1813s1v1 | B27: OP1813.1.1.2-26 | C27: 02/1813 | D27: 1 | E27: 2 | F27: 12 | G27: 14 | H27: {=_xlfn.LET(_xlpm.s,IFERROR(--F27,""),_xlpm.e,IFERROR(--G27,""),IF(OR(_xlpm.s="",_xlpm.e="",_xlpm.e<_xlpm.s),"",_xlfn.LET(_xlpm.p,_xlfn.SEQUENCE(_xlpm.e-_xlpm.s+1,1,_xlpm.s,1),SUM(1/COUNTIFS($D:$D,D27,$E:$E,E27,$F:$F,"<>N/A",$G:$G,"<>N/A",$F:$F,"<="&_xlpm.p,$G:$G,">="&_xlpm.p)))))} -> 2.5 | I27: Química | J27: Methodo imaginado, e praticado no Laboratorio Chimico do Excellentissimo Antonio de Araujo de Azevedo, nesta Cidade do Rio de Janeiro, para extracção do Oleo de Mamona. (Ricinus communis, Lin.) | K27: N/A | L27: N/A | M27: N/A | N27: N/A | O27: Local | P27: Brazil | R27: TRUE
A28: OP1813s1v1 | B28: OP1813.1.1.2-27 | C28: 02/1813 | D28: 1 | E28: 2 | F28: 15 | G28: 43 | H28: {=_xlfn.LET(_xlpm.s,IFERROR(--F28,""),_xlpm.e,IFERROR(--G28,""),IF(OR(_xlpm.s="",_xlpm.e="",_xlpm.e<_xlpm.s),"",_xlfn.LET(_xlpm.p,_xlfn.SEQUENCE(_xlpm.e-_xlpm.s+1,1,_xlpm.s,1),SUM(1/COUNTIFS($D:$D,D28,$E:$E,E28,$F:$F,"<>N/A",$G:$G,"<>N/A",$F:$F,"<="&_xlpm.p,$G:$G,">="&_xlpm.p)))))} -> 28.5 | I28: Agricultura | J28: Noções sobre a cultura, e fabrico do Anil, e Analize desta materia colorante, e do Pastel, publicadas por B.*** | K28: Domingos Borges de Barros et al. | L28: N/A | M28: N/A | N28: N/A | O28: Local | P28: Brazil | R28: TRUE
A29: OP1813s1v1 | B29: OP1813.1.1.2-28 | C29: 02/1813 | D29: 1 | E29: 2 | F29: 43 | G29: 56 | H29: {=_xlfn.LET(_xlpm.s,IFERROR(--F29,""),_xlpm.e,IFERROR(--G29,""),IF(OR(_xlpm.s="",_xlpm.e="",_xlpm.e<_xlpm.s),"",_xlfn.LET(_xlpm.p,_xlfn.SEQUENCE(_xlpm.e-_xlpm.s+1,1,_xlpm.s,1),SUM(1/COUNTIFS($D:$D,D29,$E:$E,E29,$F:$F,"<>N/A",$G:$G,"<>N/A",$F:$F,"<="&_xlpm.p,$G:$G,">="&_xlpm.p)))))} -> 13 | I29: Agricultura | J29: Memoria sobre o Algodoeiro continuado do N.º 1.º pag. 34. Capítulo II. Da descripção do Algodoeiro. | K29: Manuel Arruda da Câmara | L29: Memoria sobre a cultura dos algodoeiros | M29: N/A | N29: Câmara, Manuel Arruda da. Memoria sobre a cultura dos algodoeiros, e sobre o methodo de o escolher, e ensacar, etc.: em que se propoem alguns planos novos, para o seu melhoramento. Lisbon: Na Officina da Casa Litteraria do Arco do Cego, 1799. [4], 80, [3] p., [6] fold. plates. | O29: Reuse (Reprint) | P29: Portugal | R29: TRUE
A30: OP1813s1v1 | B30: OP1813.1.1.2-29 | C30: 02/1813 | D30: 1 | E30: 2 | F30: 56 | G30: 63 | H30: {=_xlfn.LET(_xlpm.s,IFERROR(--F30,""),_xlpm.e,IFERROR(--G30,""),IF(OR(_xlpm.s="",_xlpm.e="",_xlpm.e<_xlpm.s),"",_xlfn.LET(_xlpm.p,_xlfn.SEQUENCE(_xlpm.e-_xlpm.s+1,1,_xlpm.s,1),SUM(1/COUNTIFS($D:$D,D30,$E:$E,E30,$F:$F,"<>N/A",$G:$G,"<>N/A",$F:$F,"<="&_xlpm.p,$G:$G,">="&_xlpm.p)))))} -> 7.5 | I30: Medicina | J30: Resposta que deu o Doutor Bernardino Antonio Gomes no Programma da Camara desta Cidade, que vem no N.º 1 pag. 58. | K30: Bernardino Antonio Gomes | L30: N/A | M30: N/A | N30: N/A | O30: Local | P30: Brazil | R30: TRUE
A31: OP1813s1v1 | B31: OP1813.1.1.2-30 | C31: 02/1813 | D31: 1 | E31: 2 | F31: 64 | G31: 73 | H31: {=_xlfn.LET(_xlpm.s,IFERROR(--F31,""),_xlpm.e,IFERROR(--G31,""),IF(OR(_xlpm.s="",_xlpm.e="",_xlpm.e<_xlpm.s),"",_xlfn.LET(_xlpm.p,_xlfn.SEQUENCE(_xlpm.e-_xlpm.s+1,1,_xlpm.s,1),SUM(1/COUNTIFS($D:$D,D31,$E:$E,E31,$F:$F,"<>N/A",$G:$G,"<>N/A",$F:$F,"<="&_xlpm.p,$G:$G,">="&_xlpm.p)))))} -> 10 | I31: Literatura | J31: Epidecio à morte da Illustrissima e Excellentissima Duqueza de Alafoens, por B* | K31: Domingos Borges de Barros | L31: N/A | M31: N/A | N31: N/A | O31: Local | P31: Brazil | R31: FALSE
A32: OP1813s1v1 | B32: OP1813.1.1.2-31 | C32: 02/1813 | D32: 1 | E32: 2 | F32: 74 | G32: 74 | H32: {=_xlfn.LET(_xlpm.s,IFERROR(--F32,""),_xlpm.e,IFERROR(--G32,""),IF(OR(_xlpm.s="",_xlpm.e="",_xlpm.e<_xlpm.s),"",_xlfn.LET(_xlpm.p,_xlfn.SEQUENCE(_xlpm.e-_xlpm.s+1,1,_xlpm.s,1),SUM(1/COUNTIFS($D:$D,D32,$E:$E,E32,$F:$F,"<>N/A",$G:$G,"<>N/A",$F:$F,"<="&_xlpm.p,$G:$G,">="&_xlpm.p)))))} -> 1 | I32: Literatura | J32: Ode do Desembargador Antonio Ribeiro dos Santos. | K32: Antonio Ribeiro dos Santos | L32: N/A | M32: N/A | N32: N/A | O32: Local | P32: Brazil | R32: FALSE
A33: OP1813s1v1 | B33: OP1813.1.1.2-32 | C33: 02/1813 | D33: 1 | E33: 2 | F33: 75 | G33: 80 | H33: {=_xlfn.LET(_xlpm.s,IFERROR(--F33,""),_xlpm.e,IFERROR(--G33,""),IF(OR(_xlpm.s="",_xlpm.e="",_xlpm.e<_xlpm.s),"",_xlfn.LET(_xlpm.p,_xlfn.SEQUENCE(_xlpm.e-_xlpm.s+1,1,_xlpm.s,1),SUM(1/COUNTIFS($D:$D,D33,$E:$E,E33,$F:$F,"<>N/A",$G:$G,"<>N/A",$F:$F,"<="&_xlpm.p,$G:$G,">="&_xlpm.p)))))} -> 5.5 | I33: Literatura | J33: Dithyrambo de Diniz | K33: António Dinis da Cruz e Silva | L33: N/A | M33: N/A | N33: Cruz e Silva, António Diniz da. Poesias de Antonio Diniz da Cruz e Silva na Arcadia de Lisboa Elpino Nonacriense. Tom. III: Que contém as Poesias Líricas. Lisbon: Typografia Lacerdina, 1812. | O33: Reuse (Reprint) | P33: Portugal | R33: FALSE
A34: OP1813s1v1 | B34: OP1813.1.1.2-33 | C34: 02/1813 | D34: 1 | E34: 2 | F34: 80 | G34: 81 | H34: {=_xlfn.LET(_xlpm.s,IFERROR(--F34,""),_xlpm.e,IFERROR(--G34,""),IF(OR(_xlpm.s="",_xlpm.e="",_xlpm.e<_xlpm.s),"",_xlfn.LET(_xlpm.p,_xlfn.SEQUENCE(_xlpm.e-_xlpm.s+1,1,_xlpm.s,1),SUM(1/COUNTIFS($D:$D,D34,$E:$E,E34,$F:$F,"<>N/A",$G:$G,"<>N/A",$F:$F,"<="&_xlpm.p,$G:$G,">="&_xlpm.p)))))} -> 1.5 | I34: Literatura | J34: Ode Anacreontica do mesmo. | K34: António Dinis da Cruz e Silva | L34: N/A | M34: N/A | N34: Cruz e Silva, António Diniz da. Poesias de Antonio Diniz da Cruz e Silva na Arcadia de Lisboa Elpino Nonacriense. Tom. III: Que contém as Poesias Líricas. Lisbon: Typografia Lacerdina, 1812. | O34: Reuse (Reprint) | P34: Portugal | R34: FALSE
A35: OP1813s1v1 | B35: OP1813.1.1.2-34 | C35: 02/1813 | D35: 1 | E35: 2 | F35: 82 | G35: 82 | H35: {=_xlfn.LET(_xlpm.s,IFERROR(--F35,""),_xlpm.e,IFERROR(--G35,""),IF(OR(_xlpm.s="",_xlpm.e="",_xlpm.e<_xlpm.s),"",_xlfn.LET(_xlpm.p,_xlfn.SEQUENCE(_xlpm.e-_xlpm.s+1,1,_xlpm.s,1),SUM(1/COUNTIFS($D:$D,D35,$E:$E,E35,$F:$F,"<>N/A",$G:$G,"<>N/A",$F:$F,"<="&_xlpm.p,$G:$G,">="&_xlpm.p)))))} -> 1 | I35: Literatura | J35: Soneto de Claudio Manoel da Costa. | K35: Claudio Manoel da Costa | L35: N/A | M35: N/A | N35: Costa, Cláudio Manuel da. “Não vês, Lise, brincar esse menino…” (Soneto XLVI), in Obras (Coimbra: Officina de Luiz Secco Ferreira, 1768), p. 24. | O35: Reuse (Reprint) | P35: Portugal | R35: FALSE
A36: OP1813s1v1 | B36: OP1813.1.1.2-35 | C36: 02/1813 | D36: 1 | E36: 2 | F36: 83 | G36: 85 | H36: {=_xlfn.LET(_xlpm.s,IFERROR(--F36,""),_xlpm.e,IFERROR(--G36,""),IF(OR(_xlpm.s="",_xlpm.e="",_xlpm.e<_xlpm.s),"",_xlfn.LET(_xlpm.p,_xlfn.SEQUENCE(_xlpm.e-_xlpm.s+1,1,_xlpm.s,1),SUM(1/COUNTIFS($D:$D,D36,$E:$E,E36,$F:$F,"<>N/A",$G:$G,"<>N/A",$F:$F,"<="&_xlpm.p,$G:$G,">="&_xlpm.p)))))} -> 3 | I36: Literatura | J36: Maximas, Pensamentos, e Reflexoẽs Moraes por hum Brazileiro. | K36: Mariano Pereira da Fonseca | L36: N/A | M36: N/A | N36: N/A | O36: Local | P36: Brazil | R36: FALSE
... A43: OP1813s1v1 | B43: OP1813.1.1.3-42 | C43: 03/1813 | D43: 1 | E43: 3 | F43: 3 | G43: 15 | H43: {=_xlfn.LET(_xlpm.s,IFERROR(--F43,""),_xlpm.e,IFERROR(--G43,""),IF(OR(_xlpm.s="",_xlpm.e="",_xlpm.e<_xlpm.s),"",_xlfn.LET(_xlpm.p,_xlfn.SEQUENCE(_xlpm.e-_xlpm.s+1,1,_xlpm.s,1),SUM(1/COUNTIFS($D:$D,D43,$E:$E,E43,$F:$F,"<>N/A",$G:$G,"<>N/A",$F:$F,"<="&_xlpm.p,$G:$G,">="&_xlpm.p)))))} -> 13 | I43: Medicina | J43: Resposta, que ao Programma da Camara annunciado no N.º 1.º pag. 58, deu o Doutor Antonio Joaquim Medeiros | K43: Antonio Joaquim Medeiros | L43: N/A | M43: N/A | N43: N/A | O43: Local | P43: Brazil | R43: TRUE
A44: OP1813s1v1 | B44: OP1813.1.1.3-43 | C44: 03/1813 | D44: 1 | E44: 3 | F44: 16 | G44: 23 | H44: {=_xlfn.LET(_xlpm.s,IFERROR(--F44,""),_xlpm.e,IFERROR(--G44,""),IF(OR(_xlpm.s="",_xlpm.e="",_xlpm.e<_xlpm.s),"",_xlfn.LET(_xlpm.p,_xlfn.SEQUENCE(_xlpm.e-_xlpm.s+1,1,_xlpm.s,1),SUM(1/COUNTIFS($D:$D,D44,$E:$E,E44,$F:$F,"<>N/A",$G:$G,"<>N/A",$F:$F,"<="&_xlpm.p,$G:$G,">="&_xlpm.p)))))} -> 7.5 | I44: Botanica | J44: Relação das Plantas exoticas e de especiarias, cultivadas no Real Jardim da Lagua de Freitas, e transportadas da Ilha de França, pelo Chefe de Divisão Luiz d'Abreu. | K44: Luiz de Abreu; João Gomes da Silveira Mendonça | L44: N/A | M44: N/A | N44: N/A | O44: Local | P44: Brazil | Q44: Describes specimens and transfers in the Rio royal garden created after 1808; institutional cue “nesta Corte” context = local reporting. | R44: TRUE
A45: OP1813s1v1 | B45: OP1813.1.1.3-44 | C45: 03/1813 | D45: 1 | E45: 3 | F45: 23 | G45: 31 | H45: {=_xlfn.LET(_xlpm.s,IFERROR(--F45,""),_xlpm.e,IFERROR(--G45,""),IF(OR(_xlpm.s="",_xlpm.e="",_xlpm.e<_xlpm.s),"",_xlfn.LET(_xlpm.p,_xlfn.SEQUENCE(_xlpm.e-_xlpm.s+1,1,_xlpm.s,1),SUM(1/COUNTIFS($D:$D,D45,$E:$E,E45,$F:$F,"<>N/A",$G:$G,"<>N/A",$F:$F,"<="&_xlpm.p,$G:$G,">="&_xlpm.p)))))} -> 8.5 | I45: N/A | J45: Memoria sobre a abertura de huma estrada e communicação, entre a Capitania de Santa Catharina e a Villa de Lagens, e estabelecimento de huma Freguezia no Sertão da terra firme da mesma Capitania. Por Silvestre José dos Passos. | K45: Silvestre José dos Passos | L45: N/A | M45: N/A | N45: N/A | O45: Local | P45: Brazil | Q45: Brazilian internal communications & roadworks; no “extrahida/traduzida” cue; topic is provincial infrastructure. | R45: FALSE
A46: OP1813s1v1 | B46: OP1813.1.1.3-45 | C46: 03/1813 | D46: 1 | E46: 3 | F46: 32 | G46: 38 | H46: {=_xlfn.LET(_xlpm.s,IFERROR(--F46,""),_xlpm.e,IFERROR(--G46,""),IF(OR(_xlpm.s="",_xlpm.e="",_xlpm.e<_xlpm.s),"",_xlfn.LET(_xlpm.p,_xlfn.SEQUENCE(_xlpm.e-_xlpm.s+1,1,_xlpm.s,1),SUM(1/COUNTIFS($D:$D,D46,$E:$E,E46,$F:$F,"<>N/A",$G:$G,"<>N/A",$F:$F,"<="&_xlpm.p,$G:$G,">="&_xlpm.p)))))} -> 7 | I46: N/A | J46: Memoria sobre as novas fornalhas para cozer o assucar com o bagaço, inventadas pelo Doutor Manoel Jacinto de Almeida. Por Fr. Archangelo de Ancona, Missionario Apostolico. | K46: Fr. Archangelo de Ancona | L46: N/A | M46: N/A | N46: N/A | O46: Local | P46: Brazil | Q46: Technical note on engenho practice (bagasse-firing) with a named inventor; subject is a Brazilian manufacturing problem. | R46: TRUE
A47: OP1813s1v1 | B47: OP1813.1.1.3-46 | C47: 03/1813 | D47: 1 | E47: 3 | F47: 39 | G47: 48 | H47: {=_xlfn.LET(_xlpm.s,IFERROR(--F47,""),_xlpm.e,IFERROR(--G47,""),IF(OR(_xlpm.s="",_xlpm.e="",_xlpm.e<_xlpm.s),"",_xlfn.LET(_xlpm.p,_xlfn.SEQUENCE(_xlpm.e-_xlpm.s+1,1,_xlpm.s,1),SUM(1/COUNTIFS($D:$D,D47,$E:$E,E47,$F:$F,"<>N/A",$G:$G,"<>N/A",$F:$F,"<="&_xlpm.p,$G:$G,">="&_xlpm.p)))))} -> 10 | I47: Agricultura | J47: Memoria sobre o Algodoeiro continuada do N.º 2.º pag. 43. Capítulo IV. Do clima, ou temperie do ar mais conveniente á vegetação do Algodoeiro. | K47: Manuel Arruda da Câmara | L47: Memoria sobre a cultura dos algodoeiros | M47: N/A | N47: Câmara, Manuel Arruda da. Memoria sobre a cultura dos algodoeiros, e sobre o methodo de o escolher, e ensacar, etc.: em que se propoem alguns planos novos, para o seu melhoramento. Lisbon: Na Officina da Casa Litteraria do Arco do Cego, 1799. [4], 80, [3] p., [6] fold. plates. | O47: Reuse (Reprint) | P47: Portugal | Q47: Continues the Arruda da Câmara agronomic memória already running as a Lisbon-origin reprint in nº 1–2. | R47: TRUE
A48: OP1813s1v1 | B48: OP1813.1.1.3-47 | C48: 03/1813 | D48: 1 | E48: 3 | F48: 49 | G48: 60 | H48: {=_xlfn.LET(_xlpm.s,IFERROR(--F48,""),_xlpm.e,IFERROR(--G48,""),IF(OR(_xlpm.s="",_xlpm.e="",_xlpm.e<_xlpm.s),"",_xlfn.LET(_xlpm.p,_xlfn.SEQUENCE(_xlpm.e-_xlpm.s+1,1,_xlpm.s,1),SUM(1/COUNTIFS($D:$D,D48,$E:$E,E48,$F:$F,"<>N/A",$G:$G,"<>N/A",$F:$F,"<="&_xlpm.p,$G:$G,">="&_xlpm.p)))))} -> 12 | I48: História | J48: Continuação da Viagem ao Sertão de Benguella, continuada do N.º 2.º pag. 86. Ritos, e costumes. | K48: Joaquim José da Silva | L48: N/A | M48: N/A | N48: Silva, Joaquim José da. Letter to Júlio Mattiazzi. Benguela, 24 May 1787. Manuscript, CN/S-22. Arquivo Histórico do Museu Bocage, Museu Nacional de História Natural e da Ciência (MUHNAC/ULisboa), Lisbon; Silva, Joaquim José da. Letter to Júlio Mattiazzi. Luanda, 9 July 1787. Manuscript, CN/S-23. Arquivo Histórico do Museu Bocage, Museu Nacional de História Natural e da Ciência (MUHNAC/ULisboa), Lisbon. | O48: N/A | P48: Portugal | R48: FALSE
A49: OP1813s1v1 | B49: OP1813.1.1.3-48 | C49: 03/1813 | D49: 1 | E49: 3 | F49: 61 | G49: 64 | H49: {=_xlfn.LET(_xlpm.s,IFERROR(--F49,""),_xlpm.e,IFERROR(--G49,""),IF(OR(_xlpm.s="",_xlpm.e="",_xlpm.e<_xlpm.s),"",_xlfn.LET(_xlpm.p,_xlfn.SEQUENCE(_xlpm.e-_xlpm.s+1,1,_xlpm.s,1),SUM(1/COUNTIFS($D:$D,D49,$E:$E,E49,$F:$F,"<>N/A",$G:$G,"<>N/A",$F:$F,"<="&_xlpm.p,$G:$G,">="&_xlpm.p)))))} -> 3.5 | I49: Literatura | J49: Ode. | K49: António Dinis da Cruz e Silva | L49: N/A | M49: N/A | N49: Cruz e Silva, António Diniz da. Poesias de Antonio Diniz da Cruz e Silva na Arcadia de Lisboa Elpino Nonacriense. Tom. III: Que contém as Poesias Líricas. Lisbon: Typografia Lacerdina, 1812. | O49: Reuse (Reprint) | P49: Portugal | R49: FALSE
A50: OP1813s1v1 | B50: OP1813.1.1.3-49 | C50: 03/1813 | D50: 1 | E50: 3 | F50: 64 | G50: 66 | H50: {=_xlfn.LET(_xlpm.s,IFERROR(--F50,""),_xlpm.e,IFERROR(--G50,""),IF(OR(_xlpm.s="",_xlpm.e="",_xlpm.e<_xlpm.s),"",_xlfn.LET(_xlpm.p,_xlfn.SEQUENCE(_xlpm.e-_xlpm.s+1,1,_xlpm.s,1),SUM(1/COUNTIFS($D:$D,D50,$E:$E,E50,$F:$F,"<>N/A",$G:$G,"<>N/A",$F:$F,"<="&_xlpm.p,$G:$G,">="&_xlpm.p)))))} -> 2.5 | I50: Literatura | J50: Dithyrambo de Diniz. | K50: António Dinis da Cruz e Silva | L50: N/A | M50: N/A | N50: Cruz e Silva, António Diniz da. Poesias de Antonio Diniz da Cruz e Silva na Arcadia de Lisboa Elpino Nonacriense. Tom. III: Que contém as Poesias Líricas. Lisbon: Typografia Lacerdina, 1812. | O50: Reuse (Reprint) | P50: Portugal | R50: FALSE
A51: OP1813s1v1 | B51: OP1813.1.1.3-50 | C51: 03/1813 | D51: 1 | E51: 3 | F51: 67 | G51: 68 | H51: {=_xlfn.LET(_xlpm.s,IFERROR(--F51,""),_xlpm.e,IFERROR(--G51,""),IF(OR(_xlpm.s="",_xlpm.e="",_xlpm.e<_xlpm.s),"",_xlfn.LET(_xlpm.p,_xlfn.SEQUENCE(_xlpm.e-_xlpm.s+1,1,_xlpm.s,1),SUM(1/COUNTIFS($D:$D,D51,$E:$E,E51,$F:$F,"<>N/A",$G:$G,"<>N/A",$F:$F,"<="&_xlpm.p,$G:$G,">="&_xlpm.p)))))} -> 2 | I51: Literatura | J51: Ode Anacreontica do mesmo. | K51: António Dinis da Cruz e Silva | L51: N/A | M51: N/A | N51: Cruz e Silva, António Diniz da. Poesias de Antonio Diniz da Cruz e Silva na Arcadia de Lisboa Elpino Nonacriense. Tom. III: Que contém as Poesias Líricas. Lisbon: Typografia Lacerdina, 1812. | O51: Reuse (Reprint) | P51: Portugal | R51: FALSE
A52: OP1813s1v1 | B52: OP1813.1.1.3-51 | C52: 03/1813 | D52: 1 | E52: 3 | F52: 69 | G52: 78 | H52: {=_xlfn.LET(_xlpm.s,IFERROR(--F52,""),_xlpm.e,IFERROR(--G52,""),IF(OR(_xlpm.s="",_xlpm.e="",_xlpm.e<_xlpm.s),"",_xlfn.LET(_xlpm.p,_xlfn.SEQUENCE(_xlpm.e-_xlpm.s+1,1,_xlpm.s,1),SUM(1/COUNTIFS($D:$D,D52,$E:$E,E52,$F:$F,"<>N/A",$G:$G,"<>N/A",$F:$F,"<="&_xlpm.p,$G:$G,">="&_xlpm.p)))))} -> 9.5 | I52: Literatura | J52: Discurso sobre a Traducção. | K52: Domingos Borges de Barros | L52: N/A | M52: N/A | N52: N/A | O52: Local | P52: Brazil | R52: FALSE
A53: OP1813s1v1 | B53: OP1813.1.1.3-52 | C53: 03/1813 | D53: 1 | E53: 3 | F53: 78 | G53: 81 | H53: {=_xlfn.LET(_xlpm.s,IFERROR(--F53,""),_xlpm.e,IFERROR(--G53,""),IF(OR(_xlpm.s="",_xlpm.e="",_xlpm.e<_xlpm.s),"",_xlfn.LET(_xlpm.p,_xlfn.SEQUENCE(_xlpm.e-_xlpm.s+1,1,_xlpm.s,1),SUM(1/COUNTIFS($D:$D,D53,$E:$E,E53,$F:$F,"<>N/A",$G:$G,"<>N/A",$F:$F,"<="&_xlpm.p,$G:$G,">="&_xlpm.p)))))} -> 3 | I53: Literatura | J53: Maximas, Pensamentos, e Reflexoẽs Moraes por hum Brazileiro. | K53: Mariano Pereira da Fonseca | L53: N/A | M53: N/A | N53: N/A | O53: Local | P53: Brazil | R53: FALSE
A54: OP1813s1v1 | B54: OP1813.1.1.3-53 | C54: 03/1813 | D54: 1 | E54: 3 | F54: 81 | G54: 85 | H54: {=_xlfn.LET(_xlpm.s,IFERROR(--F54,""),_xlpm.e,IFERROR(--G54,""),IF(OR(_xlpm.s="",_xlpm.e="",_xlpm.e<_xlpm.s),"",_xlfn.LET(_xlpm.p,_xlfn.SEQUENCE(_xlpm.e-_xlpm.s+1,1,_xlpm.s,1),SUM(1/COUNTIFS($D:$D,D54,$E:$E,E54,$F:$F,"<>N/A",$G:$G,"<>N/A",$F:$F,"<="&_xlpm.p,$G:$G,">="&_xlpm.p)))))} -> 4 | I54: Política | J54: Na Corte Carlton-House, 29 de Dezembro de 1812, estando S. A. R. o Principe Regente em Conselho. | K54: Chetwynd | L54: N/A | M54: N/A | N54: “Order in Council, 23 June 1812 (Revocation of the Orders in Council as Regards American Vessels).” Reprinted in The Acts, Orders in Council, &c. of Great Britain [on Trade], 1793–1812. | O54: Reuse (Translation) | P54: United Kingdom | R54: FALSE
A55: OP1813s1v1 | B55: OP1813.1.1.3-54 | C55: 03/1813 | D55: 1 | E55: 3 | F55: 85 | G55: 88 | H55: {=_xlfn.LET(_xlpm.s,IFERROR(--F55,""),_xlpm.e,IFERROR(--G55,""),IF(OR(_xlpm.s="",_xlpm.e="",_xlpm.e<_xlpm.s),"",_xlfn.LET(_xlpm.p,_xlfn.SEQUENCE(_xlpm.e-_xlpm.s+1,1,_xlpm.s,1),SUM(1/COUNTIFS($D:$D,D55,$E:$E,E55,$F:$F,"<>N/A",$G:$G,"<>N/A",$F:$F,"<="&_xlpm.p,$G:$G,">="&_xlpm.p)))))} -> 3 | I55: Política | J55: Tratado de Paz entre a Inglaterra e a Russia. | K55: N/A | L55: N/A | M55: N/A | N55: N/A | O55: Reuse (Translation) | P55: Portugal | Q55: Diplomatic text carried via Portuguese official prints. | R55: FALSE
A56: OP1813s1v1 | B56: OP1813.1.1.3-55 | C56: 03/1813 | D56: 1 | E56: 3 | F56: 88 | G56: 93 | H56: {=_xlfn.LET(_xlpm.s,IFERROR(--F56,""),_xlpm.e,IFERROR(--G56,""),IF(OR(_xlpm.s="",_xlpm.e="",_xlpm.e<_xlpm.s),"",_xlfn.LET(_xlpm.p,_xlfn.SEQUENCE(_xlpm.e-_xlpm.s+1,1,_xlpm.s,1),SUM(1/COUNTIFS($D:$D,D56,$E:$E,E56,$F:$F,"<>N/A",$G:$G,"<>N/A",$F:$F,"<="&_xlpm.p,$G:$G,">="&_xlpm.p)))))} -> 5 | I56: Política | J56: Artigos estabelecidos no Parlamento da Sicilia, e apresentados ao Soberano para sua sancção. | K56: N/A | L56: N/A | M56: N/A | N56: N/A | O56: Reuse (Translation) | P56: Portugal | Q56: Diplomatic text carried via Portuguese official prints. | R56: FALSE
A57: OP1813s1v1 | B57: OP1813.1.1.3-56 | C57: 03/1813 | D57: 1 | E57: 3 | F57: 93 | G57: 95 | H57: {=_xlfn.LET(_xlpm.s,IFERROR(--F57,""),_xlpm.e,IFERROR(--G57,""),IF(OR(_xlpm.s="",_xlpm.e="",_xlpm.e<_xlpm.s),"",_xlfn.LET(_xlpm.p,_xlfn.SEQUENCE(_xlpm.e-_xlpm.s+1,1,_xlpm.s,1),SUM(1/COUNTIFS($D:$D,D57,$E:$E,E57,$F:$F,"<>N/A",$G:$G,"<>N/A",$F:$F,"<="&_xlpm.p,$G:$G,">="&_xlpm.p)))))} -> 2 | I57: Política | J57: Os principaes dos 16 artigos do Tratado de Paz, concluído entre a Rússia e a Subli-Porta. | K57: N/A | L57: N/A | M57: N/A | N57: N/A | O57: Local | P57: Brazil | R57: FALSE
A58: OP1813s1v1 | B58: OP1813.1.1.3-57 | C58: 03/1813 | D58: 1 | E58: 3 | F58: 95 | G58: 98 | H58: {=_xlfn.LET(_xlpm.s,IFERROR(--F58,""),_xlpm.e,IFERROR(--G58,""),IF(OR(_xlpm.s="",_xlpm.e="",_xlpm.e<_xlpm.s),"",_xlfn.LET(_xlpm.p,_xlfn.SEQUENCE(_xlpm.e-_xlpm.s+1,1,_xlpm.s,1),SUM(1/COUNTIFS($D:$D,D58,$E:$E,E58,$F:$F,"<>N/A",$G:$G,"<>N/A",$F:$F,"<="&_xlpm.p,$G:$G,">="&_xlpm.p)))))} -> 3 | I58: Estatística | J58: Noticia da População, Commercio, e Agricultura da Capitania de Goyaz. | K58: N/A | L58: N/A | M58: N/A | N58: N/A | O58: Local | P58: Brazil | R58: FALSE
A59: OP1813s1v1 | B59: OP1813.1.1.3-58 | C59: 03/1813 | D59: 1 | E59: 3 | F59: 98 | G59: 100 | H59: {=_xlfn.LET(_xlpm.s,IFERROR(--F59,""),_xlpm.e,IFERROR(--G59,""),IF(OR(_xlpm.s="",_xlpm.e="",_xlpm.e<_xlpm.s),"",_xlfn.LET(_xlpm.p,_xlfn.SEQUENCE(_xlpm.e-_xlpm.s+1,1,_xlpm.s,1),SUM(1/COUNTIFS($D:$D,D59,$E:$E,E59,$F:$F,"<>N/A",$G:$G,"<>N/A",$F:$F,"<="&_xlpm.p,$G:$G,">="&_xlpm.p)))))} -> 2 | I59: Estatística | J59: [O Governo de S. Catharina compreende nove districtos, a saber.] População, Navegação, Produçoens, etc., da Ilha de S. Catharina. | K59: N/A | L59: N/A | M59: N/A | N59: N/A | O59: Local | P59: Brazil | R59: FALSE
A60: OP1813s1v1 | B60: OP1813.1.1.3-59 | C60: 03/1813 | D60: 1 | E60: 3 | F60: 100 | G60: 105 | H60: {=_xlfn.LET(_xlpm.s,IFERROR(--F60,""),_xlpm.e,IFERROR(--G60,""),IF(OR(_xlpm.s="",_xlpm.e="",_xlpm.e<_xlpm.s),"",_xlfn.LET(_xlpm.p,_xlfn.SEQUENCE(_xlpm.e-_xlpm.s+1,1,_xlpm.s,1),SUM(1/COUNTIFS($D:$D,D60,$E:$E,E60,$F:$F,"<>N/A",$G:$G,"<>N/A",$F:$F,"<="&_xlpm.p,$G:$G,">="&_xlpm.p)))))} -> 5 | I60: Estatística | J60: Noticias Estatisticas acerca da Capitania de S. Paulo em 1811, extrahidas do Mappa Official. | K60: N/A | L60: N/A | M60: N/A | N60: N/A | O60: Local | P60: Brazil | R60: FALSE
A61: OP1813s1v1 | B61: OP1813.1.1.3-60 | C61: 03/1813 | D61: 1 | E61: 3 | F61: 105 | G61: 106 | H61: {=_xlfn.LET(_xlpm.s,IFERROR(--F61,""),_xlpm.e,IFERROR(--G61,""),IF(OR(_xlpm.s="",_xlpm.e="",_xlpm.e<_xlpm.s),"",_xlfn.LET(_xlpm.p,_xlfn.SEQUENCE(_xlpm.e-_xlpm.s+1,1,_xlpm.s,1),SUM(1/COUNTIFS($D:$D,D61,$E:$E,E61,$F:$F,"<>N/A",$G:$G,"<>N/A",$F:$F,"<="&_xlpm.p,$G:$G,">="&_xlpm.p)))))} -> 1 | I61: Estatística | J61: Noticia sobre a compra e remessa do marfim de Angola, extrahida de Documentos Officiaes. | K61: N/A | L61: N/A | M61: N/A | N61: N/A | O61: Local | P61: Brazil | R61: FALSE
A62: OP1813s1v1 | B62: OP1813.1.1.3-61 | C62: 03/1813 | D62: 1 | E62: 3 | F62: 106 | G62: 108 | H62: {=_xlfn.LET(_xlpm.s,IFERROR(--F62,""),_xlpm.e,IFERROR(--G62,""),IF(OR(_xlpm.s="",_xlpm.e="",_xlpm.e<_xlpm.s),"",_xlfn.LET(_xlpm.p,_xlfn.SEQUENCE(_xlpm.e-_xlpm.s+1,1,_xlpm.s,1),SUM(1/COUNTIFS($D:$D,D62,$E:$E,E62,$F:$F,"<>N/A",$G:$G,"<>N/A",$F:$F,"<="&_xlpm.p,$G:$G,">="&_xlpm.p)))))} -> 2 | I62: Estatística | J62: Miscellanea. | K62: N/A | L62: Panorama | M62: N/A | N62: N/A | O62: Adaptation | P62: United Kingdom | Q62: A short miscellany digest of translated/reprinted foreign “useful news” (notices + statistics, especially maritime), most likely lifted from an early-1810s English compilation credited as “(Panorama.)” in the text. | R62: FALSE
A63: OP1813s1v1 | B63: OP1813.1.1.3-62 | C63: 03/1813 | D63: 1 | E63: 3 | F63: 108 | G63: 110 | H63: {=_xlfn.LET(_xlpm.s,IFERROR(--F63,""),_xlpm.e,IFERROR(--G63,""),IF(OR(_xlpm.s="",_xlpm.e="",_xlpm.e<_xlpm.s),"",_xlfn.LET(_xlpm.p,_xlfn.SEQUENCE(_xlpm.e-_xlpm.s+1,1,_xlpm.s,1),SUM(1/COUNTIFS($D:$D,D63,$E:$E,E63,$F:$F,"<>N/A",$G:$G,"<>N/A",$F:$F,"<="&_xlpm.p,$G:$G,">="&_xlpm.p)))))} -> 2.5 | I63: Estatística | J63: Necrologia. | K63: N/A | L63: N/A | M63: N/A | N63: N/A | O63: Local | P63: Brazil | Q63: Obits mix local/foreign notices; provenance not identifiable from header. | R63: FALSE
A64: OP1813s1v1 | B64: OP1813.1.1.3-63 | C64: 03/1813 | D64: 1 | E64: 3 | F64: 111 | G64: 112 | H64: {=_xlfn.LET(_xlpm.s,IFERROR(--F64,""),_xlpm.e,IFERROR(--G64,""),IF(OR(_xlpm.s="",_xlpm.e="",_xlpm.e<_xlpm.s),"",_xlfn.LET(_xlpm.p,_xlfn.SEQUENCE(_xlpm.e-_xlpm.s+1,1,_xlpm.s,1),SUM(1/COUNTIFS($D:$D,D64,$E:$E,E64,$F:$F,"<>N/A",$G:$G,"<>N/A",$F:$F,"<="&_xlpm.p,$G:$G,">="&_xlpm.p)))))} -> 2 | I64: Estatística | J64: Continuação do Estado da athmosfera do mez de Fevereiro, e o de Março. | K64: N/A | L64: N/A | M64: N/A | N64: N/A | O64: Local | P64: Brazil | Q64: Monthly meteorological series typical of Rio reporting. | R64: FALSE
A65: OP1813s1v1 | B65: OP1813.1.1.3-64 | C65: 03/1813 | D65: 1 | E65: 3 | F65: 113 | G65: 113 | H65: {=_xlfn.LET(_xlpm.s,IFERROR(--F65,""),_xlpm.e,IFERROR(--G65,""),IF(OR(_xlpm.s="",_xlpm.e="",_xlpm.e<_xlpm.s),"",_xlfn.LET(_xlpm.p,_xlfn.SEQUENCE(_xlpm.e-_xlpm.s+1,1,_xlpm.s,1),SUM(1/COUNTIFS($D:$D,D65,$E:$E,E65,$F:$F,"<>N/A",$G:$G,"<>N/A",$F:$F,"<="&_xlpm.p,$G:$G,">="&_xlpm.p)))))} -> 1 | I65: Estatística | J65: Obra publicada nesta Corte. | K65: N/A | L65: N/A | M65: N/A | N65: N/A | O65: Local | P65: Brazil | Q65: “Nesta Corte” = Rio de Janeiro; local publication notice. | R65: FALSE
A66: OP1813s1v1 | B66: OP1813.1.1.4-65 | C66: 04/1813 | D66: 1 | E66: 4 | F66: 3 | G66: 5 | H66: {=_xlfn.LET(_xlpm.s,IFERROR(--F66,""),_xlpm.e,IFERROR(--G66,""),IF(OR(_xlpm.s="",_xlpm.e="",_xlpm.e<_xlpm.s),"",_xlfn.LET(_xlpm.p,_xlfn.SEQUENCE(_xlpm.e-_xlpm.s+1,1,_xlpm.s,1),SUM(1/COUNTIFS($D:$D,D66,$E:$E,E66,$F:$F,"<>N/A",$G:$G,"<>N/A",$F:$F,"<="&_xlpm.p,$G:$G,">="&_xlpm.p)))))} -> 2.5 | I66: Literatura | J66: Remettida de Versailles á Paris por Francisco Manoel Nascimento (Filinto Elysio) á Domingos Borges de Barros. | K66: Francisco Manoel Nascimento | L66: N/A | M66: N/A | N66: N/A | O66: Local | P66: Brazil | Q66: Framed as private correspondence first printed in Rio de Janeiro. | R66: FALSE
A67: OP1813s1v1 | B67: OP1813.1.1.4-66 | C67: 04/1813 | D67: 1 | E67: 4 | F67: 5 | G67: 8 | H67: {=_xlfn.LET(_xlpm.s,IFERROR(--F67,""),_xlpm.e,IFERROR(--G67,""),IF(OR(_xlpm.s="",_xlpm.e="",_xlpm.e<_xlpm.s),"",_xlfn.LET(_xlpm.p,_xlfn.SEQUENCE(_xlpm.e-_xlpm.s+1,1,_xlpm.s,1),SUM(1/COUNTIFS($D:$D,D67,$E:$E,E67,$F:$F,"<>N/A",$G:$G,"<>N/A",$F:$F,"<="&_xlpm.p,$G:$G,">="&_xlpm.p)))))} -> 3 | I67: Literatura | J67: Epistola em resposta, remettida de Paris á Versailles, por B*** á Filinto Elysio. | K67: Domingos Borges de Barros | L67: N/A | M67: N/A | N67: N/A | O67: Local | P67: Brazil | Q67: Framed as private correspondence first printed in Rio de Janeiro. | R67: FALSE
A68: OP1813s1v1 | B68: OP1813.1.1.4-67 | C68: 04/1813 | D68: 1 | E68: 4 | F68: 8 | G68: 9 | H68: {=_xlfn.LET(_xlpm.s,IFERROR(--F68,""),_xlpm.e,IFERROR(--G68,""),IF(OR(_xlpm.s="",_xlpm.e="",_xlpm.e<_xlpm.s),"",_xlfn.LET(_xlpm.p,_xlfn.SEQUENCE(_xlpm.e-_xlpm.s+1,1,_xlpm.s,1),SUM(1/COUNTIFS($D:$D,D68,$E:$E,E68,$F:$F,"<>N/A",$G:$G,"<>N/A",$F:$F,"<="&_xlpm.p,$G:$G,">="&_xlpm.p)))))} -> 1.5 | I68: Literatura | J68: Lyra inedita de Gonzaga. | K68: Gonzaga | L68: N/A | M68: N/A | N68: N/A | O68: Local | P68: Brazil | Q68: Marked “inédita”; first printing of a Brazilian poet’s manuscript in a Rio journal. | R68: FALSE
A69: OP1813s1v1 | B69: OP1813.1.1.4-68 | C69: 04/1813 | D69: 1 | E69: 4 | F69: 10 | G69: 10 | H69: {=_xlfn.LET(_xlpm.s,IFERROR(--F69,""),_xlpm.e,IFERROR(--G69,""),IF(OR(_xlpm.s="",_xlpm.e="",_xlpm.e<_xlpm.s),"",_xlfn.LET(_xlpm.p,_xlfn.SEQUENCE(_xlpm.e-_xlpm.s+1,1,_xlpm.s,1),SUM(1/COUNTIFS($D:$D,D69,$E:$E,E69,$F:$F,"<>N/A",$G:$G,"<>N/A",$F:$F,"<="&_xlpm.p,$G:$G,">="&_xlpm.p)))))} -> 1 | I69: Literatura | J69: Epigrammas de Diniz. | K69: António Dinis da Cruz e Silva | L69: N/A | M69: N/A | N69: Cruz e Silva, António Dinis da. “Epigrammas.” In Poesias de Antonio Diniz da Cruz e Silva (Elpino Nonacriense). Lisbon: Typographia Lacerdina, 1807–1817. | O69: Reuse (Reprint) | P69: Portugal | R69: FALSE
A70: OP1813s1v1 | B70: OP1813.1.1.4-69 | C70: 04/1813 | D70: 1 | E70: 4 | F70: 11 | G70: 20 | H70: {=_xlfn.LET(_xlpm.s,IFERROR(--F70,""),_xlpm.e,IFERROR(--G70,""),IF(OR(_xlpm.s="",_xlpm.e="",_xlpm.e<_xlpm.s),"",_xlfn.LET(_xlpm.p,_xlfn.SEQUENCE(_xlpm.e-_xlpm.s+1,1,_xlpm.s,1),SUM(1/COUNTIFS($D:$D,D70,$E:$E,E70,$F:$F,"<>N/A",$G:$G,"<>N/A",$F:$F,"<="&_xlpm.p,$G:$G,">="&_xlpm.p)))))} -> 10 | I70: Literatura | J70: Satira. | K70: M. J. S. A. | L70: N/A | M70: N/A | N70: N/A | O70: Local | P70: Brazil | R70: FALSE
A71: OP1813s1v1 | B71: OP1813.1.1.4-70 | C71: 04/1813 | D71: 1 | E71: 4 | F71: 21 | G71: 29 | H71: {=_xlfn.LET(_xlpm.s,IFERROR(--F71,""),_xlpm.e,IFERROR(--G71,""),IF(OR(_xlpm.s="",_xlpm.e="",_xlpm.e<_xlpm.s),"",_xlfn.LET(_xlpm.p,_xlfn.SEQUENCE(_xlpm.e-_xlpm.s+1,1,_xlpm.s,1),SUM(1/COUNTIFS($D:$D,D71,$E:$E,E71,$F:$F,"<>N/A",$G:$G,"<>N/A",$F:$F,"<="&_xlpm.p,$G:$G,">="&_xlpm.p)))))} -> 8.5 | I71: Gramática Filosófica | J71: Memoria de S.P.F. [As Definiçoens Grammaticaes, publicadas no primeiro…] | K71: Silvestre Pinheiro Ferreira | L71: N/A | M71: N/A | N71: N/A | O71: Local | P71: Brazil | Q71: "S.P.F". was in Rio and published his grammatical/philosophical work there in 1813; O Patriota regularly carried his original texts. | R71: FALSE
A72: OP1813s1v1 | B72: OP1813.1.1.4-71 | C72: 04/1813 | D72: 1 | E72: 4 | F72: 29 | G72: 39 | H72: {=_xlfn.LET(_xlpm.s,IFERROR(--F72,""),_xlpm.e,IFERROR(--G72,""),IF(OR(_xlpm.s="",_xlpm.e="",_xlpm.e<_xlpm.s),"",_xlfn.LET(_xlpm.p,_xlfn.SEQUENCE(_xlpm.e-_xlpm.s+1,1,_xlpm.s,1),SUM(1/COUNTIFS($D:$D,D72,$E:$E,E72,$F:$F,"<>N/A",$G:$G,"<>N/A",$F:$F,"<="&_xlpm.p,$G:$G,">="&_xlpm.p)))))} -> 10.5 | I72: Eloquência | J72: Pratica de Alexandre de Gusmão, entrando na Academia Real de Historia Portugueza, em o dia 13 de Março de 1732. | K72: N/A | L72: N/A | M72: N/A | N72: Gusmão, Alexandre de. “Pratica de Alexandre de Gusmão, entrando na Academia Real de Historia Portugueza, em o dia 13 de Março de 1732.” In Collecçam dos Documentos e Memorias da Academia Real da Historia Portugueza, n. XVI. Lisbon, 1732. | O72: Reuse (Reprint) | P72: Portugal | R72: FALSE
A73: OP1813s1v1 | B73: OP1813.1.1.4-72 | C73: 04/1813 | D73: 1 | E73: 4 | F73: 40 | G73: 68 | H73: {=_xlfn.LET(_xlpm.s,IFERROR(--F73,""),_xlpm.e,IFERROR(--G73,""),IF(OR(_xlpm.s="",_xlpm.e="",_xlpm.e<_xlpm.s),"",_xlfn.LET(_xlpm.p,_xlfn.SEQUENCE(_xlpm.e-_xlpm.s+1,1,_xlpm.s,1),SUM(1/COUNTIFS($D:$D,D73,$E:$E,E73,$F:$F,"<>N/A",$G:$G,"<>N/A",$F:$F,"<="&_xlpm.p,$G:$G,">="&_xlpm.p)))))} -> 28.5 | I73: História | J73: Memoria Historica e Geographica da Descoberta das Minas, Extrahida de Manuscritos de Claudio Manoel da Costa, Secretario do Governo daquella Capitania, que consultou muitos Documentos authenticos, existentes na Secretaria do Governo, e em outros Archivos. | K73: Claudio Manoel da Costa | L73: N/A | M73: N/A | N73: N/A | O73: Local | P73: Brazil | R73: FALSE
A74: OP1813s1v1 | B74: OP1813.1.1.4-73 | C74: 04/1813 | D74: 1 | E74: 4 | F74: 68 | G74: 81 | H74: {=_xlfn.LET(_xlpm.s,IFERROR(--F74,""),_xlpm.e,IFERROR(--G74,""),IF(OR(_xlpm.s="",_xlpm.e="",_xlpm.e<_xlpm.s),"",_xlfn.LET(_xlpm.p,_xlfn.SEQUENCE(_xlpm.e-_xlpm.s+1,1,_xlpm.s,1),SUM(1/COUNTIFS($D:$D,D74,$E:$E,E74,$F:$F,"<>N/A",$G:$G,"<>N/A",$F:$F,"<="&_xlpm.p,$G:$G,">="&_xlpm.p)))))} -> 13 | I74: Artes | J74: Noticia acerca de varios carros de transporte, e particularmente do que os Francezes chamão Haquet, invenção do celebre Pascal. Por B.*** | K74: Domingos Borges de Barros | L74: N/A | M74: N/A | N74: N/A | O74: Local | P74: Brazil | Q74: Article quotes French/European authorities, but the text does not seem to be a direct translation. | R74: TRUE
A75: OP1813s1v1 | B75: OP1813.1.1.4-74 | C75: 04/1813 | D75: 1 | E75: 4 | F75: 81 | G75: 83 | H75: {=_xlfn.LET(_xlpm.s,IFERROR(--F75,""),_xlpm.e,IFERROR(--G75,""),IF(OR(_xlpm.s="",_xlpm.e="",_xlpm.e<_xlpm.s),"",_xlfn.LET(_xlpm.p,_xlfn.SEQUENCE(_xlpm.e-_xlpm.s+1,1,_xlpm.s,1),SUM(1/COUNTIFS($D:$D,D75,$E:$E,E75,$F:$F,"<>N/A",$G:$G,"<>N/A",$F:$F,"<="&_xlpm.p,$G:$G,">="&_xlpm.p)))))} -> 2.5 | I75: Necrologia | J75: Falecimento e enterro do Tenente Coronel Lobo. | K75: N/A | L75: N/A | M75: N/A | N75: N/A | O75: Local | P75: Brazil | Q75: Routine local death notice typical of the Rio “Necrologia” rubric. | R75: FALSE
A76: OP1813s1v1 | B76: OP1813.1.1.4-75 | C76: 04/1813 | D76: 1 | E76: 4 | F76: 84 | G76: 86 | H76: {=_xlfn.LET(_xlpm.s,IFERROR(--F76,""),_xlpm.e,IFERROR(--G76,""),IF(OR(_xlpm.s="",_xlpm.e="",_xlpm.e<_xlpm.s),"",_xlfn.LET(_xlpm.p,_xlfn.SEQUENCE(_xlpm.e-_xlpm.s+1,1,_xlpm.s,1),SUM(1/COUNTIFS($D:$D,D76,$E:$E,E76,$F:$F,"<>N/A",$G:$G,"<>N/A",$F:$F,"<="&_xlpm.p,$G:$G,">="&_xlpm.p)))))} -> 3 | I76: Política | J76: Tratado de Alliança entre S. M. o Imperador e Rei e o Imperador de Austria. | K76: N/A | L76: N/A | M76: N/A | N76: N/A | O76: Reuse (Translation) | P76: Portugal | Q76: European text printed in Portuguese for a Brazilian readership. | R76: FALSE
A77: OP1813s1v1 | B77: OP1813.1.1.4-76 | C77: 04/1813 | D77: 1 | E77: 4 | F77: 87 | G77: 89 | H77: {=_xlfn.LET(_xlpm.s,IFERROR(--F77,""),_xlpm.e,IFERROR(--G77,""),IF(OR(_xlpm.s="",_xlpm.e="",_xlpm.e<_xlpm.s),"",_xlfn.LET(_xlpm.p,_xlfn.SEQUENCE(_xlpm.e-_xlpm.s+1,1,_xlpm.s,1),SUM(1/COUNTIFS($D:$D,D77,$E:$E,E77,$F:$F,"<>N/A",$G:$G,"<>N/A",$F:$F,"<="&_xlpm.p,$G:$G,">="&_xlpm.p)))))} -> 2.5 | I77: Política | J77: Tratado de Alliança concluido a 24 de Fevereiro entre S. M. o Rei de German States e S. M. o Imperador dos Francezes, Rei de Italia, etc., e ratificado em Berlim a 5 de Março de 1812. | K77: N/A | L77: N/A | M77: N/A | N77: N/A | O77: Reuse (Translation) | P77: German States | Q77: European text printed in Portuguese for a Brazilian readership. | R77: FALSE
A78: OP1813s1v1 | B78: OP1813.1.1.4-77 | C78: 04/1813 | D78: 1 | E78: 4 | F78: 89 | G78: 93 | H78: {=_xlfn.LET(_xlpm.s,IFERROR(--F78,""),_xlpm.e,IFERROR(--G78,""),IF(OR(_xlpm.s="",_xlpm.e="",_xlpm.e<_xlpm.s),"",_xlfn.LET(_xlpm.p,_xlfn.SEQUENCE(_xlpm.e-_xlpm.s+1,1,_xlpm.s,1),SUM(1/COUNTIFS($D:$D,D78,$E:$E,E78,$F:$F,"<>N/A",$G:$G,"<>N/A",$F:$F,"<="&_xlpm.p,$G:$G,">="&_xlpm.p)))))} -> 4.5 | I78: N/A | J78: ["Não havendo recebido noticias modernas da Europa…"] | K78: N/A | L78: N/A | M78: N/A | N78: N/A | O78: Local | P78: Brazil | R78: TRUE
A79: OP1813s1v1 | B79: OP1813.1.1.4-78 | C79: 04/1813 | D79: 1 | E79: 4 | F79: 94 | G79: 95 | H79: {=_xlfn.LET(_xlpm.s,IFERROR(--F79,""),_xlpm.e,IFERROR(--G79,""),IF(OR(_xlpm.s="",_xlpm.e="",_xlpm.e<_xlpm.s),"",_xlfn.LET(_xlpm.p,_xlfn.SEQUENCE(_xlpm.e-_xlpm.s+1,1,_xlpm.s,1),SUM(1/COUNTIFS($D:$D,D79,$E:$E,E79,$F:$F,"<>N/A",$G:$G,"<>N/A",$F:$F,"<="&_xlpm.p,$G:$G,">="&_xlpm.p)))))} -> 2 | I79: Estatística | J79: Mappa dos Habitantes da Capitania de Paraiba do Norte em 1812 e 1811. | K79: N/A | L79: N/A | M79: N/A | N79: N/A | O79: Local | P79: Brazil | Q79: Provincial demographic return from a Brazilian capitania. | R79: FALSE
A80: OP1813s1v1 | B80: OP1813.1.1.4-79 | C80: 04/1813 | D80: 1 | E80: 4 | F80: 96 | G80: 97 | H80: {=_xlfn.LET(_xlpm.s,IFERROR(--F80,""),_xlpm.e,IFERROR(--G80,""),IF(OR(_xlpm.s="",_xlpm.e="",_xlpm.e<_xlpm.s),"",_xlfn.LET(_xlpm.p,_xlfn.SEQUENCE(_xlpm.e-_xlpm.s+1,1,_xlpm.s,1),SUM(1/COUNTIFS($D:$D,D80,$E:$E,E80,$F:$F,"<>N/A",$G:$G,"<>N/A",$F:$F,"<="&_xlpm.p,$G:$G,">="&_xlpm.p)))))} -> 1.5 | I80: Comércio | J80: Produçoens da Ilha Grande, consumo, e exportação. | K80: N/A | L80: N/A | M80: N/A | N80: N/A | O80: Local | P80: Brazil | Q80: Economic data for Ilha Grande (RJ), clearly Brazilian local statistics. | R80: FALSE
A81: OP1813s1v1 | B81: OP1813.1.1.4-80 | C81: 04/1813 | D81: 1 | E81: 4 | F81: 97 | G81: 105 | H81: {=_xlfn.LET(_xlpm.s,IFERROR(--F81,""),_xlpm.e,IFERROR(--G81,""),IF(OR(_xlpm.s="",_xlpm.e="",_xlpm.e<_xlpm.s),"",_xlfn.LET(_xlpm.p,_xlfn.SEQUENCE(_xlpm.e-_xlpm.s+1,1,_xlpm.s,1),SUM(1/COUNTIFS($D:$D,D81,$E:$E,E81,$F:$F,"<>N/A",$G:$G,"<>N/A",$F:$F,"<="&_xlpm.p,$G:$G,">="&_xlpm.p)))))} -> 8.5 | I81: Comércio | J81: Noticia de Importação, e Exportação das possessoens Portuguezas no porto de Liverpool nos mezes de Julho, Agosto, Setembro, e Outubro de 1812, extrahida de Mappas Officiaes. | K81: N/A | L81: N/A | M81: N/A | N81: N/A | O81: Reuse (Translation) | P81: United Kingdom | Q81: Compiled from “official maps” of Liverpool; i.e., extracted/translated foreign official returns. | R81: FALSE
A82: OP1813s1v1 | B82: OP1813.1.1.4-81 | C82: 04/1813 | D82: 1 | E82: 4 | F82: 106 | G82: 107 | H82: {=_xlfn.LET(_xlpm.s,IFERROR(--F82,""),_xlpm.e,IFERROR(--G82,""),IF(OR(_xlpm.s="",_xlpm.e="",_xlpm.e<_xlpm.s),"",_xlfn.LET(_xlpm.p,_xlfn.SEQUENCE(_xlpm.e-_xlpm.s+1,1,_xlpm.s,1),SUM(1/COUNTIFS($D:$D,D82,$E:$E,E82,$F:$F,"<>N/A",$G:$G,"<>N/A",$F:$F,"<="&_xlpm.p,$G:$G,">="&_xlpm.p)))))} -> 2 | I82: N/A | J82: Continuação do Estado da athmosfera. | K82: N/A | L82: N/A | M82: N/A | N82: N/A | O82: Local | P82: Brazil | Q82: Monthly Rio meteorological table (ongoing local observation column). | R82: FALSE
A83: OP1813s1v1 | B83: OP1813.1.1.5-82 | C83: 05/1813 | D83: 1 | E83: 5 | F83: 3 | G83: 15 | H83: {=_xlfn.LET(_xlpm.s,IFERROR(--F83,""),_xlpm.e,IFERROR(--G83,""),IF(OR(_xlpm.s="",_xlpm.e="",_xlpm.e<_xlpm.s),"",_xlfn.LET(_xlpm.p,_xlfn.SEQUENCE(_xlpm.e-_xlpm.s+1,1,_xlpm.s,1),SUM(1/COUNTIFS($D:$D,D83,$E:$E,E83,$F:$F,"<>N/A",$G:$G,"<>N/A",$F:$F,"<="&_xlpm.p,$G:$G,">="&_xlpm.p)))))} -> 12.5 | I83: Agricultura | J83: Memoria sobre o Café, sua historia, cultura, e amanhos. | K83: Domingos Borges de Barros | L83: N/A | M83: N/A | N83: Veloso, José Mariano da Conceição. O Fazendeiro do Brazil, ou Tratado das plantas usuais no Brasil. Tomo III, Parte II: “Bebidas alimentosas.” Lisbon: Officina de Simão Thaddeo Ferreira, 1799. | O83: Adaptation | P83: Portugal | Q83: Article condenses Veloso’s Portuguese treatment of coffee (itself based on European authorities like Sylvestre Dufour, Aublet, Rozier, and Laborie, ), following the same sequence of advice on harvest colour, avoiding early picking (incl. the Mauritius comparison), bean sorting, and not shaking branches, but the phrasing is recast; it is an Reuse (Adaptation)/summary. | R83: TRUE
A84: OP1813s1v1 | B84: OP1813.1.1.5-83 | C84: 05/1813 | D84: 1 | E84: 5 | F84: 15 | G84: 18 | H84: {=_xlfn.LET(_xlpm.s,IFERROR(--F84,""),_xlpm.e,IFERROR(--G84,""),IF(OR(_xlpm.s="",_xlpm.e="",_xlpm.e<_xlpm.s),"",_xlfn.LET(_xlpm.p,_xlfn.SEQUENCE(_xlpm.e-_xlpm.s+1,1,_xlpm.s,1),SUM(1/COUNTIFS($D:$D,D84,$E:$E,E84,$F:$F,"<>N/A",$G:$G,"<>N/A",$F:$F,"<="&_xlpm.p,$G:$G,">="&_xlpm.p)))))} -> 3 | I84: Litteratura | J84: Discurso recitado em Presença de S. A. R., na Meza do Desembargo do Paço, pelo Desembargador Antonio Rodrigues Velloso de Oliveira, Communicado por hum amigo do Autor. | K84: Antonio Rodrigues Velloso de Oliveira | L84: N/A | M84: N/A | N84: N/A | O84: Local | P84: Brazil | Q84: Speech delivered in the “Mesa do Desembargo do Paço," then established in Rio | R84: FALSE
A85: OP1813s1v1 | B85: OP1813.1.1.5-84 | C85: 05/1813 | D85: 1 | E85: 5 | F85: 18 | G85: 29 | H85: {=_xlfn.LET(_xlpm.s,IFERROR(--F85,""),_xlpm.e,IFERROR(--G85,""),IF(OR(_xlpm.s="",_xlpm.e="",_xlpm.e<_xlpm.s),"",_xlfn.LET(_xlpm.p,_xlfn.SEQUENCE(_xlpm.e-_xlpm.s+1,1,_xlpm.s,1),SUM(1/COUNTIFS($D:$D,D85,$E:$E,E85,$F:$F,"<>N/A",$G:$G,"<>N/A",$F:$F,"<="&_xlpm.p,$G:$G,">="&_xlpm.p)))))} -> 11.5 | I85: Gramática Filosófica | J85: Memoria remettida de Macau ao Redactor da Gazeta desta Corte por Joaquim José Leite, Reitor do Real Collegio de S. José em 14 de Janeiro de 1813. | K85: Joaquim José Leite | L85: N/A | M85: N/A | N85: N/A | O85: N/A | P85: Portuguese Macau | Q85: Foreign letter. | R85: FALSE
A86: OP1813s1v1 | B86: OP1813.1.1.5-85 | C86: 05/1813 | D86: 1 | E86: 5 | F86: 30 | G86: 31 | H86: {=_xlfn.LET(_xlpm.s,IFERROR(--F86,""),_xlpm.e,IFERROR(--G86,""),IF(OR(_xlpm.s="",_xlpm.e="",_xlpm.e<_xlpm.s),"",_xlfn.LET(_xlpm.p,_xlfn.SEQUENCE(_xlpm.e-_xlpm.s+1,1,_xlpm.s,1),SUM(1/COUNTIFS($D:$D,D86,$E:$E,E86,$F:$F,"<>N/A",$G:$G,"<>N/A",$F:$F,"<="&_xlpm.p,$G:$G,">="&_xlpm.p)))))} -> 1.5 | I86: Gramática Filosófica | J86: Ode Anacreontica de Diniz. | K86: António Dinis da Cruz e Silva | L86: N/A | M86: N/A | N86: Cruz e Silva, António Dinis da. “Leves Auras, que voando …” (Ode anacreôntica, XXXIII). In Poesias de Antonio Diniz da Cruz e Silva … Tomo III: Que contém as Poesias Líricas, 125–126. Lisbon: Typografia Lacerdina, 1812. | O86: Reuse (Reprint) | P86: Portugal | R86: FALSE
A87: OP1813s1v1 | B87: OP1813.1.1.5-86 | C87: 05/1813 | D87: 1 | E87: 5 | F87: 31 | G87: 33 | H87: {=_xlfn.LET(_xlpm.s,IFERROR(--F87,""),_xlpm.e,IFERROR(--G87,""),IF(OR(_xlpm.s="",_xlpm.e="",_xlpm.e<_xlpm.s),"",_xlfn.LET(_xlpm.p,_xlfn.SEQUENCE(_xlpm.e-_xlpm.s+1,1,_xlpm.s,1),SUM(1/COUNTIFS($D:$D,D87,$E:$E,E87,$F:$F,"<>N/A",$G:$G,"<>N/A",$F:$F,"<="&_xlpm.p,$G:$G,">="&_xlpm.p)))))} -> 2 | I87: Gramática Filosófica | J87: Outra do mesmo Author. | K87: António Dinis da Cruz e Silva | L87: N/A | M87: N/A | N87: Cruz e Silva, António Diniz da. Poesias de Antonio Diniz da Cruz e Silva na Arcadia de Lisboa Elpino Nonacriense. Tom. III: Que contém as Poesias Líricas. Lisbon: Typografia Lacerdina, 1812. | O87: Reuse (Reprint) | P87: Portugal | R87: FALSE
A88: OP1813s1v1 | B88: OP1813.1.1.5-87 | C88: 05/1813 | D88: 1 | E88: 5 | F88: 33 | G88: 34 | H88: {=_xlfn.LET(_xlpm.s,IFERROR(--F88,""),_xlpm.e,IFERROR(--G88,""),IF(OR(_xlpm.s="",_xlpm.e="",_xlpm.e<_xlpm.s),"",_xlfn.LET(_xlpm.p,_xlfn.SEQUENCE(_xlpm.e-_xlpm.s+1,1,_xlpm.s,1),SUM(1/COUNTIFS($D:$D,D88,$E:$E,E88,$F:$F,"<>N/A",$G:$G,"<>N/A",$F:$F,"<="&_xlpm.p,$G:$G,">="&_xlpm.p)))))} -> 0.83333333 | I88: Gramática Filosófica | J88: Epigramma de Diniz. | K88: António Dinis da Cruz e Silva | L88: N/A | M88: N/A | N88: Cruz e Silva, António Diniz da. Poesias de Antonio Diniz da Cruz e Silva na Arcadia de Lisboa Elpino Nonacriense. Tom. III: Que contém as Poesias Líricas. Lisbon: Typografia Lacerdina, 1812. | O88: Reuse (Reprint) | P88: Portugal | R88: FALSE
A89: OP1813s1v1 | B89: OP1813.1.1.5-88 | C89: 05/1813 | D89: 1 | E89: 5 | F89: 34 | G89: 34 | H89: {=_xlfn.LET(_xlpm.s,IFERROR(--F89,""),_xlpm.e,IFERROR(--G89,""),IF(OR(_xlpm.s="",_xlpm.e="",_xlpm.e<_xlpm.s),"",_xlfn.LET(_xlpm.p,_xlfn.SEQUENCE(_xlpm.e-_xlpm.s+1,1,_xlpm.s,1),SUM(1/COUNTIFS($D:$D,D89,$E:$E,E89,$F:$F,"<>N/A",$G:$G,"<>N/A",$F:$F,"<="&_xlpm.p,$G:$G,">="&_xlpm.p)))))} -> 0.33333333 | I89: Gramática Filosófica | J89: Outro do mesmo Author. | K89: António Dinis da Cruz e Silva | L89: N/A | M89: N/A | N89: Cruz e Silva, António Diniz da. Poesias de Antonio Diniz da Cruz e Silva na Arcadia de Lisboa Elpino Nonacriense. Tom. III: Que contém as Poesias Líricas. Lisbon: Typografia Lacerdina, 1812. | O89: Reuse (Reprint) | P89: Portugal | R89: FALSE
A90: OP1813s1v1 | B90: OP1813.1.1.5-89 | C90: 05/1813 | D90: 1 | E90: 5 | F90: 34 | G90: 36 | H90: {=_xlfn.LET(_xlpm.s,IFERROR(--F90,""),_xlpm.e,IFERROR(--G90,""),IF(OR(_xlpm.s="",_xlpm.e="",_xlpm.e<_xlpm.s),"",_xlfn.LET(_xlpm.p,_xlfn.SEQUENCE(_xlpm.e-_xlpm.s+1,1,_xlpm.s,1),SUM(1/COUNTIFS($D:$D,D90,$E:$E,E90,$F:$F,"<>N/A",$G:$G,"<>N/A",$F:$F,"<="&_xlpm.p,$G:$G,">="&_xlpm.p)))))} -> 2.3333333 | I90: Gramática Filosófica | J90: Ode ao Illustrissimo e Excellentissimo Senhor D. Manoel de Portugal e Castro, sobre a Tradução dos Ensayos Moraes, e Ensaio sobre a Critica d'Alexandre Pope, feita pelo Illustrissimo, e Excellentissimo Senhor Conde d'Aguiar, seu Tio. | K90: N/A | L90: N/A | M90: N/A | N90: N/A | O90: Local | P90: Brazil | R90: FALSE
A91: OP1813s1v1 | B91: OP1813.1.1.5-90 | C91: 05/1813 | D91: 1 | E91: 5 | F91: 37 | G91: 43 | H91: {=_xlfn.LET(_xlpm.s,IFERROR(--F91,""),_xlpm.e,IFERROR(--G91,""),IF(OR(_xlpm.s="",_xlpm.e="",_xlpm.e<_xlpm.s),"",_xlfn.LET(_xlpm.p,_xlfn.SEQUENCE(_xlpm.e-_xlpm.s+1,1,_xlpm.s,1),SUM(1/COUNTIFS($D:$D,D91,$E:$E,E91,$F:$F,"<>N/A",$G:$G,"<>N/A",$F:$F,"<="&_xlpm.p,$G:$G,">="&_xlpm.p)))))} -> 7 | I91: Gramática Filosófica | J91: Vantagens da vida campestre, em resposta à carta, em que de Lisboa se despedia, devendo partir para a Bahia, Paulo José de Mello, escritas de Paris aos 21 de Maio de 1806. Por B.*** | K91: Domingos Borges de Barros | L91: N/A | M91: N/A | N91: N/A | O91: Local | P91: Brazil | Q91: Framed as private correspondence | R91: FALSE
A92: OP1813s1v1 | B92: OP1813.1.1.5-91 | C92: 05/1813 | D92: 1 | E92: 5 | F92: 44 | G92: 44 | H92: {=_xlfn.LET(_xlpm.s,IFERROR(--F92,""),_xlpm.e,IFERROR(--G92,""),IF(OR(_xlpm.s="",_xlpm.e="",_xlpm.e<_xlpm.s),"",_xlfn.LET(_xlpm.p,_xlfn.SEQUENCE(_xlpm.e-_xlpm.s+1,1,_xlpm.s,1),SUM(1/COUNTIFS($D:$D,D92,$E:$E,E92,$F:$F,"<>N/A",$G:$G,"<>N/A",$F:$F,"<="&_xlpm.p,$G:$G,">="&_xlpm.p)))))} -> 1 | I92: Gramática Filosófica | J92: Soneto aos annos de S. A. R. o Principe Regente Nosso Senhor. | K92: N/A | L92: N/A | M92: N/A | N92: N/A | O92: Reuse (Reprint) | P92: Portugal | Q92: It is explicitly marked as “Remettido de Lisboa." | R92: FALSE
A93: OP1813s1v1 | B93: OP1813.1.1.5-92 | C93: 05/1813 | D93: 1 | E93: 5 | F93: 45 | G93: 50 | H93: {=_xlfn.LET(_xlpm.s,IFERROR(--F93,""),_xlpm.e,IFERROR(--G93,""),IF(OR(_xlpm.s="",_xlpm.e="",_xlpm.e<_xlpm.s),"",_xlfn.LET(_xlpm.p,_xlfn.SEQUENCE(_xlpm.e-_xlpm.s+1,1,_xlpm.s,1),SUM(1/COUNTIFS($D:$D,D93,$E:$E,E93,$F:$F,"<>N/A",$G:$G,"<>N/A",$F:$F,"<="&_xlpm.p,$G:$G,">="&_xlpm.p)))))} -> 5.5 | I93: Gramática Filosófica | J93: Satira aos Poetas, attribuida ao celebre Philologo Pedro José da Fonseca. | K93: Pedro José da Fonseca | L93: N/A | M93: N/A | N93: Veríssimo Lusitano [Pedro José da Fonseca], Invectiva ou sátira contra os maus poetas (Lisbon: Off. da Viúva de Ignacio Nogueira Xisto, 1767). | O93: Reuse (Reprint) | P93: Portugal | R93: FALSE
A94: OP1813s1v1 | B94: OP1813.1.1.5-93 | C94: 05/1813 | D94: 1 | E94: 5 | F94: 50 | G94: 61 | H94: {=_xlfn.LET(_xlpm.s,IFERROR(--F94,""),_xlpm.e,IFERROR(--G94,""),IF(OR(_xlpm.s="",_xlpm.e="",_xlpm.e<_xlpm.s),"",_xlfn.LET(_xlpm.p,_xlfn.SEQUENCE(_xlpm.e-_xlpm.s+1,1,_xlpm.s,1),SUM(1/COUNTIFS($D:$D,D94,$E:$E,E94,$F:$F,"<>N/A",$G:$G,"<>N/A",$F:$F,"<="&_xlpm.p,$G:$G,">="&_xlpm.p)))))} -> 11 | I94: História | J94: Viagem da Capitania de S. Paulo à Villa de Cuiabá. | K94: N/A | L94: N/A | M94: N/A | N94: N/A | O94: Local | P94: Brazil | Q94: Brazilian itinerary/description; the body of the issue around this section describes Brazilian rivers, fauna, routes, etc., typical of editor-prepared local materials. | R94: FALSE
A95: OP1813s1v1 | B95: OP1813.1.1.5-94 | C95: 05/1813 | D95: 1 | E95: 5 | F95: 61 | G95: 69 | H95: {=_xlfn.LET(_xlpm.s,IFERROR(--F95,""),_xlpm.e,IFERROR(--G95,""),IF(OR(_xlpm.s="",_xlpm.e="",_xlpm.e<_xlpm.s),"",_xlfn.LET(_xlpm.p,_xlfn.SEQUENCE(_xlpm.e-_xlpm.s+1,1,_xlpm.s,1),SUM(1/COUNTIFS($D:$D,D95,$E:$E,E95,$F:$F,"<>N/A",$G:$G,"<>N/A",$F:$F,"<="&_xlpm.p,$G:$G,">="&_xlpm.p)))))} -> 8.5 | I95: História | J95: Historia do Rio de Janeiro, descobrimento, e primeira restauração deste Territorio. | K95: N/A | L95: N/A | M95: N/A | N95: N/A | O95: Local | P95: Brazil | Q95: Narrative history focused on Rio produced as an internal serial | R95: FALSE
A96: OP1813s1v1 | B96: OP1813.1.1.5-95 | C96: 05/1813 | D96: 1 | E96: 5 | F96: 70 | G96: 83 | H96: {=_xlfn.LET(_xlpm.s,IFERROR(--F96,""),_xlpm.e,IFERROR(--G96,""),IF(OR(_xlpm.s="",_xlpm.e="",_xlpm.e<_xlpm.s),"",_xlfn.LET(_xlpm.p,_xlfn.SEQUENCE(_xlpm.e-_xlpm.s+1,1,_xlpm.s,1),SUM(1/COUNTIFS($D:$D,D96,$E:$E,E96,$F:$F,"<>N/A",$G:$G,"<>N/A",$F:$F,"<="&_xlpm.p,$G:$G,">="&_xlpm.p)))))} -> 13.5 | I96: Política | J96: Manifesto da America Septentrional contra a Gran Bretanha. | K96: James Madison | L96: N/A | M96: N/A | N96: N/A | O96: Reuse (Translation) | P96: Portugal | Q96: War-of-1812 political document presented in Portuguese for Brazilian readers | R96: FALSE
A97: OP1813s1v1 | B97: OP1813.1.1.5-96 | C97: 05/1813 | D97: 1 | E97: 5 | F97: 83 | G97: 86 | H97: {=_xlfn.LET(_xlpm.s,IFERROR(--F97,""),_xlpm.e,IFERROR(--G97,""),IF(OR(_xlpm.s="",_xlpm.e="",_xlpm.e<_xlpm.s),"",_xlfn.LET(_xlpm.p,_xlfn.SEQUENCE(_xlpm.e-_xlpm.s+1,1,_xlpm.s,1),SUM(1/COUNTIFS($D:$D,D97,$E:$E,E97,$F:$F,"<>N/A",$G:$G,"<>N/A",$F:$F,"<="&_xlpm.p,$G:$G,">="&_xlpm.p)))))} -> 3 | I97: Política | J97: Declaração de Luiz XVIII. Rei de França. | K97: N/A | L97: N/A | M97: N/A | N97: N/A | O97: Reuse (Translation) | P97: France | Q97: French royal declaration translated for the paper’s political section. | R97: FALSE
A98: OP1813s1v1 | B98: OP1813.1.1.5-97 | C98: 05/1813 | D98: 1 | E98: 5 | F98: 86 | G98: 111 | H98: {=_xlfn.LET(_xlpm.s,IFERROR(--F98,""),_xlpm.e,IFERROR(--G98,""),IF(OR(_xlpm.s="",_xlpm.e="",_xlpm.e<_xlpm.s),"",_xlfn.LET(_xlpm.p,_xlfn.SEQUENCE(_xlpm.e-_xlpm.s+1,1,_xlpm.s,1),SUM(1/COUNTIFS($D:$D,D98,$E:$E,E98,$F:$F,"<>N/A",$G:$G,"<>N/A",$F:$F,"<="&_xlpm.p,$G:$G,">="&_xlpm.p)))))} -> 25.5 | I98: Política | J98: Declaração do Principe Regente da Gran Bretanha contra os Estados Unidos da America. | K98: N/A | L98: N/A | M98: N/A | N98: N/A | O98: Reuse (Translation) | P98: United Kingdom | Q98: British government act rendered in Portuguese | R98: FALSE
A99: OP1813s1v1 | B99: OP1813.1.1.5-98 | C99: 05/1813 | D99: 1 | E99: 5 | F99: 112 | G99: 124 | H99: {=_xlfn.LET(_xlpm.s,IFERROR(--F99,""),_xlpm.e,IFERROR(--G99,""),IF(OR(_xlpm.s="",_xlpm.e="",_xlpm.e<_xlpm.s),"",_xlfn.LET(_xlpm.p,_xlfn.SEQUENCE(_xlpm.e-_xlpm.s+1,1,_xlpm.s,1),SUM(1/COUNTIFS($D:$D,D99,$E:$E,E99,$F:$F,"<>N/A",$G:$G,"<>N/A",$F:$F,"<="&_xlpm.p,$G:$G,">="&_xlpm.p)))))} -> 13 | I99: Política | J99: Discurso sobre o Estado Politico da Europa. | K99: N/A | L99: N/A | M99: N/A | N99: N/A | O99: Local | P99: Brazil | Q99: Broad European situation report compiled from foreign gazettes and printed in Portuguese | R99: FALSE
A100: OP1813s1v1 | B100: OP1813.1.1.5-99 | C100: 05/1813 | D100: 1 | E100: 5 | F100: 125 | G100: 126 | H100: {=_xlfn.LET(_xlpm.s,IFERROR(--F100,""),_xlpm.e,IFERROR(--G100,""),IF(OR(_xlpm.s="",_xlpm.e="",_xlpm.e<_xlpm.s),"",_xlfn.LET(_xlpm.p,_xlfn.SEQUENCE(_xlpm.e-_xlpm.s+1,1,_xlpm.s,1),SUM(1/COUNTIFS($D:$D,D100,$E:$E,E100,$F:$F,"<>N/A",$G:$G,"<>N/A",$F:$F,"<="&_xlpm.p,$G:$G,">="&_xlpm.p)))))} -> 2 | I100: N/A | J100: Continuação do Estado da athmosfera. | K100: N/A | L100: N/A | M100: N/A | N100: N/A | O100: Local | P100: Brazil | Q100: The monthly Rio meteorological tabl, ongoing local observational series. | R100: FALSE
A101: OP1813s1v1 | B101: OP1813.1.1.6-100 | C101: 06/1813 | D101: 1 | E101: 6 | F101: 3 | G101: 14 | H101: {=_xlfn.LET(_xlpm.s,IFERROR(--F101,""),_xlpm.e,IFERROR(--G101,""),IF(OR(_xlpm.s="",_xlpm.e="",_xlpm.e<_xlpm.s),"",_xlfn.LET(_xlpm.p,_xlfn.SEQUENCE(_xlpm.e-_xlpm.s+1,1,_xlpm.s,1),SUM(1/COUNTIFS($D:$D,D101,$E:$E,E101,$F:$F,"<>N/A",$G:$G,"<>N/A",$F:$F,"<="&_xlpm.p,$G:$G,">="&_xlpm.p)))))} -> 12 | I101: Litteratura | J101: Methodo de achar novas combinaçoens de letras para novas palavras, continuado do N.º 5.º pag. 18. | K101: N/A | L101: N/A | M101: N/A | N101: N/A | O101: Local | P101: Brazil | Q101: Original critical/philological essay. | R101: FALSE
A102: OP1813s1v1 | B102: OP1813.1.1.6-101 | C102: 06/1813 | D102: 1 | E102: 6 | F102: 15 | G102: 22 | H102: {=_xlfn.LET(_xlpm.s,IFERROR(--F102,""),_xlpm.e,IFERROR(--G102,""),IF(OR(_xlpm.s="",_xlpm.e="",_xlpm.e<_xlpm.s),"",_xlfn.LET(_xlpm.p,_xlfn.SEQUENCE(_xlpm.e-_xlpm.s+1,1,_xlpm.s,1),SUM(1/COUNTIFS($D:$D,D102,$E:$E,E102,$F:$F,"<>N/A",$G:$G,"<>N/A",$F:$F,"<="&_xlpm.p,$G:$G,">="&_xlpm.p)))))} -> 7.5 | I102: Poesia | J102: Poema, recitado no dia dos annos de S. Magestade Fidelissima D. MARIA I. em 1788. | K102: M. J. S. A. | L102: N/A | M102: N/A | N102: N/A | O102: Local | P102: Brazil | Q102: Occasional court ode for the Rio court | R102: FALSE
A103: OP1813s1v1 | B103: OP1813.1.1.6-102 | C103: 06/1813 | D103: 1 | E103: 6 | F103: 22 | G103: 27 | H103: {=_xlfn.LET(_xlpm.s,IFERROR(--F103,""),_xlpm.e,IFERROR(--G103,""),IF(OR(_xlpm.s="",_xlpm.e="",_xlpm.e<_xlpm.s),"",_xlfn.LET(_xlpm.p,_xlfn.SEQUENCE(_xlpm.e-_xlpm.s+1,1,_xlpm.s,1),SUM(1/COUNTIFS($D:$D,D103,$E:$E,E103,$F:$F,"<>N/A",$G:$G,"<>N/A",$F:$F,"<="&_xlpm.p,$G:$G,">="&_xlpm.p)))))} -> 5 | I103: Poesia | J103: Canção inedita de Bocage a Luiz de Vasconcellos e Souza, então Vice-Rei deste Estado. | K103: N/A | L103: N/A | M103: N/A | N103: N/A | O103: Local | P103: Brazil | Q103: Marked "inédita" (first publication) of a manuscript by Manuel Maria Barbosa du Bocage (1765-1805). | R103: FALSE
A104: OP1813s1v1 | B104: OP1813.1.1.6-103 | C104: 06/1813 | D104: 1 | E104: 6 | F104: 27 | G104: 27 | H104: {=_xlfn.LET(_xlpm.s,IFERROR(--F104,""),_xlpm.e,IFERROR(--G104,""),IF(OR(_xlpm.s="",_xlpm.e="",_xlpm.e<_xlpm.s),"",_xlfn.LET(_xlpm.p,_xlfn.SEQUENCE(_xlpm.e-_xlpm.s+1,1,_xlpm.s,1),SUM(1/COUNTIFS($D:$D,D104,$E:$E,E104,$F:$F,"<>N/A",$G:$G,"<>N/A",$F:$F,"<="&_xlpm.p,$G:$G,">="&_xlpm.p)))))} -> 0.5 | I104: Poesia | J104: Soneto do Desembargador Antonio Ribeiro dos Santos, ao Illustrissimo Francisco de Borja Garção Stockler. | K104: Antonio Ribeiro dos Santos | L104: N/A | M104: N/A | N104: N/A | O104: Local | P104: Brazil | R104: FALSE
A105: OP1813s1v1 | B105: OP1813.1.1.6-104 | C105: 06/1813 | D105: 1 | E105: 6 | F105: 28 | G105: 30 | H105: {=_xlfn.LET(_xlpm.s,IFERROR(--F105,""),_xlpm.e,IFERROR(--G105,""),IF(OR(_xlpm.s="",_xlpm.e="",_xlpm.e<_xlpm.s),"",_xlfn.LET(_xlpm.p,_xlfn.SEQUENCE(_xlpm.e-_xlpm.s+1,1,_xlpm.s,1),SUM(1/COUNTIFS($D:$D,D105,$E:$E,E105,$F:$F,"<>N/A",$G:$G,"<>N/A",$F:$F,"<="&_xlpm.p,$G:$G,">="&_xlpm.p)))))} -> 3 | I105: Poesia | J105: O Retrato de Armia. | K105: Elmano Bahiense | L105: N/A | M105: N/A | N105: N/A | O105: Local | P105: Brazil | Q105: Elmano Bahiense was a pseudonym of Manuel Ferreira de Araújo Guimarães, the journal's editor. | R105: FALSE
A106: OP1813s1v1 | B106: OP1813.1.1.6-105 | C106: 06/1813 | D106: 1 | E106: 6 | F106: 31 | G106: 43 | H106: {=_xlfn.LET(_xlpm.s,IFERROR(--F106,""),_xlpm.e,IFERROR(--G106,""),IF(OR(_xlpm.s="",_xlpm.e="",_xlpm.e<_xlpm.s),"",_xlfn.LET(_xlpm.p,_xlfn.SEQUENCE(_xlpm.e-_xlpm.s+1,1,_xlpm.s,1),SUM(1/COUNTIFS($D:$D,D106,$E:$E,E106,$F:$F,"<>N/A",$G:$G,"<>N/A",$F:$F,"<="&_xlpm.p,$G:$G,">="&_xlpm.p)))))} -> 13 | I106: Agricultura | J106: Cultura do Café. Segunda Parte. | K106: Domingos Borges de Barros | L106: N/A | M106: N/A | N106: Veloso, José Mariano da Conceição. O Fazendeiro do Brazil, ou Tratado das plantas usuais no Brasil. Tomo III, Parte II: “Bebidas alimentosas.” Lisbon: Officina de Simão Thaddeo Ferreira, 1799. | O106: Adaptation | P106: Portugal | Q106: Article condenses Veloso’s Portuguese treatment of coffee (itself based on European authorities like Sylvestre Dufour, Aublet, Rozier, and Laborie, ), following the same sequence of advice on harvest colour, avoiding early picking (incl. the Mauritius comparison), bean sorting, and not shaking branches, but the phrasing is recast; it is an Reuse (Adaptation)/summary. | R106: TRUE
...

Sheet 2. JSEL
A1: File | B1: ID | C1: Date | D1: Vol. | E1: Issue | F1: Start | G1: End | H1: Size | I1: Section | J1: Title | K1: AuthorhipAttribution | L1: SourceAttribution | M1: ProximateSourceIdentification | N1: Reference | O1: TextualProvenanceClassification | P1: ProximateSourceLocation | Q1: Notes | R1: Science
A2: JSEL1826s1v1n1 | B2: JSEL1826.1.1.1-1 | C2: 05/1826 | D2: 1 | E2: 1 | F2: N/A | G2: N/A | H2: 8 | I2: N/A | J2: Discurso preliminar. | K2: Redactores | L2: N/A | M2: N/A | N2: N/A | O2: Local | P2: Brazil | R2: FALSE
A3: JSEL1826s1v1n1 | B3: JSEL1826.1.1.1-2 | C3: 05/1826 | D3: 1 | E3: 1 | F3: 1 | G3: 6 | H3: {=_xlfn.LET(_xlpm.s,IFERROR(--F3,""),_xlpm.e,IFERROR(--G3,""),IF(OR(_xlpm.s="",_xlpm.e="",_xlpm.e<_xlpm.s),"",_xlfn.LET(_xlpm.p,_xlfn.SEQUENCE(_xlpm.e-_xlpm.s+1,1,_xlpm.s,1),SUM(1/COUNTIFS($D:$D,D3,$E:$E,E3,$F:$F,"<>N/A",$G:$G,"<>N/A",$F:$F,"<="&_xlpm.p,$G:$G,">="&_xlpm.p)))))} -> 6 | I3: Sciencias e Artes | J3: Theoria do universo. Ou da Causa primitiva do Movimento, e de seus principaes Effeitos. | K3: N/A | L3: N/A | M3: N/A | N3: Allix, J. A. F. Théorie de l’univers, ou, De la cause primitive du mouvement, et de ses principaux effets. 2nd ed. Paris: Mme Veuve Courcier, 1818. | O3: Reuse (Translation) | P3: France | Q3: Marked as a translation by the editor. | R3: TRUE
A4: JSEL1826s1v1n1 | B4: JSEL1826.1.1.1-3 | C4: 05/1826 | D4: 1 | E4: 1 | F4: 7 | G4: 20 | H4: {=_xlfn.LET(_xlpm.s,IFERROR(--F4,""),_xlpm.e,IFERROR(--G4,""),IF(OR(_xlpm.s="",_xlpm.e="",_xlpm.e<_xlpm.s),"",_xlfn.LET(_xlpm.p,_xlfn.SEQUENCE(_xlpm.e-_xlpm.s+1,1,_xlpm.s,1),SUM(1/COUNTIFS($D:$D,D4,$E:$E,E4,$F:$F,"<>N/A",$G:$G,"<>N/A",$F:$F,"<="&_xlpm.p,$G:$G,">="&_xlpm.p)))))} -> 14 | I4: Sciencias e Artes | J4: Ensaio sobre a origem dos corpos organisados, e inorganisados. Primeira parte. Da origem dos Corpos organisados. | K4: N/A | L4: N/A | M4: N/A | N4: Fray-Fournier, Jean-Baptiste. Essai sur l’origine des corps organisés et inorganisés, et sur quelques phénomènes de physiologie animale et végétale. Paris: Mme Ve Courcier, 1817. | O4: Reuse (Translation) | P4: France | R4: TRUE
A5: JSEL1826s1v1n1 | B5: JSEL1826.1.1.1-4 | C5: 05/1826 | D5: 1 | E5: 1 | F5: 21 | G5: 27 | H5: {=_xlfn.LET(_xlpm.s,IFERROR(--F5,""),_xlpm.e,IFERROR(--G5,""),IF(OR(_xlpm.s="",_xlpm.e="",_xlpm.e<_xlpm.s),"",_xlfn.LET(_xlpm.p,_xlfn.SEQUENCE(_xlpm.e-_xlpm.s+1,1,_xlpm.s,1),SUM(1/COUNTIFS($D:$D,D5,$E:$E,E5,$F:$F,"<>N/A",$G:$G,"<>N/A",$F:$F,"<="&_xlpm.p,$G:$G,">="&_xlpm.p)))))} -> 7 | I5: Sciencias e Artes | J5: Sobre o Commercio interior, Canaes, Estradas, Pontes, e Calçadas. | K5: N/A | L5: N/A | M5: N/A | N5: J. Cordier, Ponts et chaussées. Essais sur la construction des routes, des ponts suspendus, des barrages, etc., extraits de divers ouvrages anglais (Lille: Imprimerie de Reboux-Leroy, 1825), vi–lxxxiii. | O5: Adaptation | P5: France | R5: TRUE
A6: JSEL1826s1v1n1 | B6: JSEL1826.1.1.1-5 | C6: 05/1826 | D6: 1 | E6: 1 | F6: 28 | G6: 30 | H6: {=_xlfn.LET(_xlpm.s,IFERROR(--F6,""),_xlpm.e,IFERROR(--G6,""),IF(OR(_xlpm.s="",_xlpm.e="",_xlpm.e<_xlpm.s),"",_xlfn.LET(_xlpm.p,_xlfn.SEQUENCE(_xlpm.e-_xlpm.s+1,1,_xlpm.s,1),SUM(1/COUNTIFS($D:$D,D6,$E:$E,E6,$F:$F,"<>N/A",$G:$G,"<>N/A",$F:$F,"<="&_xlpm.p,$G:$G,">="&_xlpm.p)))))} -> 3 | I6: Sciencias e Artes | J6: Inventos Modernos. | K6: N/A | L6: N/A | M6: N/A | N6: N/A | O6: Local | P6: Brazil | R6: TRUE
A7: JSEL1826s1v1n1 | B7: JSEL1826.1.1.1-6 | C7: 05/1826 | D7: 1 | E7: 1 | F7: 31 | G7: 37 | H7: {=_xlfn.LET(_xlpm.s,IFERROR(--F7,""),_xlpm.e,IFERROR(--G7,""),IF(OR(_xlpm.s="",_xlpm.e="",_xlpm.e<_xlpm.s),"",_xlfn.LET(_xlpm.p,_xlfn.SEQUENCE(_xlpm.e-_xlpm.s+1,1,_xlpm.s,1),SUM(1/COUNTIFS($D:$D,D7,$E:$E,E7,$F:$F,"<>N/A",$G:$G,"<>N/A",$F:$F,"<="&_xlpm.p,$G:$G,">="&_xlpm.p)))))} -> 7 | I7: Sciencias e Artes | J7: Agricultura, e economia rural. | K7: Redactores | L7: N/A | M7: N/A | N7: Humphry Davy, Elements of Agricultural Chemistry, in a Course of Lectures for the Board of Agriculture, 2nd ed. (London: Longman, Hurst, Rees, Orme, and Brown; and A. Constable and Co., 1814), 4–9. | O7: Adaptation | P7: United Kingdom | R7: TRUE
A8: JSEL1826s1v1n1 | B8: JSEL1826.1.1.1-7 | C8: 05/1826 | D8: 1 | E8: 1 | F8: 38 | G8: 47 | H8: {=_xlfn.LET(_xlpm.s,IFERROR(--F8,""),_xlpm.e,IFERROR(--G8,""),IF(OR(_xlpm.s="",_xlpm.e="",_xlpm.e<_xlpm.s),"",_xlfn.LET(_xlpm.p,_xlfn.SEQUENCE(_xlpm.e-_xlpm.s+1,1,_xlpm.s,1),SUM(1/COUNTIFS($D:$D,D8,$E:$E,E8,$F:$F,"<>N/A",$G:$G,"<>N/A",$F:$F,"<="&_xlpm.p,$G:$G,">="&_xlpm.p)))))} -> 10 | I8: Sciencias e Artes | J8: Memoria dirigida da extincta Assemblea Geral e Constituinte do Imperio do Brasil, por hum dos Redactores deste Jornal, a qual foi remetida à Comissão de Agricultura. | K8: Redactores | L8: N/A | M8: N/A | N8: N/A | O8: Local | P8: Brazil | R8: TRUE
A9: JSEL1826s1v1n1 | B9: JSEL1826.1.1.1-8 | C9: 05/1826 | D9: 1 | E9: 1 | F9: 48 | G9: 48 | H9: {=_xlfn.LET(_xlpm.s,IFERROR(--F9,""),_xlpm.e,IFERROR(--G9,""),IF(OR(_xlpm.s="",_xlpm.e="",_xlpm.e<_xlpm.s),"",_xlfn.LET(_xlpm.p,_xlfn.SEQUENCE(_xlpm.e-_xlpm.s+1,1,_xlpm.s,1),SUM(1/COUNTIFS($D:$D,D9,$E:$E,E9,$F:$F,"<>N/A",$G:$G,"<>N/A",$F:$F,"<="&_xlpm.p,$G:$G,">="&_xlpm.p)))))} -> 1 | I9: Poesia e Bellas Artes | J9: A' futura prosperidade do Brasil. Soneto. Improvisado no Rio de Janeiro no Anno de 1812. | K9: N/A | L9: N/A | M9: N/A | N9: N/A | O9: Local | P9: Brazil | R9: FALSE
A10: JSEL1826s1v1n1 | B10: JSEL1826.1.1.1-9 | C10: 05/1826 | D10: 1 | E10: 1 | F10: 49 | G10: 57 | H10: {=_xlfn.LET(_xlpm.s,IFERROR(--F10,""),_xlpm.e,IFERROR(--G10,""),IF(OR(_xlpm.s="",_xlpm.e="",_xlpm.e<_xlpm.s),"",_xlfn.LET(_xlpm.p,_xlfn.SEQUENCE(_xlpm.e-_xlpm.s+1,1,_xlpm.s,1),SUM(1/COUNTIFS($D:$D,D10,$E:$E,E10,$F:$F,"<>N/A",$G:$G,"<>N/A",$F:$F,"<="&_xlpm.p,$G:$G,">="&_xlpm.p)))))} -> 8.3333333 | I10: Poesia e Bellas Artes | J10: Villa Rica. Poema em dez cantos. De Claudio Manoel da Costa, Arcade Ultramarino. | K10: Claudio Manoel da Costa | L10: N/A | M10: N/A | N10: N/A | O10: Local | P10: Brazil | R10: FALSE
A11: JSEL1826s1v1n1 | B11: JSEL1826.1.1.1-10 | C11: 05/1826 | D11: 1 | E11: 1 | F11: 57 | G11: 57 | H11: {=_xlfn.LET(_xlpm.s,IFERROR(--F11,""),_xlpm.e,IFERROR(--G11,""),IF(OR(_xlpm.s="",_xlpm.e="",_xlpm.e<_xlpm.s),"",_xlfn.LET(_xlpm.p,_xlfn.SEQUENCE(_xlpm.e-_xlpm.s+1,1,_xlpm.s,1),SUM(1/COUNTIFS($D:$D,D11,$E:$E,E11,$F:$F,"<>N/A",$G:$G,"<>N/A",$F:$F,"<="&_xlpm.p,$G:$G,">="&_xlpm.p)))))} -> 0.33333333 | I11: Poesia e Bellas Artes | J11: Fábula | K11: N/A | L11: N/A | M11: N/A | N11: N/A | O11: Local | P11: Brazil | R11: FALSE
A12: JSEL1826s1v1n1 | B12: JSEL1826.1.1.1-11 | C12: 05/1826 | D12: 1 | E12: 1 | F12: 57 | G12: 58 | H12: {=_xlfn.LET(_xlpm.s,IFERROR(--F12,""),_xlpm.e,IFERROR(--G12,""),IF(OR(_xlpm.s="",_xlpm.e="",_xlpm.e<_xlpm.s),"",_xlfn.LET(_xlpm.p,_xlfn.SEQUENCE(_xlpm.e-_xlpm.s+1,1,_xlpm.s,1),SUM(1/COUNTIFS($D:$D,D12,$E:$E,E12,$F:$F,"<>N/A",$G:$G,"<>N/A",$F:$F,"<="&_xlpm.p,$G:$G,">="&_xlpm.p)))))} -> 0.83333333 | I12: Poesia e Bellas Artes | J12: Pensamentos soltos. | K12: N/A | L12: N/A | M12: N/A | N12: N/A | O12: Local | P12: Brazil | R12: FALSE
A13: JSEL1826s1v1n1 | B13: JSEL1826.1.1.1-12 | C13: 05/1826 | D13: 1 | E13: 1 | F13: 58 | G13: 59 | H13: {=_xlfn.LET(_xlpm.s,IFERROR(--F13,""),_xlpm.e,IFERROR(--G13,""),IF(OR(_xlpm.s="",_xlpm.e="",_xlpm.e<_xlpm.s),"",_xlfn.LET(_xlpm.p,_xlfn.SEQUENCE(_xlpm.e-_xlpm.s+1,1,_xlpm.s,1),SUM(1/COUNTIFS($D:$D,D13,$E:$E,E13,$F:$F,"<>N/A",$G:$G,"<>N/A",$F:$F,"<="&_xlpm.p,$G:$G,">="&_xlpm.p)))))} -> 1.5 | I13: Poesia e Bellas Artes | J13: Sentenças, e maximas. | K13: N/A | L13: N/A | M13: N/A | N13: N/A | O13: Local | P13: Brazil | R13: FALSE
A14: JSEL1826s1v1n1 | B14: JSEL1826.1.1.1-13 | C14: 05/1826 | D14: 1 | E14: 1 | F14: 60 | G14: 67 | H14: {=_xlfn.LET(_xlpm.s,IFERROR(--F14,""),_xlpm.e,IFERROR(--G14,""),IF(OR(_xlpm.s="",_xlpm.e="",_xlpm.e<_xlpm.s),"",_xlfn.LET(_xlpm.p,_xlfn.SEQUENCE(_xlpm.e-_xlpm.s+1,1,_xlpm.s,1),SUM(1/COUNTIFS($D:$D,D14,$E:$E,E14,$F:$F,"<>N/A",$G:$G,"<>N/A",$F:$F,"<="&_xlpm.p,$G:$G,">="&_xlpm.p)))))} -> 8 | I14: Viagens | J14: Viagens. Viagem à roda do mundo pelos Russos. | K14: N/A | L14: N/A | M14: N/A | N14: Krusenstern, Adam Johann von. Voyage Round the World in the Years 1803, 1804, 1805, & 1806. Translated from the original German by Richard Belgrave Hoppner. 2 vols. London: John Murray, 1813. | O14: Reuse (Translation) | P14: United Kingdom | R14: FALSE
A15: JSEL1826s1v1n1 | B15: JSEL1826.1.1.1-14 | C15: 05/1826 | D15: 1 | E15: 1 | F15: 68 | G15: 80 | H15: {=_xlfn.LET(_xlpm.s,IFERROR(--F15,""),_xlpm.e,IFERROR(--G15,""),IF(OR(_xlpm.s="",_xlpm.e="",_xlpm.e<_xlpm.s),"",_xlfn.LET(_xlpm.p,_xlfn.SEQUENCE(_xlpm.e-_xlpm.s+1,1,_xlpm.s,1),SUM(1/COUNTIFS($D:$D,D15,$E:$E,E15,$F:$F,"<>N/A",$G:$G,"<>N/A",$F:$F,"<="&_xlpm.p,$G:$G,">="&_xlpm.p)))))} -> 13 | I15: Variedades | J15: Drama Racional. | K15: N/A | L15: N/A | M15: N/A | N15: Delisle de Sales, Jean-Baptiste-Claude. “Drame raisonnable (en un acte, avec des commentaires).” In De la philosophie de la nature, ou Traité de la morale pour le genre humain, vol. 4. London, 1804. | O15: Reuse (Translation) | P15: United Kingdom | R15: FALSE
... A18: JSEL1826s1v1n2 | B18: JSEL1826.1.1.2-17 | C18: 06/1826 | D18: 1 | E18: 2 | F18: 91 | G18: 100 | H18: {=_xlfn.LET(_xlpm.s,IFERROR(--F18,""),_xlpm.e,IFERROR(--G18,""),IF(OR(_xlpm.s="",_xlpm.e="",_xlpm.e<_xlpm.s),"",_xlfn.LET(_xlpm.p,_xlfn.SEQUENCE(_xlpm.e-_xlpm.s+1,1,_xlpm.s,1),SUM(1/COUNTIFS($D:$D,D18,$E:$E,E18,$F:$F,"<>N/A",$G:$G,"<>N/A",$F:$F,"<="&_xlpm.p,$G:$G,">="&_xlpm.p)))))} -> 10 | I18: Sciencias e Artes | J18: Sciencias e Artes. | K18: Redactores | L18: N/A | M18: N/A | N18: N/A | O18: Local | P18: Brazil | R18: TRUE
A19: JSEL1826s1v1n2 | B19: JSEL1826.1.1.2-18 | C19: 06/1826 | D19: 1 | E19: 2 | F19: 101 | G19: 110 | H19: {=_xlfn.LET(_xlpm.s,IFERROR(--F19,""),_xlpm.e,IFERROR(--G19,""),IF(OR(_xlpm.s="",_xlpm.e="",_xlpm.e<_xlpm.s),"",_xlfn.LET(_xlpm.p,_xlfn.SEQUENCE(_xlpm.e-_xlpm.s+1,1,_xlpm.s,1),SUM(1/COUNTIFS($D:$D,D19,$E:$E,E19,$F:$F,"<>N/A",$G:$G,"<>N/A",$F:$F,"<="&_xlpm.p,$G:$G,">="&_xlpm.p)))))} -> 9.5 | I19: Sciencias e Artes | J19: Theoria do universo. Ou da Causa primitiva do Movimento, e de seus principaes Effeitos. (Continuada da Pag. 6 do 1.º N.º). Capítulo I. Do Calorico. | K19: N/A | L19: N/A | M19: N/A | N19: Allix, J. A. F. Théorie de l’univers, ou, De la cause primitive du mouvement, et de ses principaux effets. 2nd ed. Paris: Mme Veuve Courcier, 1818. | O19: Reuse (Translation) | P19: France | Q19: Marked as a translation by the editor. | R19: TRUE
A20: JSEL1826s1v1n2 | B20: JSEL1826.1.1.2-19 | C20: 06/1826 | D20: 1 | E20: 2 | F20: 110 | G20: 116 | H20: {=_xlfn.LET(_xlpm.s,IFERROR(--F20,""),_xlpm.e,IFERROR(--G20,""),IF(OR(_xlpm.s="",_xlpm.e="",_xlpm.e<_xlpm.s),"",_xlfn.LET(_xlpm.p,_xlfn.SEQUENCE(_xlpm.e-_xlpm.s+1,1,_xlpm.s,1),SUM(1/COUNTIFS($D:$D,D20,$E:$E,E20,$F:$F,"<>N/A",$G:$G,"<>N/A",$F:$F,"<="&_xlpm.p,$G:$G,">="&_xlpm.p)))))} -> 6.5 | I20: Sciencias e Artes | J20: Ensaio sobre a origem dos corpos organisados, e inorganisados. (Continuado da Pag. 20.) | K20: N/A | L20: N/A | M20: N/A | N20: Fray-Fournier, Jean-Baptiste. Essai sur l’origine des corps organisés et inorganisés, et sur quelques phénomènes de physiologie animale et végétale. Paris: Mme Ve Courcier, 1817. | O20: Reuse (Translation) | P20: France | R20: TRUE
A21: JSEL1826s1v1n2 | B21: JSEL1826.1.1.2-20 | C21: 06/1826 | D21: 1 | E21: 2 | F21: 117 | G21: 132 | H21: {=_xlfn.LET(_xlpm.s,IFERROR(--F21,""),_xlpm.e,IFERROR(--G21,""),IF(OR(_xlpm.s="",_xlpm.e="",_xlpm.e<_xlpm.s),"",_xlfn.LET(_xlpm.p,_xlfn.SEQUENCE(_xlpm.e-_xlpm.s+1,1,_xlpm.s,1),SUM(1/COUNTIFS($D:$D,D21,$E:$E,E21,$F:$F,"<>N/A",$G:$G,"<>N/A",$F:$F,"<="&_xlpm.p,$G:$G,">="&_xlpm.p)))))} -> 16 | I21: Sciencias e Artes | J21: Mineralogia. Memoria Historica e Topografica sobre a Descoberta das Minas de Ferro de Sorocaba, na Provincia de S. Paulo; e sobre as vantagens, que o Brasil póde obter da continuação do seu Descobrimento e progressos, e do importante e urgente estabelecimento de Fabricas de Ferro de que mui essencialmente depende a sua futura prosperidade. | K21: N/A | L21: N/A | M21: N/A | N21: N/A | O21: Local | P21: Brazil | R21: TRUE
A22: JSEL1826s1v1n2 | B22: JSEL1826.1.1.2-21 | C22: 06/1826 | D22: 1 | E22: 2 | F22: 133 | G22: 136 | H22: {=_xlfn.LET(_xlpm.s,IFERROR(--F22,""),_xlpm.e,IFERROR(--G22,""),IF(OR(_xlpm.s="",_xlpm.e="",_xlpm.e<_xlpm.s),"",_xlfn.LET(_xlpm.p,_xlfn.SEQUENCE(_xlpm.e-_xlpm.s+1,1,_xlpm.s,1),SUM(1/COUNTIFS($D:$D,D22,$E:$E,E22,$F:$F,"<>N/A",$G:$G,"<>N/A",$F:$F,"<="&_xlpm.p,$G:$G,">="&_xlpm.p)))))} -> 3.5 | I22: Sciencias e Artes | J22: Estradas, Pontes, Calçadas, e caminhos de ferro. (Artigo continuado de pag. 27 do 1.º N.º). | K22: Redactores | L22: N/A | M22: N/A | N22: J. Cordier, Ponts et chaussées. Essais sur la construction des routes, des ponts suspendus, des barrages, etc., extraits de divers ouvrages anglais (Lille: Imprimerie de Reboux-Leroy, 1825), 445–448. | O22: Reuse (Translation) | P22: France | R22: TRUE
A23: JSEL1826s1v1n2 | B23: JSEL1826.1.1.2-22 | C23: 06/1826 | D23: 1 | E23: 2 | F23: 136 | G23: 140 | H23: {=_xlfn.LET(_xlpm.s,IFERROR(--F23,""),_xlpm.e,IFERROR(--G23,""),IF(OR(_xlpm.s="",_xlpm.e="",_xlpm.e<_xlpm.s),"",_xlfn.LET(_xlpm.p,_xlfn.SEQUENCE(_xlpm.e-_xlpm.s+1,1,_xlpm.s,1),SUM(1/COUNTIFS($D:$D,D23,$E:$E,E23,$F:$F,"<>N/A",$G:$G,"<>N/A",$F:$F,"<="&_xlpm.p,$G:$G,">="&_xlpm.p)))))} -> 4.5 | I23: Sciencias e Artes | J23: Instrucçoens publicadas por ordem do Parlamento para a reparação das estradas aos Commissarios e Engenheiros encarregados do seu entretenimento. | K23: N/A | L23: N/A | M23: N/A | N23: Great Britain. Parliament. Commissioners for the Improvement of the Mail Coach Roads. General Rules for Repairing Roads, Recommended, by the Parliamentary Commissioners for the Improvement of the Mail Coach Road from London, by Coventry, to Holyhead, to the Turnpike Trustees between London and Shrewsbury. Illustrated with a Plate. 4th ed. London: J. Taylor, 1823. | O23: Reuse (Translation) | P23: United Kingdom | R23: TRUE
A24: JSEL1826s1v1n2 | B24: JSEL1826.1.1.2-23 | C24: 06/1826 | D24: 1 | E24: 2 | F24: 141 | G24: 146 | H24: {=_xlfn.LET(_xlpm.s,IFERROR(--F24,""),_xlpm.e,IFERROR(--G24,""),IF(OR(_xlpm.s="",_xlpm.e="",_xlpm.e<_xlpm.s),"",_xlfn.LET(_xlpm.p,_xlfn.SEQUENCE(_xlpm.e-_xlpm.s+1,1,_xlpm.s,1),SUM(1/COUNTIFS($D:$D,D24,$E:$E,E24,$F:$F,"<>N/A",$G:$G,"<>N/A",$F:$F,"<="&_xlpm.p,$G:$G,">="&_xlpm.p)))))} -> 6 | I24: Sciencias e Artes | J24: Chimica Agricola. Continuação da Lição Primeira, seguida da pag. 37. (sobre a idéa geral dos objectos do curso, e da ordem pela qual elles serão tratados.) | K24: N/A | L24: N/A | M24: N/A | N24: Davy, Humphry. Elements of Agricultural Chemistry, in a Course of Lectures for the Board of Agriculture. 2nd ed. London: Longman, Hurst, Rees, Orme, and Brown, 1814. | O24: Reuse (Translation) | P24: United Kingdom | R24: TRUE
A25: JSEL1826s1v1n2 | B25: JSEL1826.1.1.2-24 | C25: 06/1826 | D25: 1 | E25: 2 | F25: 147 | G25: 148 | H25: {=_xlfn.LET(_xlpm.s,IFERROR(--F25,""),_xlpm.e,IFERROR(--G25,""),IF(OR(_xlpm.s="",_xlpm.e="",_xlpm.e<_xlpm.s),"",_xlfn.LET(_xlpm.p,_xlfn.SEQUENCE(_xlpm.e-_xlpm.s+1,1,_xlpm.s,1),SUM(1/COUNTIFS($D:$D,D25,$E:$E,E25,$F:$F,"<>N/A",$G:$G,"<>N/A",$F:$F,"<="&_xlpm.p,$G:$G,">="&_xlpm.p)))))} -> 2 | I25: Poesia e Bellas Artes | J25: Soneto. | K25: Redactores | L25: N/A | M25: N/A | N25: N/A | O25: Local | P25: Brazil | R25: FALSE
A26: JSEL1826s1v1n2 | B26: JSEL1826.1.1.2-25 | C26: 06/1826 | D26: 1 | E26: 2 | F26: 149 | G26: 150 | H26: {=_xlfn.LET(_xlpm.s,IFERROR(--F26,""),_xlpm.e,IFERROR(--G26,""),IF(OR(_xlpm.s="",_xlpm.e="",_xlpm.e<_xlpm.s),"",_xlfn.LET(_xlpm.p,_xlfn.SEQUENCE(_xlpm.e-_xlpm.s+1,1,_xlpm.s,1),SUM(1/COUNTIFS($D:$D,D26,$E:$E,E26,$F:$F,"<>N/A",$G:$G,"<>N/A",$F:$F,"<="&_xlpm.p,$G:$G,">="&_xlpm.p)))))} -> 1.5 | I26: Poesia e Bellas Artes | J26: Epigrammas. | K26: N/A | L26: N/A | M26: N/A | N26: N/A | O26: Local | P26: Brazil | R26: FALSE
A27: JSEL1826s1v1n2 | B27: JSEL1826.1.1.2-26 | C27: 06/1826 | D27: 1 | E27: 2 | F27: 150 | G27: 150 | H27: {=_xlfn.LET(_xlpm.s,IFERROR(--F27,""),_xlpm.e,IFERROR(--G27,""),IF(OR(_xlpm.s="",_xlpm.e="",_xlpm.e<_xlpm.s),"",_xlfn.LET(_xlpm.p,_xlfn.SEQUENCE(_xlpm.e-_xlpm.s+1,1,_xlpm.s,1),SUM(1/COUNTIFS($D:$D,D27,$E:$E,E27,$F:$F,"<>N/A",$G:$G,"<>N/A",$F:$F,"<="&_xlpm.p,$G:$G,">="&_xlpm.p)))))} -> 0.5 | I27: Poesia e Bellas Artes | J27: Pensamentos soltos. | K27: N/A | L27: N/A | M27: N/A | N27: N/A | O27: Local | P27: Brazil | R27: FALSE
A28: JSEL1826s1v1n2 | B28: JSEL1826.1.1.2-27 | C28: 06/1826 | D28: 1 | E28: 2 | F28: 151 | G28: 162 | H28: {=_xlfn.LET(_xlpm.s,IFERROR(--F28,""),_xlpm.e,IFERROR(--G28,""),IF(OR(_xlpm.s="",_xlpm.e="",_xlpm.e<_xlpm.s),"",_xlfn.LET(_xlpm.p,_xlfn.SEQUENCE(_xlpm.e-_xlpm.s+1,1,_xlpm.s,1),SUM(1/COUNTIFS($D:$D,D28,$E:$E,E28,$F:$F,"<>N/A",$G:$G,"<>N/A",$F:$F,"<="&_xlpm.p,$G:$G,">="&_xlpm.p)))))} -> 11.5 | I28: Poesia e Bellas Artes | J28: Villa Rica. Poema. Canto II. | K28: Claudio Manoel da Costa | L28: N/A | M28: N/A | N28: N/A | O28: Local | P28: Brazil | R28: FALSE
A29: JSEL1826s1v1n2 | B29: JSEL1826.1.1.2-28 | C29: 06/1826 | D29: 1 | E29: 2 | F29: 162 | G29: 162 | H29: {=_xlfn.LET(_xlpm.s,IFERROR(--F29,""),_xlpm.e,IFERROR(--G29,""),IF(OR(_xlpm.s="",_xlpm.e="",_xlpm.e<_xlpm.s),"",_xlfn.LET(_xlpm.p,_xlfn.SEQUENCE(_xlpm.e-_xlpm.s+1,1,_xlpm.s,1),SUM(1/COUNTIFS($D:$D,D29,$E:$E,E29,$F:$F,"<>N/A",$G:$G,"<>N/A",$F:$F,"<="&_xlpm.p,$G:$G,">="&_xlpm.p)))))} -> 0.5 | I29: Poesia e Bellas Artes | J29: Pensamento Filososico. | K29: N/A | L29: N/A | M29: N/A | N29: N/A | O29: Local | P29: Brazil | R29: FALSE
A30: JSEL1826s1v1n2 | B30: JSEL1826.1.1.2-29 | C30: 06/1826 | D30: 1 | E30: 2 | F30: 163 | G30: 165 | H30: {=_xlfn.LET(_xlpm.s,IFERROR(--F30,""),_xlpm.e,IFERROR(--G30,""),IF(OR(_xlpm.s="",_xlpm.e="",_xlpm.e<_xlpm.s),"",_xlfn.LET(_xlpm.p,_xlfn.SEQUENCE(_xlpm.e-_xlpm.s+1,1,_xlpm.s,1),SUM(1/COUNTIFS($D:$D,D30,$E:$E,E30,$F:$F,"<>N/A",$G:$G,"<>N/A",$F:$F,"<="&_xlpm.p,$G:$G,">="&_xlpm.p)))))} -> 3 | I30: Viagens | J30: Viagem à roda do mundo. (Continuada de pag. 67 do 1.º N.º) | K30: N/A | L30: N/A | M30: N/A | N30: Krusenstern, Adam Johann von. Voyage Round the World in the Years 1803, 1804, 1805, & 1806. Translated from the original German by Richard Belgrave Hoppner. 2 vols. London: John Murray, 1813. | O30: Reuse (Translation) | P30: United Kingdom | R30: FALSE
A31: JSEL1826s1v1n2 | B31: JSEL1826.1.1.2-30 | C31: 06/1826 | D31: 1 | E31: 2 | F31: 166 | G31: 170 | H31: {=_xlfn.LET(_xlpm.s,IFERROR(--F31,""),_xlpm.e,IFERROR(--G31,""),IF(OR(_xlpm.s="",_xlpm.e="",_xlpm.e<_xlpm.s),"",_xlfn.LET(_xlpm.p,_xlfn.SEQUENCE(_xlpm.e-_xlpm.s+1,1,_xlpm.s,1),SUM(1/COUNTIFS($D:$D,D31,$E:$E,E31,$F:$F,"<>N/A",$G:$G,"<>N/A",$F:$F,"<="&_xlpm.p,$G:$G,">="&_xlpm.p)))))} -> 5 | I31: Viagens | J31: Viagem à Pensilvania. Prisão da Filadelfia; seu estabelecimento, e regimen. | K31: N/A | L31: N/A | M31: N/A | N31: La Rochefoucauld-Liancourt, François-Alexandre-Frédéric, duc de. Des prisons de Philadelphie. Par un Européen. Philadelphia: Moreau de Saint-Méry, 1796. | O31: Reuse (Translation) | P31: United States of America | R31: FALSE
... A48: JSEL1826s1v1n3 | B48: JSEL1826.1.1.3-47 | C48: 07/1826 | D48: 1 | E48: 3 | F48: 269 | G48: 274 | H48: {=_xlfn.LET(_xlpm.s,IFERROR(--F48,""),_xlpm.e,IFERROR(--G48,""),IF(OR(_xlpm.s="",_xlpm.e="",_xlpm.e<_xlpm.s),"",_xlfn.LET(_xlpm.p,_xlfn.SEQUENCE(_xlpm.e-_xlpm.s+1,1,_xlpm.s,1),SUM(1/COUNTIFS($D:$D,D48,$E:$E,E48,$F:$F,"<>N/A",$G:$G,"<>N/A",$F:$F,"<="&_xlpm.p,$G:$G,">="&_xlpm.p)))))} -> 5.5 | I48: Variedades | J48: Memorial, de que havemos feito menção, e que não foi attendido. | K48: N/A | L48: N/A | M48: N/A | N48: N/A | O48: Local | P48: Brazil | R48: FALSE

Sheet 3. PSM
A1: File | B1: ID | C1: Date | D1: Vol. | E1: Issue | F1: Start | G1: End | H1: Size | I1: Section | J1: Title | K1: AuthorhipAttribution | L1: SourceAttribution | M1: ProximateSourceIdentification | N1: Reference | O1: TextualProvenanceClassification | P1: ProximateSourceLocation | Q1: Notes | R1: Science
A2: PSM1827s1v1 | B2: PSM1827.1.1.1-1 | C2: 01/1827 | D2: 1 | E2: 1 | F2: 5 | G2: 9 | H2: {=_xlfn.LET(_xlpm.s,IFERROR(--F2,""),_xlpm.e,IFERROR(--G2,""),IF(OR(_xlpm.s="",_xlpm.e="",_xlpm.e<_xlpm.s),"",_xlfn.LET(_xlpm.p,_xlfn.SEQUENCE(_xlpm.e-_xlpm.s+1,1,_xlpm.s,1),SUM(1/COUNTIFS($D:$D,D2,$E:$E,E2,$F:$F,"<>N/A",$G:$G,"<>N/A",$F:$F,"<="&_xlpm.p,$G:$G,">="&_xlpm.p)))))} -> 4.5 | I2: N/A | J2: Introducção | K2: José Francisco Sigaud | L2: N/A | M2: N/A | N2: N/A | O2: Local | P2: Brazil | R2: TRUE
A3: PSM1827s1v1 | B3: PSM1827.1.1.1-2 | C3: 01/1827 | D3: 1 | E3: 1 | F3: 9 | G3: 39 | H3: {=_xlfn.LET(_xlpm.s,IFERROR(--F3,""),_xlpm.e,IFERROR(--G3,""),IF(OR(_xlpm.s="",_xlpm.e="",_xlpm.e<_xlpm.s),"",_xlfn.LET(_xlpm.p,_xlfn.SEQUENCE(_xlpm.e-_xlpm.s+1,1,_xlpm.s,1),SUM(1/COUNTIFS($D:$D,D3,$E:$E,E3,$F:$F,"<>N/A",$G:$G,"<>N/A",$F:$F,"<="&_xlpm.p,$G:$G,">="&_xlpm.p)))))} -> 30 | I3: Medicina | J3: Primeira memoria sobre as allucinações dos sentidos; por M. Bayle. | K3: N/A | L3: N/A | M3: RMFE1825s1v1 | N3: Antoine-Laurent-Jessé Bayle, "Sur les Hallucinations des sens," Revue Médicale Française et Etrangère (Paris) 1, no. 1 (1825): 31–53. | O3: Reuse (Translation) | P3: France | R3: TRUE
A4: PSM1827s1v1 | B4: PSM1827.1.1.1-3 | C4: 01/1827 | D4: 1 | E4: 1 | F4: 39 | G4: 51 | H4: {=_xlfn.LET(_xlpm.s,IFERROR(--F4,""),_xlpm.e,IFERROR(--G4,""),IF(OR(_xlpm.s="",_xlpm.e="",_xlpm.e<_xlpm.s),"",_xlfn.LET(_xlpm.p,_xlfn.SEQUENCE(_xlpm.e-_xlpm.s+1,1,_xlpm.s,1),SUM(1/COUNTIFS($D:$D,D4,$E:$E,E4,$F:$F,"<>N/A",$G:$G,"<>N/A",$F:$F,"<="&_xlpm.p,$G:$G,">="&_xlpm.p)))))} -> 12 | I4: Medicina | J4: Observações sobre as funcções dos orgãos digestivos. | K4: M. F. Lallemand | L4: N/A | M4: NJM1818s1v2 | N4: Claude François Lallemand, “Observations pathologiques propres à éclairer plusieurs points de physiologie: Observations sur les fonctions des organes digestifs (‘Sur le vomissement’).” Nouveau Journal de Médecine, Chirurgie, Pharmacie, etc. (Paris) 2 (1818): 338–344. | O4: Reuse (Translation) | P4: France | R4: TRUE
A5: PSM1827s1v1 | B5: PSM1827.1.1.1-4 | C5: 01/1827 | D5: 1 | E5: 1 | F5: 51 | G5: 57 | H5: {=_xlfn.LET(_xlpm.s,IFERROR(--F5,""),_xlpm.e,IFERROR(--G5,""),IF(OR(_xlpm.s="",_xlpm.e="",_xlpm.e<_xlpm.s),"",_xlfn.LET(_xlpm.p,_xlfn.SEQUENCE(_xlpm.e-_xlpm.s+1,1,_xlpm.s,1),SUM(1/COUNTIFS($D:$D,D5,$E:$E,E5,$F:$F,"<>N/A",$G:$G,"<>N/A",$F:$F,"<="&_xlpm.p,$G:$G,">="&_xlpm.p)))))} -> 6.5 | I5: Medicina | J5: Observações sobre as vantagens e o emprego dos purgantes em muitas molestias; por James Hamilton, Doutor em Medicina em Edimburgo: traduzidas do Inglez e da 7.ª edic., por A. Lafisse, Medico em Paris. Hum vol. in-8º de 250 pag. Paris, 1825. | K5: N/A | L5: N/A | M5: N/A | N5: N/A | O5: Local | P5: Brazil | R5: TRUE
A6: PSM1827s1v1 | B6: PSM1827.1.1.1-5 | C6: 01/1827 | D6: 1 | E6: 1 | F6: 58 | G6: 61 | H6: {=_xlfn.LET(_xlpm.s,IFERROR(--F6,""),_xlpm.e,IFERROR(--G6,""),IF(OR(_xlpm.s="",_xlpm.e="",_xlpm.e<_xlpm.s),"",_xlfn.LET(_xlpm.p,_xlfn.SEQUENCE(_xlpm.e-_xlpm.s+1,1,_xlpm.s,1),SUM(1/COUNTIFS($D:$D,D6,$E:$E,E6,$F:$F,"<>N/A",$G:$G,"<>N/A",$F:$F,"<="&_xlpm.p,$G:$G,">="&_xlpm.p)))))} -> 3.5 | I6: Medicina | J6: Observações sobre a inflammação da membrana mucosa, que forra os seios frontaes. | K6: E. L. Pereyra, D. M. P. | L6: N/A | M6: JMG1825s1v3 | N6: E. L. Pereyra. "Observations sur l'inflammation de la membrane muqueuse qui tapisse les sinusfrontaux." Journal médical de la Gironde (Bordeaux) 3 (1825): 454–457. | O6: Reuse (Translation) | P6: France | R6: TRUE
A7: PSM1827s1v1 | B7: PSM1827.1.1.1-6 | C7: 01/1827 | D7: 1 | E7: 1 | F7: 61 | G7: 78 | H7: {=_xlfn.LET(_xlpm.s,IFERROR(--F7,""),_xlpm.e,IFERROR(--G7,""),IF(OR(_xlpm.s="",_xlpm.e="",_xlpm.e<_xlpm.s),"",_xlfn.LET(_xlpm.p,_xlfn.SEQUENCE(_xlpm.e-_xlpm.s+1,1,_xlpm.s,1),SUM(1/COUNTIFS($D:$D,D7,$E:$E,E7,$F:$F,"<>N/A",$G:$G,"<>N/A",$F:$F,"<="&_xlpm.p,$G:$G,">="&_xlpm.p)))))} -> 17 | I7: Medicina | J7: Historia da ultima enfermidade do General Foy. Hypertrophia do coração, seguida de aneurisma deste orgão com dilatação; phlegmasia e ulcerações da crossa da aorta; gastro-duodenite; estado gorduroso do fígado, e alteração do rim esquerdo. | K7: Victour Broussais | L7: N/A | M7: AMP1826s1v9 | N7: “Histoire de la maladie du général Foy; …” Annales de la médecine physiologique (Paris) 9 (1826): 20–41. | O7: Reuse (Translation) | P7: France | R7: TRUE
A8: PSM1827s1v1 | B8: PSM1827.1.1.1-7 | C8: 01/1827 | D8: 1 | E8: 1 | F8: 78 | G8: 81 | H8: {=_xlfn.LET(_xlpm.s,IFERROR(--F8,""),_xlpm.e,IFERROR(--G8,""),IF(OR(_xlpm.s="",_xlpm.e="",_xlpm.e<_xlpm.s),"",_xlfn.LET(_xlpm.p,_xlfn.SEQUENCE(_xlpm.e-_xlpm.s+1,1,_xlpm.s,1),SUM(1/COUNTIFS($D:$D,D8,$E:$E,E8,$F:$F,"<>N/A",$G:$G,"<>N/A",$F:$F,"<="&_xlpm.p,$G:$G,">="&_xlpm.p)))))} -> 3 | I8: Medicina | J8: Tratamento das molestias escrofulosas por M. Dupuytren, Professor de Medecina Operatoria da Escola de Medicina de Paris, etc. | K8: N/A | L8: N/A | M8: JGMCP1825s2v29-30 | N8: "Formulaire pratique des hôpitaux civils de Paris ; par M. Ratier, D. M. ( II . Édition revue et considérablement augmentée. 1825. Chez Baillière.)" Journal Général de Médecine, de Chirurgie et de Pharmacie (Paris) 30 (April 1825): 280–282. | O8: Reuse (Translation) | P8: France | R8: TRUE
A9: PSM1827s1v1 | B9: PSM1827.1.1.1-8 | C9: 01/1827 | D9: 1 | E9: 1 | F9: 81 | G9: 85 | H9: {=_xlfn.LET(_xlpm.s,IFERROR(--F9,""),_xlpm.e,IFERROR(--G9,""),IF(OR(_xlpm.s="",_xlpm.e="",_xlpm.e<_xlpm.s),"",_xlfn.LET(_xlpm.p,_xlfn.SEQUENCE(_xlpm.e-_xlpm.s+1,1,_xlpm.s,1),SUM(1/COUNTIFS($D:$D,D9,$E:$E,E9,$F:$F,"<>N/A",$G:$G,"<>N/A",$F:$F,"<="&_xlpm.p,$G:$G,">="&_xlpm.p)))))} -> 4.5 | I9: Medicina | J9: Tratamento da Blennorrhagia Syphilitica. | K9: N/A | L9: N/A | M9: N/A | N9: N/A | O9: Local | P9: Brazil | R9: TRUE
A10: PSM1827s1v1 | B10: PSM1827.1.1.1-9 | C10: 01/1827 | D10: 1 | E10: 1 | F10: 86 | G10: 91 | H10: {=_xlfn.LET(_xlpm.s,IFERROR(--F10,""),_xlpm.e,IFERROR(--G10,""),IF(OR(_xlpm.s="",_xlpm.e="",_xlpm.e<_xlpm.s),"",_xlfn.LET(_xlpm.p,_xlfn.SEQUENCE(_xlpm.e-_xlpm.s+1,1,_xlpm.s,1),SUM(1/COUNTIFS($D:$D,D10,$E:$E,E10,$F:$F,"<>N/A",$G:$G,"<>N/A",$F:$F,"<="&_xlpm.p,$G:$G,">="&_xlpm.p)))))} -> 5.5 | I10: Medicina | J10: Reflexões sobre a administração do Sulfato de Quinina. | K10: J. F. Tavares | L10: N/A | M10: N/A | N10: N/A | O10: Local | P10: Brazil | R10: TRUE
A11: PSM1827s1v1 | B11: PSM1827.1.1.1-10 | C11: 01/1827 | D11: 1 | E11: 1 | F11: 91 | G11: 103 | H11: {=_xlfn.LET(_xlpm.s,IFERROR(--F11,""),_xlpm.e,IFERROR(--G11,""),IF(OR(_xlpm.s="",_xlpm.e="",_xlpm.e<_xlpm.s),"",_xlfn.LET(_xlpm.p,_xlfn.SEQUENCE(_xlpm.e-_xlpm.s+1,1,_xlpm.s,1),SUM(1/COUNTIFS($D:$D,D11,$E:$E,E11,$F:$F,"<>N/A",$G:$G,"<>N/A",$F:$F,"<="&_xlpm.p,$G:$G,">="&_xlpm.p)))))} -> 12 | I11: Cirurgia | J11: Observações sobre as molestias dos orgãos genito-urinarios, por M. F. Lallemand, Professor de Clinica cirurgica etc. Primeira Parte – Estreitamentos da urethra. | K11: N/A | L11: N/A | M11: JMG1825s1v4 | N11: Burguet. "Observations sur les maladies des organes génito-urinaires; par M. F. Lallemand, prof. de clinique chirurgicale à la Faculté de med. de Montpellier. Premérie Partie : Des rétrécissemens de l'urètre. — Un vol. in-8°. de iij-22o pag. Paris, 1825 (i)." Journal médical de la Gironde (Bordeaux) 4 (1825): 255–264. | O11: Reuse (Translation) | P11: France | R11: TRUE
A12: PSM1827s1v1 | B12: PSM1827.1.1.1-11 | C12: 01/1827 | D12: 1 | E12: 1 | F12: 103 | G12: 105 | H12: {=_xlfn.LET(_xlpm.s,IFERROR(--F12,""),_xlpm.e,IFERROR(--G12,""),IF(OR(_xlpm.s="",_xlpm.e="",_xlpm.e<_xlpm.s),"",_xlfn.LET(_xlpm.p,_xlfn.SEQUENCE(_xlpm.e-_xlpm.s+1,1,_xlpm.s,1),SUM(1/COUNTIFS($D:$D,D12,$E:$E,E12,$F:$F,"<>N/A",$G:$G,"<>N/A",$F:$F,"<="&_xlpm.p,$G:$G,">="&_xlpm.p)))))} -> 2.5 | I12: Cirurgia | J12: Aneurisma da arteria axillar curado pela ligadura da subclavia; por Henrique Blacke-Gibbs D. M. | K12: Henrique Blacke-Gibbs | L12: N/A | M12: AGM1825s1v8 | N12: Harry Laeke Gibbs, "Anévrysme de l'artère axillaire guéri par la ligature de la sous-clavière." Archives générales de médecine (Paris) 8 (August 1825): 595–600. | O12: Reuse (Translation) | P12: France | R12: TRUE
A13: PSM1827s1v1 | B13: PSM1827.1.1.1-12 | C13: 01/1827 | D13: 1 | E13: 1 | F13: 106 | G13: 113 | H13: {=_xlfn.LET(_xlpm.s,IFERROR(--F13,""),_xlpm.e,IFERROR(--G13,""),IF(OR(_xlpm.s="",_xlpm.e="",_xlpm.e<_xlpm.s),"",_xlfn.LET(_xlpm.p,_xlfn.SEQUENCE(_xlpm.e-_xlpm.s+1,1,_xlpm.s,1),SUM(1/COUNTIFS($D:$D,D13,$E:$E,E13,$F:$F,"<>N/A",$G:$G,"<>N/A",$F:$F,"<="&_xlpm.p,$G:$G,">="&_xlpm.p)))))} -> 7.5 | I13: Cirurgia | J13: Observação sobre o entupimento das fossas nasaes. | K13: J. F. Tavares | L13: N/A | M13: N/A | N13: N/A | O13: Local | P13: Brazil | R13: TRUE
... A19: PSM1827s1v1 | B19: PSM1827.1.1.1-18 | C19: 01/1827 | D19: 1 | E19: 1 | F19: 118 | G19: 119 | H19: {=_xlfn.LET(_xlpm.s,IFERROR(--F19,""),_xlpm.e,IFERROR(--G19,""),IF(OR(_xlpm.s="",_xlpm.e="",_xlpm.e<_xlpm.s),"",_xlfn.LET(_xlpm.p,_xlfn.SEQUENCE(_xlpm.e-_xlpm.s+1,1,_xlpm.s,1),SUM(1/COUNTIFS($D:$D,D19,$E:$E,E19,$F:$F,"<>N/A",$G:$G,"<>N/A",$F:$F,"<="&_xlpm.p,$G:$G,">="&_xlpm.p)))))} -> 0.66666667 | I19: Pharmacia | J19: Novo methodo de fazer o acetato d'ammoniaco. | K19: N/A | L19: Jornal de Pharmacia de Paris | M19: JPSA1824s1v10 | N19: Jéromel. “Acétate d’ammoniaque liquide.” Journal de pharmacie et des sciences accessoires (Paris) 10 (1824): 69. | O19: Adaptation | P19: France | R19: TRUE
A20: PSM1827s1v1 | B20: PSM1827.1.1.1-19 | C20: 01/1827 | D20: 1 | E20: 1 | F20: 118 | G20: 119 | H20: {=_xlfn.LET(_xlpm.s,IFERROR(--F20,""),_xlpm.e,IFERROR(--G20,""),IF(OR(_xlpm.s="",_xlpm.e="",_xlpm.e<_xlpm.s),"",_xlfn.LET(_xlpm.p,_xlfn.SEQUENCE(_xlpm.e-_xlpm.s+1,1,_xlpm.s,1),SUM(1/COUNTIFS($D:$D,D20,$E:$E,E20,$F:$F,"<>N/A",$G:$G,"<>N/A",$F:$F,"<="&_xlpm.p,$G:$G,">="&_xlpm.p)))))} -> 0.66666667 | I20: Pharmacia | J20: Novo meio de descorar os assucares e os xaropes. | K20: N/A | L20: N/A | M20: N/A | N20: N/A | O20: Adaptation | P20: France | Q20: This is a short practical decolourising “recipe” (sugar/syrup clarification) that is most plausibly a translated extract from French applied-chemistry or pharmacy literature, because it mirrors the characteristic French technical register and vocabulary of the period around noir/charbon animal and alumina used to remove colour from sugar products, a well documented French discourse in works like Payen’s 1822 treatise on animal charcoal in sugar refining and contemporary French compilations that explicitly recommend mixtures of noir animal and alumine to whiten syrups. | R20: TRUE
A21: PSM1827s1v1 | B21: PSM1827.1.1.1-20 | C21: 01/1827 | D21: 1 | E21: 1 | F21: 119 | G21: 120 | H21: {=_xlfn.LET(_xlpm.s,IFERROR(--F21,""),_xlpm.e,IFERROR(--G21,""),IF(OR(_xlpm.s="",_xlpm.e="",_xlpm.e<_xlpm.s),"",_xlfn.LET(_xlpm.p,_xlfn.SEQUENCE(_xlpm.e-_xlpm.s+1,1,_xlpm.s,1),SUM(1/COUNTIFS($D:$D,D21,$E:$E,E21,$F:$F,"<>N/A",$G:$G,"<>N/A",$F:$F,"<="&_xlpm.p,$G:$G,">="&_xlpm.p)))))} -> 0.83333333 | I21: Pharmacia | J21: Remedios particulares. | K21: N/A | L21: N/A | M21: FMMP1826 | N21: F. Ratier, “Remèdes particuliers.” in Formulaire pratique des hôpitaux civils de Paris (Paris: J.-B. Baillière, 1823), 242–44. | O21: Reuse (Translation) | P21: France | R21: TRUE
A22: PSM1827s1v1 | B22: PSM1827.1.1.1-21 | C22: 01/1827 | D22: 1 | E22: 1 | F22: 120 | G22: 121 | H22: {=_xlfn.LET(_xlpm.s,IFERROR(--F22,""),_xlpm.e,IFERROR(--G22,""),IF(OR(_xlpm.s="",_xlpm.e="",_xlpm.e<_xlpm.s),"",_xlfn.LET(_xlpm.p,_xlfn.SEQUENCE(_xlpm.e-_xlpm.s+1,1,_xlpm.s,1),SUM(1/COUNTIFS($D:$D,D22,$E:$E,E22,$F:$F,"<>N/A",$G:$G,"<>N/A",$F:$F,"<="&_xlpm.p,$G:$G,">="&_xlpm.p)))))} -> 0.83333333 | I22: Pharmacia | J22: Vinho diureutico do Professor Corvisart (Hospital da Caridade). | K22: N/A | L22: N/A | M22: FMMP1826 | N22: F. Ratier, “Vin diurétique amer de la Charité.” in Formulaire pratique des hôpitaux civils de Paris (Paris: J.-B. Baillière, 1823), 247. | O22: Reuse (Translation) | P22: France | R22: TRUE
A23: PSM1827s1v1 | B23: PSM1827.1.1.1-22 | C23: 01/1827 | D23: 1 | E23: 1 | F23: 121 | G23: 121 | H23: {=_xlfn.LET(_xlpm.s,IFERROR(--F23,""),_xlpm.e,IFERROR(--G23,""),IF(OR(_xlpm.s="",_xlpm.e="",_xlpm.e<_xlpm.s),"",_xlfn.LET(_xlpm.p,_xlfn.SEQUENCE(_xlpm.e-_xlpm.s+1,1,_xlpm.s,1),SUM(1/COUNTIFS($D:$D,D23,$E:$E,E23,$F:$F,"<>N/A",$G:$G,"<>N/A",$F:$F,"<="&_xlpm.p,$G:$G,">="&_xlpm.p)))))} -> 0.33333333 | I23: Variedades Medicas | J23: Ligadura da arteria humeral. | K23: N/A | L23: N/A | M23: RMFE1826s1v1 | N23: "Ligature de l’artère humérale pour un anévrysme consécutif." Revue médicale française et étrangère (Paris) 1 (1826): 325. | O23: Reuse (Translation) | P23: France | R23: TRUE
A24: PSM1827s1v1 | B24: PSM1827.1.1.1-23 | C24: 01/1827 | D24: 1 | E24: 1 | F24: 121 | G24: 122 | H24: {=_xlfn.LET(_xlpm.s,IFERROR(--F24,""),_xlpm.e,IFERROR(--G24,""),IF(OR(_xlpm.s="",_xlpm.e="",_xlpm.e<_xlpm.s),"",_xlfn.LET(_xlpm.p,_xlfn.SEQUENCE(_xlpm.e-_xlpm.s+1,1,_xlpm.s,1),SUM(1/COUNTIFS($D:$D,D24,$E:$E,E24,$F:$F,"<>N/A",$G:$G,"<>N/A",$F:$F,"<="&_xlpm.p,$G:$G,">="&_xlpm.p)))))} -> 0.83333333 | I24: Variedades Medicas | J24: Operação do Phimosis. | K24: N/A | L24: N/A | M24: RMFE1826s1v1 | N24: "Operation du phimosis." Revue médicale française et étrangère (Paris) 1 (1826): 325. | O24: Reuse (Translation) | P24: France | R24: TRUE
A25: PSM1827s1v1 | B25: PSM1827.1.1.1-24 | C25: 01/1827 | D25: 1 | E25: 1 | F25: 122 | G25: 123 | H25: {=_xlfn.LET(_xlpm.s,IFERROR(--F25,""),_xlpm.e,IFERROR(--G25,""),IF(OR(_xlpm.s="",_xlpm.e="",_xlpm.e<_xlpm.s),"",_xlfn.LET(_xlpm.p,_xlfn.SEQUENCE(_xlpm.e-_xlpm.s+1,1,_xlpm.s,1),SUM(1/COUNTIFS($D:$D,D25,$E:$E,E25,$F:$F,"<>N/A",$G:$G,"<>N/A",$F:$F,"<="&_xlpm.p,$G:$G,">="&_xlpm.p)))))} -> 0.83333333 | I25: Variedades Medicas | J25: Sobre a vaccina. | K25: N/A | L25: Revue Medicale, Octobre 1825 | M25: RMFE1825s1v4 | N25: "Séance générale extraordinaire du 20 septembre." Revue médicale française et étrangère (Paris) 4 (1825): 168–174. | O25: Reuse (Translation) | P25: France | R25: TRUE
A26: PSM1827s1v1 | B26: PSM1827.1.1.1-25 | C26: 01/1827 | D26: 1 | E26: 1 | F26: 123 | G26: 123 | H26: {=_xlfn.LET(_xlpm.s,IFERROR(--F26,""),_xlpm.e,IFERROR(--G26,""),IF(OR(_xlpm.s="",_xlpm.e="",_xlpm.e<_xlpm.s),"",_xlfn.LET(_xlpm.p,_xlfn.SEQUENCE(_xlpm.e-_xlpm.s+1,1,_xlpm.s,1),SUM(1/COUNTIFS($D:$D,D26,$E:$E,E26,$F:$F,"<>N/A",$G:$G,"<>N/A",$F:$F,"<="&_xlpm.p,$G:$G,">="&_xlpm.p)))))} -> 0.33333333 | I26: Variedades Medicas | J26: Fistula Lacrymal. | K26: N/A | L26: N/A | M26: RMFE1826s1v1 | N26: "Fistule lacrymale." Revue médicale française et étrangère (Paris) 1 (1826): 325. | O26: Reuse (Translation) | P26: France | R26: TRUE
A27: PSM1827s1v1 | B27: PSM1827.1.1.1-26 | C27: 01/1827 | D27: 1 | E27: 1 | F27: 123 | G27: 124 | H27: {=_xlfn.LET(_xlpm.s,IFERROR(--F27,""),_xlpm.e,IFERROR(--G27,""),IF(OR(_xlpm.s="",_xlpm.e="",_xlpm.e<_xlpm.s),"",_xlfn.LET(_xlpm.p,_xlfn.SEQUENCE(_xlpm.e-_xlpm.s+1,1,_xlpm.s,1),SUM(1/COUNTIFS($D:$D,D27,$E:$E,E27,$F:$F,"<>N/A",$G:$G,"<>N/A",$F:$F,"<="&_xlpm.p,$G:$G,">="&_xlpm.p)))))} -> 0.83333333 | I27: Variedades Medicas | J27: Amputação do collo da madre. | K27: N/A | L27: N/A | M27: RMFE1826s1v1 | N27: "Amputation du col de la matrice." Revue médicale française et étrangère (Paris) 1 (1826): 325–326. | O27: Reuse (Translation) | P27: France | R27: TRUE
A28: PSM1827s1v1 | B28: PSM1827.1.1.1-27 | C28: 01/1827 | D28: 1 | E28: 1 | F28: 124 | G28: 124 | H28: {=_xlfn.LET(_xlpm.s,IFERROR(--F28,""),_xlpm.e,IFERROR(--G28,""),IF(OR(_xlpm.s="",_xlpm.e="",_xlpm.e<_xlpm.s),"",_xlfn.LET(_xlpm.p,_xlfn.SEQUENCE(_xlpm.e-_xlpm.s+1,1,_xlpm.s,1),SUM(1/COUNTIFS($D:$D,D28,$E:$E,E28,$F:$F,"<>N/A",$G:$G,"<>N/A",$F:$F,"<="&_xlpm.p,$G:$G,">="&_xlpm.p)))))} -> 0.5 | I28: Variedades Medicas | J28: Urethrotomo do Sr. Lisfranc. | K28: N/A | L28: N/A | M28: RMFE1826s1v1 | N28: "Séance du 29 décembre. Urétrotome." Revue médicale française et étrangère (Paris) 1 (1826): 325–326. | O28: Reuse (Translation) | P28: France | R28: TRUE
A29: PSM1827s1v1 | B29: PSM1827.1.1.1-28 | C29: 01/1827 | D29: 1 | E29: 1 | F29: 125 | G29: 126 | H29: {=_xlfn.LET(_xlpm.s,IFERROR(--F29,""),_xlpm.e,IFERROR(--G29,""),IF(OR(_xlpm.s="",_xlpm.e="",_xlpm.e<_xlpm.s),"",_xlfn.LET(_xlpm.p,_xlfn.SEQUENCE(_xlpm.e-_xlpm.s+1,1,_xlpm.s,1),SUM(1/COUNTIFS($D:$D,D29,$E:$E,E29,$F:$F,"<>N/A",$G:$G,"<>N/A",$F:$F,"<="&_xlpm.p,$G:$G,">="&_xlpm.p)))))} -> 2 | I29: Variedades Medicas | J29: Medicina Ingleza. | K29: N/A | L29: N/A | M29: AMP1826s1v9 | N29: "Médecine étrangère. Angleterre." Annales de la médecine physiologique (Paris) 9 (1826): 176–179. | O29: Adaptation | P29: France | Q29: The article summarizes the Broussais–Granville controversy by contrasting a French critique of English medicine with Granville’s defense of British practice as fact-based and clinically effective. | R29: TRUE
A30: PSM1827s1v1 | B30: PSM1827.1.1.1-29 | C30: 01/1827 | D30: 1 | E30: 1 | F30: 127 | G30: 129 | H30: {=_xlfn.LET(_xlpm.s,IFERROR(--F30,""),_xlpm.e,IFERROR(--G30,""),IF(OR(_xlpm.s="",_xlpm.e="",_xlpm.e<_xlpm.s),"",_xlfn.LET(_xlpm.p,_xlfn.SEQUENCE(_xlpm.e-_xlpm.s+1,1,_xlpm.s,1),SUM(1/COUNTIFS($D:$D,D30,$E:$E,E30,$F:$F,"<>N/A",$G:$G,"<>N/A",$F:$F,"<="&_xlpm.p,$G:$G,">="&_xlpm.p)))))} -> 3 | I30: Bibliographia Medica | J30: Obras de medicina publicadas em França em 1826. | K30: José Francisco Sigaud | L30: N/A | M30: N/A | N30: N/A | O30: Adaptation | P30: France | Q30: Bibliographic notes summarising newly published French medical books, likely compiled from Parisian publishers’ catalogues. | R30: TRUE
A31: PSM1827s1v1 | B31: PSM1827.1.1.1-30 | C31: 01/1827 | D31: 1 | E31: 1 | F31: 130 | G31: 131 | H31: {=_xlfn.LET(_xlpm.s,IFERROR(--F31,""),_xlpm.e,IFERROR(--G31,""),IF(OR(_xlpm.s="",_xlpm.e="",_xlpm.e<_xlpm.s),"",_xlfn.LET(_xlpm.p,_xlfn.SEQUENCE(_xlpm.e-_xlpm.s+1,1,_xlpm.s,1),SUM(1/COUNTIFS($D:$D,D31,$E:$E,E31,$F:$F,"<>N/A",$G:$G,"<>N/A",$F:$F,"<="&_xlpm.p,$G:$G,">="&_xlpm.p)))))} -> 1.5 | I31: Bibliographia Medica | J31: Obras publicadas em Inglaterra em 1826. | K31: José Francisco Sigaud | L31: N/A | M31: N/A | N31: N/A | O31: Adaptation | P31: United Kingdom | Q31: Bibliographic notes summarising newly published English medical books, likely compiled from publishers’ catalogues. | R31: TRUE
A32: PSM1827s1v1 | B32: PSM1827.1.1.1-31 | C32: 01/1827 | D32: 1 | E32: 1 | F32: 131 | G32: 133 | H32: {=_xlfn.LET(_xlpm.s,IFERROR(--F32,""),_xlpm.e,IFERROR(--G32,""),IF(OR(_xlpm.s="",_xlpm.e="",_xlpm.e<_xlpm.s),"",_xlfn.LET(_xlpm.p,_xlfn.SEQUENCE(_xlpm.e-_xlpm.s+1,1,_xlpm.s,1),SUM(1/COUNTIFS($D:$D,D32,$E:$E,E32,$F:$F,"<>N/A",$G:$G,"<>N/A",$F:$F,"<="&_xlpm.p,$G:$G,">="&_xlpm.p)))))} -> 2 | I32: Boletim das Sciencias Naturaes | J32: Historia Natural e medica do Agrião do Pará. | K32: N/A | L32: N/A | M32: JCMP1825s1v1 | N32: "Académia Royale de Médecine. Section de Pharmacie. 5 avril." Journal de chimie médicale, de pharmacie et de toxicologie (Paris) 1, no. 5 (May 1825): 261-262. | O32: Adaptation | P32: France | R32: TRUE
A33: PSM1827s1v1 | B33: PSM1827.1.1.1-32 | C33: 01/1827 | D33: 1 | E33: 1 | F33: 133 | G33: 133 | H33: {=_xlfn.LET(_xlpm.s,IFERROR(--F33,""),_xlpm.e,IFERROR(--G33,""),IF(OR(_xlpm.s="",_xlpm.e="",_xlpm.e<_xlpm.s),"",_xlfn.LET(_xlpm.p,_xlfn.SEQUENCE(_xlpm.e-_xlpm.s+1,1,_xlpm.s,1),SUM(1/COUNTIFS($D:$D,D33,$E:$E,E33,$F:$F,"<>N/A",$G:$G,"<>N/A",$F:$F,"<="&_xlpm.p,$G:$G,">="&_xlpm.p)))))} -> 0.5 | I33: Boletim das Sciencias Naturaes | J33: Cultura do Chá no Brasil. | K33: N/A | L33: N/A | M33: N/A | N33: N/A | O33: Local | P33: Brazil | R33: TRUE
A34: PSM1827s1v1 | B34: PSM1827.1.1.1-33 | C34: 01/1827 | D34: 1 | E34: 1 | F34: 134 | G34: 134 | H34: {=_xlfn.LET(_xlpm.s,IFERROR(--F34,""),_xlpm.e,IFERROR(--G34,""),IF(OR(_xlpm.s="",_xlpm.e="",_xlpm.e<_xlpm.s),"",_xlfn.LET(_xlpm.p,_xlfn.SEQUENCE(_xlpm.e-_xlpm.s+1,1,_xlpm.s,1),SUM(1/COUNTIFS($D:$D,D34,$E:$E,E34,$F:$F,"<>N/A",$G:$G,"<>N/A",$F:$F,"<="&_xlpm.p,$G:$G,">="&_xlpm.p)))))} -> 1 | I34: Boletim das Sciencias Naturaes | J34: Palma Christi d’America. | K34: N/A | L34: N/A | M34: N/A | N34: N/A | O34: Local | P34: Brazil | R34: TRUE
A35: PSM1827s1v1 | B35: PSM1827.1.1.1-34 | C35: 01/1827 | D35: 1 | E35: 1 | F35: 135 | G35: 135 | H35: {=_xlfn.LET(_xlpm.s,IFERROR(--F35,""),_xlpm.e,IFERROR(--G35,""),IF(OR(_xlpm.s="",_xlpm.e="",_xlpm.e<_xlpm.s),"",_xlfn.LET(_xlpm.p,_xlfn.SEQUENCE(_xlpm.e-_xlpm.s+1,1,_xlpm.s,1),SUM(1/COUNTIFS($D:$D,D35,$E:$E,E35,$F:$F,"<>N/A",$G:$G,"<>N/A",$F:$F,"<="&_xlpm.p,$G:$G,">="&_xlpm.p)))))} -> 0.5 | I35: Boletim das Sciencias Naturaes | J35: Analyse do Fedegoso. | K35: N/A | L35: N/A | M35: JPSA1824s1v10 | N35: "Analyse d'une écorce apportée du Brésil, désignée sous le nom de Fédégoso." Journal de pharmacie et des sciences accessoires (Paris) 10 (1824): 217–223. | O35: Adaptation | P35: France | R35: TRUE
A36: PSM1827s1v1 | B36: PSM1827.1.1.1-35 | C36: 01/1827 | D36: 1 | E36: 1 | F36: 135 | G36: 136 | H36: {=_xlfn.LET(_xlpm.s,IFERROR(--F36,""),_xlpm.e,IFERROR(--G36,""),IF(OR(_xlpm.s="",_xlpm.e="",_xlpm.e<_xlpm.s),"",_xlfn.LET(_xlpm.p,_xlfn.SEQUENCE(_xlpm.e-_xlpm.s+1,1,_xlpm.s,1),SUM(1/COUNTIFS($D:$D,D36,$E:$E,E36,$F:$F,"<>N/A",$G:$G,"<>N/A",$F:$F,"<="&_xlpm.p,$G:$G,">="&_xlpm.p)))))} -> 1 | I36: Boletim das Sciencias Naturaes | J36: Sociedade Linneanna | K36: N/A | L36: N/A | M36: N/A | N36: N/A | O36: Local | P36: Brazil | R36: TRUE
A37: PSM1827s1v1 | B37: PSM1827.1.1.1-36 | C37: 01/1827 | D37: 1 | E37: 1 | F37: 136 | G37: 141 | H37: {=_xlfn.LET(_xlpm.s,IFERROR(--F37,""),_xlpm.e,IFERROR(--G37,""),IF(OR(_xlpm.s="",_xlpm.e="",_xlpm.e<_xlpm.s),"",_xlfn.LET(_xlpm.p,_xlfn.SEQUENCE(_xlpm.e-_xlpm.s+1,1,_xlpm.s,1),SUM(1/COUNTIFS($D:$D,D37,$E:$E,E37,$F:$F,"<>N/A",$G:$G,"<>N/A",$F:$F,"<="&_xlpm.p,$G:$G,">="&_xlpm.p)))))} -> 5.5 | I37: Boletim das Sciencias Naturaes | J37: Noticia sobre M. de Lacépède. | K37: José Francisco Sigaud | L37: N/A | M37: RMFE1825s1v4 | N37: Fortenelle, Julia. "Notice historique sur M. Le Comte de Lacépède." Revue médicale française et étrangère (Paris) 4 (November 1825): 351–359. | O37: Reuse (Translation) | P37: France | R37: TRUE
A38: PSM1827s1v1 | B38: PSM1827.1.1.1-37 | C38: 01/1827 | D38: 1 | E38: 1 | F38: 142 | G38: 142 | H38: {=_xlfn.LET(_xlpm.s,IFERROR(--F38,""),_xlpm.e,IFERROR(--G38,""),IF(OR(_xlpm.s="",_xlpm.e="",_xlpm.e<_xlpm.s),"",_xlfn.LET(_xlpm.p,_xlfn.SEQUENCE(_xlpm.e-_xlpm.s+1,1,_xlpm.s,1),SUM(1/COUNTIFS($D:$D,D38,$E:$E,E38,$F:$F,"<>N/A",$G:$G,"<>N/A",$F:$F,"<="&_xlpm.p,$G:$G,">="&_xlpm.p)))))} -> 1 | I38: Boletim das Sciencias Naturaes | J38: Explicação da Estampa. | K38: N/A | L38: N/A | M38: N/A | N38: Burguet. "Observations sur les maladies des organes génito-urinaires; par M. F. Lallemand, prof. de clinique chirurgicale à la Faculté de med. de Montpellier. Premérie Partie : Des rétrécissemens de l'urètre. — Un vol. in-8°. de iij-22o pag. Paris, 1825 (i)." Journal médical de la Gironde (Bordeaux) 4 (1825): 255–264. | O38: Reuse (Translation) | P38: France | R38: TRUE
A39: PSM1827s1v1 | B39: PSM1827.1.1.2-38 | C39: 02/1827 | D39: 1 | E39: 2 | F39: 143 | G39: 158 | H39: {=_xlfn.LET(_xlpm.s,IFERROR(--F39,""),_xlpm.e,IFERROR(--G39,""),IF(OR(_xlpm.s="",_xlpm.e="",_xlpm.e<_xlpm.s),"",_xlfn.LET(_xlpm.p,_xlfn.SEQUENCE(_xlpm.e-_xlpm.s+1,1,_xlpm.s,1),SUM(1/COUNTIFS($D:$D,D39,$E:$E,E39,$F:$F,"<>N/A",$G:$G,"<>N/A",$F:$F,"<="&_xlpm.p,$G:$G,">="&_xlpm.p)))))} -> 15.5 | I39: Medicina | J39: Considerações sobre a séde, natureza, e o tratamento do tétanos, por M.A. Bonnet. D. M. | K39: Bonnet | L39: N/A | M39: JMG1824s1v1 | N39: Bonnet. “Du siège, de la nature et du traitement du tétanos.” Journal médical de la Gironde (Bordeaux) 3 (1825): 349–74. | O39: Reuse (Translation) | P39: France | R39: TRUE
A40: PSM1827s1v1 | B40: PSM1827.1.1.2-39 | C40: 02/1827 | D40: 1 | E40: 2 | F40: 158 | G40: 161 | H40: {=_xlfn.LET(_xlpm.s,IFERROR(--F40,""),_xlpm.e,IFERROR(--G40,""),IF(OR(_xlpm.s="",_xlpm.e="",_xlpm.e<_xlpm.s),"",_xlfn.LET(_xlpm.p,_xlfn.SEQUENCE(_xlpm.e-_xlpm.s+1,1,_xlpm.s,1),SUM(1/COUNTIFS($D:$D,D40,$E:$E,E40,$F:$F,"<>N/A",$G:$G,"<>N/A",$F:$F,"<="&_xlpm.p,$G:$G,">="&_xlpm.p)))))} -> 3.5 | I40: Medicina | J40: Extracto das sessões da Academia de Medicina e de Cirurgia de Paris. | K40: N/A | L40: N/A | M40: RMFE1826s1v1 | N40: “Académie royale de médecine — Séance de médecine (13 décembre): Ventouses sur les plaies empoisonnées.” Revue médicale française et étrangère (Paris) 2 (February 1826): 167–184. | O40: Reuse (Translation) | P40: France | R40: TRUE
A41: PSM1827s1v1 | B41: PSM1827.1.1.2-40 | C41: 02/1827 | D41: 1 | E41: 2 | F41: 162 | G41: 188 | H41: {=_xlfn.LET(_xlpm.s,IFERROR(--F41,""),_xlpm.e,IFERROR(--G41,""),IF(OR(_xlpm.s="",_xlpm.e="",_xlpm.e<_xlpm.s),"",_xlfn.LET(_xlpm.p,_xlfn.SEQUENCE(_xlpm.e-_xlpm.s+1,1,_xlpm.s,1),SUM(1/COUNTIFS($D:$D,D41,$E:$E,E41,$F:$F,"<>N/A",$G:$G,"<>N/A",$F:$F,"<="&_xlpm.p,$G:$G,">="&_xlpm.p)))))} -> 27 | I41: Medicina | J41: Relação historica da Enfermidade do Ill.mo Snr. Brigadeiro Luiz Pereira da Nobrega de Souza Coutinho, Presidente da Camara dos Deputados do Imperio do Brasil, Ajudante de Campo de S. M. o Imperador, etc. etc.; seguida da Refutação das Cartas do Doutor José Maria Bontempo; por J. F. Sigaud, D. M. e R. P. | K41: José Francisco Sigaud | L41: N/A | M41: N/A | N41: N/A | O41: Local | P41: Brazil | R41: TRUE
A42: PSM1827s1v1 | B42: PSM1827.1.1.2-41 | C42: 02/1827 | D42: 1 | E42: 2 | F42: 189 | G42: 191 | H42: {=_xlfn.LET(_xlpm.s,IFERROR(--F42,""),_xlpm.e,IFERROR(--G42,""),IF(OR(_xlpm.s="",_xlpm.e="",_xlpm.e<_xlpm.s),"",_xlfn.LET(_xlpm.p,_xlfn.SEQUENCE(_xlpm.e-_xlpm.s+1,1,_xlpm.s,1),SUM(1/COUNTIFS($D:$D,D42,$E:$E,E42,$F:$F,"<>N/A",$G:$G,"<>N/A",$F:$F,"<="&_xlpm.p,$G:$G,">="&_xlpm.p)))))} -> 2.5 | I42: Medicina | J42: Autopsia cadaverica. | K42: N/A | L42: N/A | M42: N/A | N42: N/A | O42: Local | P42: Brazil | R42: TRUE
A43: PSM1827s1v1 | B43: PSM1827.1.1.2-42 | C43: 02/1827 | D43: 1 | E43: 2 | F43: 191 | G43: 199 | H43: {=_xlfn.LET(_xlpm.s,IFERROR(--F43,""),_xlpm.e,IFERROR(--G43,""),IF(OR(_xlpm.s="",_xlpm.e="",_xlpm.e<_xlpm.s),"",_xlfn.LET(_xlpm.p,_xlfn.SEQUENCE(_xlpm.e-_xlpm.s+1,1,_xlpm.s,1),SUM(1/COUNTIFS($D:$D,D43,$E:$E,E43,$F:$F,"<>N/A",$G:$G,"<>N/A",$F:$F,"<="&_xlpm.p,$G:$G,">="&_xlpm.p)))))} -> 8 | I43: Cirurgia | J43: Memoria sobre o labio leporino. | K43: Francisco José Alypio | L43: N/A | M43: N/A | N43: N/A | O43: Local | P43: Brazil | R43: TRUE
... A57: PSM1827s1v1 | B57: PSM1827.1.1.2-56 | C57: 02/1827 | D57: 1 | E57: 2 | F57: 237 | G57: 241 | H57: {=_xlfn.LET(_xlpm.s,IFERROR(--F57,""),_xlpm.e,IFERROR(--G57,""),IF(OR(_xlpm.s="",_xlpm.e="",_xlpm.e<_xlpm.s),"",_xlfn.LET(_xlpm.p,_xlfn.SEQUENCE(_xlpm.e-_xlpm.s+1,1,_xlpm.s,1),SUM(1/COUNTIFS($D:$D,D57,$E:$E,E57,$F:$F,"<>N/A",$G:$G,"<>N/A",$F:$F,"<="&_xlpm.p,$G:$G,">="&_xlpm.p)))))} -> 4.5 | I57: Variedades Medicas | J57: Extracto do elogio de Corvisart, recitado por M. Pariset. | K57: M. Pariset | L57: N/A | M57: RMFE1824s1v3 | N57: "Séance publique de la section de médecine." Revue médicale française et étrangère (Paris) 3 (1824): 313–325. | O57: Adaptation | P57: France | R57: TRUE
A58: PSM1827s1v1 | B58: PSM1827.1.1.2-57 | C58: 02/1827 | D58: 1 | E58: 2 | F58: 241 | G58: 243 | H58: {=_xlfn.LET(_xlpm.s,IFERROR(--F58,""),_xlpm.e,IFERROR(--G58,""),IF(OR(_xlpm.s="",_xlpm.e="",_xlpm.e<_xlpm.s),"",_xlfn.LET(_xlpm.p,_xlfn.SEQUENCE(_xlpm.e-_xlpm.s+1,1,_xlpm.s,1),SUM(1/COUNTIFS($D:$D,D58,$E:$E,E58,$F:$F,"<>N/A",$G:$G,"<>N/A",$F:$F,"<="&_xlpm.p,$G:$G,">="&_xlpm.p)))))} -> 2 | I58: Variedades Medicas | J58: Revista dos Jornaes de Medicina Inglezes. | K58: N/A | L58: N/A | M58: N/A | N58: N/A | O58: Adaptation | P58: United Kingdom | Q58: The piece explicitly says it is a review of English journals and then retells Dr Walter’s transfusion case in its own words. | R58: TRUE
A59: PSM1827s1v1 | B59: PSM1827.1.1.2-58 | C59: 02/1827 | D59: 1 | E59: 2 | F59: 243 | G59: 244 | H59: {=_xlfn.LET(_xlpm.s,IFERROR(--F59,""),_xlpm.e,IFERROR(--G59,""),IF(OR(_xlpm.s="",_xlpm.e="",_xlpm.e<_xlpm.s),"",_xlfn.LET(_xlpm.p,_xlfn.SEQUENCE(_xlpm.e-_xlpm.s+1,1,_xlpm.s,1),SUM(1/COUNTIFS($D:$D,D59,$E:$E,E59,$F:$F,"<>N/A",$G:$G,"<>N/A",$F:$F,"<="&_xlpm.p,$G:$G,">="&_xlpm.p)))))} -> 1 | I59: Variedades Medicas | J59: Prenhez na trompa de Fallopio. | K59: N/A | L59: N/A | M59: RMFE1826s1v1 | N59: "Grossesse dans la trompe de Fallope." Revue médicale française et étrangère (Paris) 1 (February 1826): 295–286. | O59: Reuse (Translation) | P59: France | R59: TRUE
A60: PSM1827s1v1 | B60: PSM1827.1.1.2-59 | C60: 02/1827 | D60: 1 | E60: 2 | F60: 244 | G60: 246 | H60: {=_xlfn.LET(_xlpm.s,IFERROR(--F60,""),_xlpm.e,IFERROR(--G60,""),IF(OR(_xlpm.s="",_xlpm.e="",_xlpm.e<_xlpm.s),"",_xlfn.LET(_xlpm.p,_xlfn.SEQUENCE(_xlpm.e-_xlpm.s+1,1,_xlpm.s,1),SUM(1/COUNTIFS($D:$D,D60,$E:$E,E60,$F:$F,"<>N/A",$G:$G,"<>N/A",$F:$F,"<="&_xlpm.p,$G:$G,">="&_xlpm.p)))))} -> 2 | I60: Variedades Medicas | J60: Sobre as curvaduras lateraes da Espinha. | K60: N/A | L60: N/A | M60: RMFE1825s1v4 | N60: "X. Sur les courbures latérales de l’épine et sur les corsets par lesquels on y remédie. — M. Shaw, dont nous avons." Revue médicale française et étrangère (Paris) 4 (November 1825): 327–330. | O60: Reuse (Translation) | P60: France | R60: TRUE
A61: PSM1827s1v1 | B61: PSM1827.1.1.2-60 | C61: 02/1827 | D61: 1 | E61: 2 | F61: 246 | G61: 248 | H61: {=_xlfn.LET(_xlpm.s,IFERROR(--F61,""),_xlpm.e,IFERROR(--G61,""),IF(OR(_xlpm.s="",_xlpm.e="",_xlpm.e<_xlpm.s),"",_xlfn.LET(_xlpm.p,_xlfn.SEQUENCE(_xlpm.e-_xlpm.s+1,1,_xlpm.s,1),SUM(1/COUNTIFS($D:$D,D61,$E:$E,E61,$F:$F,"<>N/A",$G:$G,"<>N/A",$F:$F,"<="&_xlpm.p,$G:$G,">="&_xlpm.p)))))} -> 2 | I61: Variedades Medicas | J61: Revista dos Jornaes de medicina Francezes. | K61: N/A | L61: Journal Complementaire des Sciences Medicales | M61: RMFE1825s1v4 | N61: "Revue des journaux de médecine Français." Revue médicale française et étrangère (Paris) 4 (1825): 463–475. | O61: Adaptation | P61: France | R61: TRUE
A62: PSM1827s1v1 | B62: PSM1827.1.1.2-61 | C62: 02/1827 | D62: 1 | E62: 2 | F62: 248 | G62: 254 | H62: {=_xlfn.LET(_xlpm.s,IFERROR(--F62,""),_xlpm.e,IFERROR(--G62,""),IF(OR(_xlpm.s="",_xlpm.e="",_xlpm.e<_xlpm.s),"",_xlfn.LET(_xlpm.p,_xlfn.SEQUENCE(_xlpm.e-_xlpm.s+1,1,_xlpm.s,1),SUM(1/COUNTIFS($D:$D,D62,$E:$E,E62,$F:$F,"<>N/A",$G:$G,"<>N/A",$F:$F,"<="&_xlpm.p,$G:$G,">="&_xlpm.p)))))} -> 6 | I62: Bibliographia Medica | J62: Bibliographia Classica Medica. | K62: N/A | L62: Zimmermann, traité de l'experience | M62: AMP1827s1v11 | N62: "Annonces d’ouvrages nouveaux." Annales de la médecine physiologique (Paris) 11 (1827): 1–16. | O62: Adaptation | P62: France | R62: TRUE
A63: PSM1827s1v1 | B63: PSM1827.1.1.2-62 | C63: 02/1827 | D63: 1 | E63: 2 | F63: 254 | G63: 255 | H63: {=_xlfn.LET(_xlpm.s,IFERROR(--F63,""),_xlpm.e,IFERROR(--G63,""),IF(OR(_xlpm.s="",_xlpm.e="",_xlpm.e<_xlpm.s),"",_xlfn.LET(_xlpm.p,_xlfn.SEQUENCE(_xlpm.e-_xlpm.s+1,1,_xlpm.s,1),SUM(1/COUNTIFS($D:$D,D63,$E:$E,E63,$F:$F,"<>N/A",$G:$G,"<>N/A",$F:$F,"<="&_xlpm.p,$G:$G,">="&_xlpm.p)))))} -> 1 | I63: Boletim das Sciencias Naturaes | J63: Zoologia. | K63: N/A | L63: N/A | M63: AMP1827s1v11 | N63: "Annonces d’ouvrages nouveaux." Annales de la médecine physiologique (Paris) 11 (1827): 1–16. | O63: Adaptation | P63: France | R63: TRUE
A64: PSM1827s1v1 | B64: PSM1827.1.1.2-63 | C64: 02/1827 | D64: 1 | E64: 2 | F64: 255 | G64: 256 | H64: {=_xlfn.LET(_xlpm.s,IFERROR(--F64,""),_xlpm.e,IFERROR(--G64,""),IF(OR(_xlpm.s="",_xlpm.e="",_xlpm.e<_xlpm.s),"",_xlfn.LET(_xlpm.p,_xlfn.SEQUENCE(_xlpm.e-_xlpm.s+1,1,_xlpm.s,1),SUM(1/COUNTIFS($D:$D,D64,$E:$E,E64,$F:$F,"<>N/A",$G:$G,"<>N/A",$F:$F,"<="&_xlpm.p,$G:$G,">="&_xlpm.p)))))} -> 1 | I64: Boletim das Sciencias Naturaes | J64: Noticia sobre a quina do Brasil. | K64: N/A | L64: N/A | M64: N/A | N64: N/A | O64: Local | P64: Brazil | R64: TRUE
A65: PSM1827s1v1 | B65: PSM1827.1.1.2-64 | C65: 02/1827 | D65: 1 | E65: 2 | F65: 256 | G65: 258 | H65: {=_xlfn.LET(_xlpm.s,IFERROR(--F65,""),_xlpm.e,IFERROR(--G65,""),IF(OR(_xlpm.s="",_xlpm.e="",_xlpm.e<_xlpm.s),"",_xlfn.LET(_xlpm.p,_xlfn.SEQUENCE(_xlpm.e-_xlpm.s+1,1,_xlpm.s,1),SUM(1/COUNTIFS($D:$D,D65,$E:$E,E65,$F:$F,"<>N/A",$G:$G,"<>N/A",$F:$F,"<="&_xlpm.p,$G:$G,">="&_xlpm.p)))))} -> 2.5 | I65: Boletim das Sciencias Naturaes | J65: Trabalhos d'Historia natural devido à Vicq-d'Azir. | K65: N/A | L65: N/A | M65: AMP1827s1v11 | N65: "Homme (Homo), article extrait du tome VIII du Ditionnaire classique d'histoire naturelle; par M. le colonel Bory de Saint-Vincent. In-8°. A Paris, chez Rey et Gravier, libraires-éditeurs, quai des Augustins, n° 55; et chez mademoiselle Delaunay, rue Saint-Jacques, n.° 71." Annales de la médecine physiologique (Paris) 11 (1827): 8–9. | O65: Reuse (Translation) | P65: France | R65: TRUE
A66: PSM1827s1v1 | B66: PSM1827.1.1.2-65 | C66: 02/1827 | D66: 1 | E66: 2 | F66: 259 | G66: 287 | H66: {=_xlfn.LET(_xlpm.s,IFERROR(--F66,""),_xlpm.e,IFERROR(--G66,""),IF(OR(_xlpm.s="",_xlpm.e="",_xlpm.e<_xlpm.s),"",_xlfn.LET(_xlpm.p,_xlfn.SEQUENCE(_xlpm.e-_xlpm.s+1,1,_xlpm.s,1),SUM(1/COUNTIFS($D:$D,D66,$E:$E,E66,$F:$F,"<>N/A",$G:$G,"<>N/A",$F:$F,"<="&_xlpm.p,$G:$G,">="&_xlpm.p)))))} -> 29 | I66: N/A | J66: Resposta ao Snr. J. M. Bomtempo | K66: José Francisco Sigaud | L66: N/A | M66: N/A | N66: N/A | O66: Local | P66: Brazil | R66: TRUE
